Workbook
Name ReservaLegal: Caratula!$24:$24
Name Capital: Caratula!$22:$22
Name PasivoNoCorr: Caratula!$19:$19
Name high: Altman!$D$4:$D$11
Name zeta4: Caratula!$59:$59
Name OtrosPatrimonio: Caratula!$23:$23
Name ROA: Caratula!$44:$44
Name CTrabajo: Caratula!$30:$30
Name RotaInventarios: Caratula!$33:$33
Name ApalancaBca: Caratula!$40:$40
Name altman2: Altman!$I$4:$I$11
Name ROE: Caratula!$43:$43
Name CrecVentas: Caratula!$42:$42
Name izsel: Caratula!$C$62:$C$69
Name Acida: Caratula!$29:$29
Name Cajaendias: Caratula!$36:$36
Name altman4: Altman!$K$4:$K$11
Name PasivoTotal: Caratula!$20:$20
Name PasivoCorr: Caratula!$18:$18
Name Liquidez: Caratula!$28:$28
Name zeta3: Caratula!$58:$58
Name ApalancaCom: Caratula!$41:$41
Name UtilidadRetenida: Caratula!$25:$25
Name Cobrodias: Caratula!$32:$32
Name low: Altman!$C$4:$C$11
Name zeta5: Caratula!$60:$60
Name ActivoCorr: Caratula!$13:$13
Name altman3: Altman!$J$4:$J$11
Name altman1: Altman!$H$4:$H$11
Name UtilidadNeta: Caratula!$11:$11
Name Inventarios: Balance!$18:$18
Name Patrimonio: Caratula!$26:$26
Name Ventas: Caratula!$10:$10
Name altman5: Altman!$L$4:$L$11
Name Apalancamiento: Caratula!$39:$39
Name ActivoTotal: Caratula!$16:$16
Name EBITDA: Caratula!$37:$37
Name zeta2: Caratula!$57:$57
Name sel: Caratula!$B$71
Name ActivoNoCorr: Caratula!$14:$14
Name ActDiferido: Caratula!$15:$15
Name Pagoendias: Caratula!$34:$34
Name zeta1: Caratula!$56:$56

Sheet Caratula
D1: LU3-American Medical Enterprises | K1: LU4-Novoswiss PFJuridica | Q1: LU2-Luminova PFJuridica | V1: LU1-Helvetia PFJuridica | AA1: ETI-Corp Etisa 2025 vf | AF1: Bahía Colorada | AJ1: Soluciones Carnicas | AM1: Servicios y Perecederos | AQ1: Quimica Total | AU1: Logistica Nave | AY1: Inversiones Iginia | BD1: Ing_Palo_Gordo | BI1: Distribuidora Me Llega | BM1: Corinco | BQ1: Inversiones Mapakhan, S.A. | BT1: Corporación Mogori
D2: 2020 | E2: 2021 | F2: 2022 | G2: 2023 | H2: 2024 | J2: 2020 | K2: 2021 | L2: 2022 | M2: 2023 | N2: 2024 | P2: 2020 | Q2: 2021 | R2: 2022 | S2: 2023 | T2: 2024 | V2: 2021 | W2: 2022 | X2: 2023 | Y2: 2024 | AA2: 2021 | AB2: 2022 | AC2: 2023 | AD2: 2024 | AF2: 2021 | AG2: 2022 | AH2: 2023 | AJ2: 2022 | AK2: 2023 | AM2: 2021 | AN2: 2022 | AO2: 2023 | AQ2: 2022 | AR2: 2023 | AS2: 2024 | AU2: 2022 | AV2: 2023 | AW2: 2024 | AY2: 2020 | AZ2: 2021 | BA2: 2022 | BB2: 2023 | BD2: 2021 | BE2: 2022 | BF2: 2023 | BG2: 2024 | BI2: 2022 | BJ2: 2023 | BK2: 2024 | BM2: 2021 | BN2: 2022 | BO2: 2023 | BQ2: 2021 | BR2: 2022 | BT2: 2021 | BU2: 2022 | BV2: 2023
D3: Auditado | E3: Auditado | F3: Auditado | G3: Auditado | H3: Admin. | J3: Auditado | K3: Auditado | L3: Auditado | M3: Auditado | N3: Admin. | P3: Auditado | Q3: Auditado | R3: Auditado | S3: Admin. | T3: Admin. | V3: Auditado | W3: Auditado | X3: Auditado | Y3: Admin. | AA3: Pendiente | AB3: Auditado | AC3: Auditado | AD3: Admin. | AF3: Auditado | AG3: Auditado | AH3: Administrativo | AJ3: Administrativo | AK3: Administrativo | AM3: Auditado | AN3: Auditado | AO3: Administrativo | AQ3: Administrativo | AR3: Administrativo | AS3: Administrativo | AU3: Auditado | AV3: Auditado | AW3: Administrativo | AY3: Auditado | AZ3: Auditado | BA3: Auditado | BB3: Auditado | BD3: Auditado | BE3: Auditado | BF3: Auditado | BG3: Administrativo | BI3: Auditado | BJ3: Auditado | BK3: Administrativo | BM3: Administrativo | BN3: Administrativo | BO3: Administrativo | BQ3: Administrativo | BR3: Administrativo | BT3: Administrativo | BU3: Administrativo | BV3: Administrativo
A5: NOMBRE DEL CLIENTE: | D5: LU3-American Medical Enterprises | K5: LU4-Novoswiss PFJuridica | Q5: LU2-Luminova PFJuridica | V5: LU1-Helvetia PFJuridica | AA5: ETI-Corp Etisa 2025 vf | AF5: Bahía Colorada, S.A. | AJ5: Soluciones Carnicas de Guatemala, S.A. | AM5: Servicios y Perecederos | AQ5: QUIMICA TOTAL, S.A. | AU5: LOGISTICA NAVE, S.A. | AY5: INVERSIONES IGINLA, S.A. | BD5: Ingenio Palo Gordo, S.A. | BI5: Distribuidora Me Llega, S.A. | BM5: Corinco, S.A. | BQ5: Inversiones Mapakhan, S.A.
A6: GIRO DEL NEGOCIO: | J6: Importación, exportación, fabricación y distribución de toda clase de medicamentos | P6: Venta de medicamentos | V6: Importación, fabricación y distribución de medicamentos y productos dietéticos | AA6: Impresión de etiquetas, viñetas o cualquier clase de impresión | AF6: Planificación, desarrollo, ejecución y promoción de urbanizaciones, lotificaciones | AJ6: Venta de productos carnicos | AQ6: INDUSTRIA DE QUIMICOS | AU6: Prestación de servicios de importación, bodegas, maquila y logistica de todo tipo de productos. | AY6: Compra, venta y distibución e importación de accesorios, respuestos y máquinaria para industria automotriz. | BD6: Tiene como actividad principal la fabricación y venta loca y del exterior de acucar, melaza y alcohol, los cuales son productos del proceso de la caña de azucar. Así como la cogeneración y venta de energía electríca. | BI6: Compra, venta y comercialización de productos alimenticios, de belleza, de hogar. | BM6: Producción de empaques plasticos de agroindustrua y comercio | BQ6: Importación, exportacion, maquila, comercializacion y venta de todo tipo de Juguetes y de juegos.
A7: EN MILES DE: | D7: Dólares | J7: QUETZALES | P7: QUETZALES | V7: QUETZALES | AA7: QUETZALES | AF7: QUETZALES | AJ7: QUETZALES | AQ7: QUETZALES | AU7: QUETZALES | AY7: QUETZALES | BD7: QUETZALES | BI7: QUETZALES | BM7: QUETZALES | BQ7: QUETZALES
A8: FIRMA DE AUDITORIA (O CONTADOR): | D8: Axel Samuel Rosas | J8: Axel Samuel Rosas | P8: Axel Samuel Rosas | V8: Axel Samuel Rosas | AA8: Mynor Armando Alacan Morales | AF8: Lic. Edwin R. Hernandez B. | AJ8: Hugo Waldermar Sutuj Chamale | AQ8: Jorge Eduardo Motta Morales | AU8: Nexia | AY8: Lic. Oscar Saul Rodríguez Lemus | BD8: PKF | BI8: Nexia | BM8: Miguel Miculax Olcot | BQ8: Sergio Armando Mancilla López
A10: Ventas | D10: 23930.151 | E10: 23578.78 | F10: 29792.243 | G10: 32768.103 | H10: 24145.584 | J10: 337466 | K10: 330048 | L10: 360978.12 | M10: 419772.2 | N10: 312105.95 | P10: 4317 | Q10: 70441.169 | R10: 103822.19 | S10: 109585.88 | T10: 75793.976 | V10: 20425.762 | W10: 33740.045 | X10: 42955.437 | Y10: 33868.198 | AA10: 0 | AB10: 39281.699 | AC10: 52097.658 | AD10: 54416.681 | AF10: 0 | AG10: 84.33 | AH10: 41.09 | AJ10: 0 | AK10: 7801.0852 | AM10: 78485.195 | AN10: 87117.634 | AO10: 44163.718 | AQ10: 82237.533 | AR10: 68840.543 | AS10: 19674.964 | AU10: 121315.38 | AV10: 202588.23 | AW10: 261570.89 | AY10: 5447.2655 | AZ10: 2139.0766 | BA10: 11106.372 | BB10: 24713.03 | BD10: 866642.62 | BE10: 1060188.4 | BF10: 1102452.7 | BG10: 965922.81 | BI10: 1222964.8 | BJ10: 1675859.3 | BK10: 2072384.5 | BM10: 15793.657 | BN10: 20165.228 | BO10: 24153.542 | BQ10: 2842.924 | BR10: 4509.4649 | BT10: 14171.65 | BU10: 22085.897 | BV10: 25741.048
A11: Utilidad Neta | D11: 14418.686 | E11: 2893.883 | F11: 5234.476 | G11: 6219.504 | H11: 3790.438 | J11: 19435 | K11: 21414 | L11: 16122.97 | M11: 7214.951 | N11: 2151.953 | P11: -2996 | Q11: 1275.956 | R11: 2586.204 | S11: 4571.311 | T11: -2835.862 | V11: -35.504 | W11: -2708.358 | X11: 711.661 | Y11: 1111.626 | AA11: 0 | AB11: 1160.272 | AC11: 887.238 | AD11: 2968.52 | AF11: -0.28 | AG11: 5.53129 | AH11: 1.85184 | AJ11: -519.13544 | AK11: 1232.1515 | AM11: 4380.6467 | AN11: 4565.6092 | AO11: 2065.929 | AQ11: 7054.376 | AR11: 4141.618 | AS11: 1335.7 | AU11: 12848.287 | AV11: 23613.1 | AW11: 33959.983 | AY11: 20.594914 | AZ11: 609.10853 | BA11: 2768.891 | BB11: 5028.2748 | BD11: 7083.423 | BE11: 17602.676 | BF11: 44943.41 | BG11: 3219.1304 | BI11: -10822.811 | BJ11: -37184.829 | BK11: 11939.541 | BM11: 1764.4344 | BN11: 2457.77 | BO11: 3680.8237 | BQ11: 64.311 | BR11: 269.01435 | BT11: 371.763 | BU11: 2177.1423 | BV11: 2076.6117
A13: Activo Corriente | D13: 21443.876 | E13: 16147.77 | F13: 27257.998 | G13: 30188.632 | H13: 28923.839 | J13: 489171 | K13: 559173 | L13: 658388.66 | M13: 747714.18 | N13: 731542.08 | P13: 156739.98 | Q13: 50343.569 | R13: 69251.927 | S13: 80296.962 | T13: 89011.252 | V13: 17118.68 | W13: 22603.33 | X13: 41829.318 | Y13: 22008.315 | AA13: 4149 | AB13: 55862.546 | AC13: 47567.44 | AD13: 53771.717 | AF13: 16158.428 | AG13: 16137.416 | AH13: 16139.218 | AJ13: 5 | AK13: 18025.535 | AM13: 49728.769 | AN13: 62872.607 | AO13: 56280.634 | AQ13: 59812.929 | AR13: 77391.045 | AS13: 74316.734 | AU13: 489257.84 | AV13: 495285.08 | AW13: 460780.22 | AY13: 20834.299 | AZ13: 37591.151 | BA13: 57469.938 | BB13: 68526.191 | BD13: 1207333.4 | BE13: 1247545.1 | BF13: 1252652.1 | BG13: 1294259.4 | BI13: 403277.95 | BJ13: 537700.31 | BK13: 710962.57 | BM13: 10197.616 | BN13: 12016.524 | BO13: 16407.74 | BQ13: 407.668 | BR13: 2554.7835 | BT13: 6856.8995 | BU13: 11124.908 | BV13: 15295.218
A14: Activo No Corriente | D14: 0 | E14: 0 | F14: 0 | G14: 0 | H14: 0 | J14: 117278.28 | K14: 105337 | L14: 183901.7 | M14: 221052.02 | N14: 95615.306 | P14: 25948 | Q14: 26300.778 | R14: 23715.271 | S14: 28567.047 | T14: 29221.778 | V14: 45079.636 | W14: 2661.033 | X14: 3208.322 | Y14: 5083.783 | AA14: 0 | AB14: 11951.704 | AC14: 10657.175 | AD14: 10971.355 | AF14: 1937.5 | AG14: 1937.5 | AH14: 1937.5 | AJ14: 0 | AK14: 129.08187 | AM14: 16347.708 | AN14: 18501.092 | AO14: 20780.629 | AQ14: 1807.105 | AR14: 1742.831 | AS14: 1813.014 | AU14: 71490.305 | AV14: 102640.33 | AW14: 116100.16 | AY14: 495.56997 | AZ14: 195.31259 | BA14: 1469.1188 | BB14: 2981.4867 | BD14: 1074320.7 | BE14: 988756.83 | BF14: 991524.48 | BG14: 1035248.8 | BI14: 2157.85 | BJ14: 6069.277 | BK14: 19132.291 | BM14: 3591.4617 | BN14: 3841.6349 | BO14: 6142.7224 | BQ14: 3.33248 | BR14: 27.64633 | BT14: 44.108 | BU14: 47.24313 | BV14: 121.70389
A15: Activo Diferido | D15: 43854.634 | E15: 47511.01 | F15: 43317.688 | G15: 51328.915 | H15: 73222.413 | J15: 316380 | K15: 332106 | L15: 269491.19 | M15: 282184.37 | N15: 442297.11 | P15: 34413 | Q15: 162778.8 | R15: 148720.9 | S15: 154873.23 | T15: 168630.21 | V15: 0 | W15: 0 | X15: 0 | Y15: 31265.551 | AA15: 0 | AB15: 11319.385 | AC15: 20216.327 | AD15: 14995.304 | AF15: 0 | AG15: 0 | AH15: 0 | AJ15: 7.5 | AK15: 7.5 | AM15: 4372.5589 | AN15: 2125.3835 | AO15: 2125.3849 | AQ15: 12.811 | AR15: 250.039 | AS15: 235.915 | AU15: 3297.461 | AV15: 4455.227 | AW15: 5384.058 | AY15: 2141.2416 | AZ15: 1956.096 | BA15: 1770.9504 | BB15: 1585.8048 | BD15: 132202.72 | BE15: 135392.1 | BF15: 119134.51 | BG15: 98694.956 | BI15: 5951.627 | BJ15: 5951.627 | BK15: 5951.627 | BM15: 0 | BN15: 0 | BO15: 0 | BQ15: 0 | BR15: 0 | BT15: 0 | BU15: 0 | BV15: 0
A16: Total de Activo | D16: 65298.51 | E16: 63658.78 | F16: 70575.686 | G16: 81517.547 | H16: 102146.25 | J16: 922829.28 | K16: 996616 | L16: 1111781.5 | M16: 1250950.6 | N16: 1269454.5 | P16: 217100.98 | Q16: 239423.14 | R16: 241688.1 | S16: 263737.24 | T16: 286863.24 | V16: 62198.316 | W16: 25264.363 | X16: 45037.64 | Y16: 58357.649 | AA16: 4149 | AB16: 79133.635 | AC16: 78440.942 | AD16: 79738.376 | AF16: 18095.928 | AG16: 18074.916 | AH16: 18076.718 | AJ16: 12.5 | AK16: 18162.117 | AM16: 70449.036 | AN16: 83499.083 | AO16: 79186.648 | AQ16: 61632.845 | AR16: 79383.915 | AS16: 76365.663 | AU16: 564045.6 | AV16: 602380.64 | AW16: 582264.43 | AY16: 23471.111 | AZ16: 39742.559 | BA16: 60710.007 | BB16: 73093.482 | BD16: 2413856.8 | BE16: 2371694 | BF16: 2363311 | BG16: 2428203.1 | BI16: 411387.43 | BJ16: 549721.22 | BK16: 736046.49 | BM16: 13789.078 | BN16: 15858.159 | BO16: 22550.462 | BQ16: 411.00048 | BR16: 2582.4298 | BT16: 6901.0075 | BU16: 11172.151 | BV16: 15416.922
A18: Pasivo Corriente | D18: 40792.936 | E18: 30309.361 | F18: 38072.359 | G18: 30532.448 | H18: 41502.354 | J18: 162415 | K18: 268455 | L18: 234795.17 | M18: 277370.83 | N18: 442676.45 | P18: 35006 | Q18: 42593.636 | R18: 53598.854 | S18: 61927.296 | T18: 86036.563 | V18: 40572.929 | W18: 6092.298 | X18: 25287.61 | Y18: 21943.731 | AA18: 0 | AB18: 22040.14 | AC18: 20790.369 | AD18: 14654.413 | AF18: 0 | AG18: 0 | AH18: 0 | AJ18: 7.5 | AK18: 14330.181 | AM18: 36686.451 | AN18: 39334.017 | AO18: 39432.836 | AQ18: 7584.777 | AR18: 4763.187 | AS18: 602.094 | AU18: 43044.148 | AV18: 75189.951 | AW18: 70585.001 | AY18: 1697.3226 | AZ18: 7422.986 | BA18: 19266.655 | BB18: 22946.795 | BD18: 351927.3 | BE18: 368985 | BF18: 404572.41 | BG18: 687122.82 | BI18: 269718.17 | BJ18: 451638.98 | BK18: 626024.71 | BM18: 816.3589 | BN18: 899.5229 | BO18: 1267.1727 | BQ18: 341.97861 | BR18: 464.43575 | BT18: 2794.4995 | BU18: 8406.5064 | BV18: 2683.9404
A19: Pasivo No Corriente | D19: 10181.019 | E19: 16130.981 | F19: 10050.413 | G19: 22312.681 | H19: 21738.022 | J19: 310963 | K19: 257172 | L19: 351454.95 | M19: 411562.72 | N19: 315090.21 | P19: 45937 | Q19: 58943.814 | R19: 48747.619 | S19: 53904.635 | T19: 55329.341 | V19: 77.481 | W19: 331.962 | X19: 198.82 | Y19: 15751.093 | AA19: 0 | AB19: 20186.765 | AC19: 19842.093 | AD19: 24459.709 | AF19: 5.89476 | AG19: 0 | AH19: 0 | AJ19: 0 | AK19: 0 | AM19: 7271.0714 | AN19: 14107.943 | AO19: 10130.76 | AQ19: 25322.054 | AR19: 44035.114 | AS19: 43842.254 | AU19: 377116.73 | AV19: 359692.86 | AW19: 348368.48 | AY19: 8550 | AZ19: 20819.712 | BA19: 22472.022 | BB19: 22106.502 | BD19: 1122074.3 | BE19: 1111928.2 | BF19: 1125454.4 | BG19: 1141114.8 | BI19: 3542.761 | BJ19: 321.476 | BK19: 321.476 | BM19: 1291.9569 | BN19: 785.48835 | BO19: 3429.3175 | BQ19: 0 | BR19: 1761.4282 | BT19: 0 | BU19: 97.46402 | BV19: 8532.5861
A20: Total Pasivo | D20: 50973.955 | E20: 46440.342 | F20: 48122.772 | G20: 52845.129 | H20: 63240.376 | J20: 473378 | K20: 525627 | L20: 586250.12 | M20: 688933.55 | N20: 757766.65 | P20: 80943 | Q20: 101537.45 | R20: 102346.47 | S20: 115831.93 | T20: 141365.9 | V20: 40650.41 | W20: 6424.26 | X20: 25486.43 | Y20: 37694.824 | AA20: 0 | AB20: 42226.905 | AC20: 40632.462 | AD20: 39114.122 | AF20: 5.89476 | AG20: 0 | AH20: 0 | AJ20: 7.5 | AK20: 14330.181 | AM20: 43957.523 | AN20: 53441.961 | AO20: 49563.596 | AQ20: 32906.831 | AR20: 48798.301 | AS20: 44444.348 | AU20: 420160.88 | AV20: 434882.81 | AW20: 418953.48 | AY20: 10247.323 | AZ20: 28242.698 | BA20: 41738.677 | BB20: 45053.297 | BD20: 1474001.6 | BE20: 1480913.2 | BF20: 1530026.8 | BG20: 1828237.7 | BI20: 273260.93 | BJ20: 451960.46 | BK20: 626346.19 | BM20: 2108.3158 | BN20: 1685.0113 | BO20: 4696.4903 | BQ20: 341.97861 | BR20: 2225.864 | BT20: 2794.4995 | BU20: 8503.9704 | BV20: 11216.527
A22: Capital | J22: 114975 | K22: 114995 | L22: 114995 | M22: 114995 | N22: 114995 | P22: 128348 | Q22: 128370.97 | R22: 128397.93 | S22: 128397.93 | T22: 128414.01 | V22: 21388 | W22: 21388 | X22: 21388 | Y22: 21388 | AA22: 0 | AB22: 20598 | AC22: 20598 | AD22: 20598 | AF22: 2000 | AG22: 2000 | AH22: 2000 | AJ22: 5 | AK22: 490 | AM22: 15000 | AN22: 15000 | AO22: 15000 | AQ22: 5005 | AR22: 5005 | AS22: 5005 | AU22: 111574.8 | AV22: 111574.8 | AW22: 111574.8 | AY22: 7572.2 | AZ22: 7572.2 | BA22: 7572.2 | BB22: 16105.6 | BD22: 134051.4 | BE22: 134051.4 | BF22: 134051.4 | BG22: 134051.4 | BI22: 460989 | BJ22: 460989 | BK22: 92197.8 | BM22: 3105 | BN22: 3105 | BO22: 3105 | BQ22: 5 | BR22: 5 | BT22: 6 | BU22: 6 | BV22: 6
A23: Otros | D23: 0 | E23: 0 | F23: 0 | G23: 0 | H23: 0 | J23: 0 | K23: 0 | L23: -6800.427 | M23: 22470.203 | N23: 0 | P23: 6984 | Q23: 7515.611 | R23: 1254.59 | S23: 949.485 | T23: 3094.496 | V23: 0 | W23: 0 | X23: 0 | Y23: 0 | AA23: 0 | AB23: 0 | AC23: 0 | AD23: 5439.5 | AF23: 14879.185 | AG23: 14858.537 | AH23: 14858.257 | AJ23: 0 | AK23: 3000 | AM23: 0 | AN23: 0 | AO23: 0 | AQ23: 9995 | AR23: 9995 | AS23: 9995 | AU23: 8912.602 | AV23: 8912.602 | AW23: 13912.579 | AY23: 4838.439 | AZ23: 2473.345 | BA23: 7207.9805 | BB23: 2655.2001 | BD23: 827460.03 | BE23: 763600.52 | BF23: 641385.65 | BG23: 406960.01 | BI23: 3180.903 | BJ23: 0 | BK23: 0 | BM23: 2.8535 | BN23: 2.8535 | BO23: 2.8535 | BQ23: 0 | BR23: 0 | BT23: 0 | BU23: 0 | BV23: 0
A24: Reserva Legal | J24: 28309 | K24: 29652 | L24: 31064.837 | M24: 31778.92 | N24: 31778.92 | P24: 3668 | Q24: 3835.227 | R24: 4086.595 | S24: 4175.852 | T24: 4541.229 | V24: 71.441 | W24: 71.441 | X24: 119.549 | Y24: 119.549 | AA24: 0 | AB24: 0 | AC24: 0 | AD24: 694.589 | AF24: 44.22588 | AG24: 44.22588 | AH24: 44.22588 | AM24: 271.946 | AN24: 490.97832 | AO24: 490.97832 | AQ24: 1186.153 | AR24: 1404.133 | AS24: 1404.133 | AU24: 2164.457 | AV24: 3357.874 | AW24: 5105.494 | AY24: 46.49867 | AZ24: 78.55701 | BA24: 46.49867 | BB24: 119.76161 | BD24: 21884.101 | BE24: 22869.044 | BF24: 24625.769 | BG24: 27650.698 | BI24: 0 | BJ24: 0 | BK24: 0 | BM24: 796.52592 | BN24: 1083.2658 | BO24: 1291.8694 | BQ24: 0 | BR24: 0 | BT24: 75.655 | BU24: 112.83228 | BV24: 140.05211
A25: Utilidades Retenidas | D25: 14324.555 | E25: 17218.238 | F25: 22452.714 | G25: 28672.218 | H25: 38905.676 | J25: 306165 | K25: 326342 | L25: 386272.01 | M25: 392772.88 | N25: 364913.92 | P25: -2843 | Q25: -1836.117 | R25: 360.338 | S25: 8745.705 | T25: -4538.771 | V25: 88.465 | W25: -2619.893 | X25: -1956.339 | Y25: -844.713 | AA25: 0 | AB25: 16308.73 | AC25: 17210.48 | AD25: 13892.165 | AF25: 1166.622 | AG25: 1172.1533 | AH25: 1174.2357 | AJ25: 0 | AK25: 341.9356 | AM25: 11219.567 | AN25: 14566.144 | AO25: 14132.073 | AQ25: 12539.861 | AR25: 14181.481 | AS25: 15517.182 | AU25: 21232.865 | AV25: 43652.548 | AW25: 32718.079 | AY25: 766.65075 | AZ25: 1375.7592 | BA25: 4144.6502 | BB25: 9159.6235 | BD25: -43540.303 | BE25: -29740.147 | BF25: 33221.445 | BG25: 31303.343 | BI25: -326043.41 | BJ25: -363228.24 | BK25: 17502.502 | BM25: 7776.3825 | BN25: 9982.0288 | BO25: 13454.249 | BQ25: 64.02187 | BR25: 351.56579 | BT25: 4024.853 | BU25: 2549.3482 | BV25: 4054.3434
A26: Total Patrimonio | D26: 14324.755 | E26: 17218.438 | F26: 22452.914 | G26: 28672.418 | H26: 38905.876 | J26: 449449 | K26: 470989 | L26: 525531.42 | M26: 562017 | N26: 511687.84 | P26: 136157 | Q26: 137885.69 | R26: 139341.63 | S26: 147905.31 | T26: 145497.34 | V26: 21547.906 | W26: 18839.548 | X26: 19551.21 | Y26: 20662.836 | AA26: 0 | AB26: 36906.73 | AC26: 37808.48 | AD26: 40624.254 | AF26: 18090.033 | AG26: 18074.916 | AH26: 18076.718 | AJ26: 5 | AK26: 3831.9356 | AM26: 26491.513 | AN26: 30057.122 | AO26: 29623.051 | AQ26: 28726.014 | AR26: 30585.614 | AS26: 31921.315 | AU26: 143884.72 | AV26: 167497.82 | AW26: 163310.95 | AY26: 13223.788 | AZ26: 11499.861 | BA26: 18971.329 | BB26: 28040.185 | BD26: 939855.23 | BE26: 890780.82 | BF26: 833284.27 | BG26: 599965.45 | BI26: 138126.49 | BJ26: 97760.761 | BK26: 109700.3 | BM26: 11680.762 | BN26: 14173.148 | BO26: 17853.972 | BQ26: 69.02187 | BR26: 356.56579 | BT26: 4106.508 | BU26: 2668.1805 | BV26: 4200.3955
A28: Liquidez | D28: 0.52567621 | E28: 0.53276511 | F28: 0.71595243 | G28: 0.98873932 | H28: 0.69692044 | J28: 3.0118585 | K28: 2.0829301 | L28: 2.804098 | M28: 2.6957203 | N28: 1.6525435 | P28: 4.4775176 | Q28: 1.1819505 | R28: 1.2920412 | S28: 1.2966328 | T28: 1.0345747 | V28: 0.42192369 | W28: 3.7101485 | X28: 1.6541428 | Y28: 1.0029432 | AA28: 0 | AB28: 2.5345822 | AC28: 2.2879555 | AD28: 3.6693191 | AF28: 0 | AG28: 0 | AH28: 0 | AJ28: 0.66666667 | AK28: 1.2578721 | AM28: 1.3555077 | AN28: 1.5984283 | AO28: 1.427253 | AQ28: 7.8859179 | AR28: 16.247744 | AS28: 123.43045 | AU28: 11.366419 | AV28: 6.587118 | AW28: 6.5280188 | AY28: 12.274803 | AZ28: 5.0641548 | BA28: 2.9828705 | BB28: 2.9863077 | BD28: 3.430633 | BE28: 3.3810184 | BF28: 3.096237 | BG28: 1.8835925 | BI28: 1.4951827 | BJ28: 1.1905534 | BK28: 1.1356781 | BM28: 12.491584 | BN28: 13.358775 | BO28: 12.948305 | BQ28: 1.1920863 | BR28: 5.5008329 | BT28: 2.4537129 | BU28: 1.3233687 | BV28: 5.6987921
A29: Prueba Acida | D29: 0.52567489 | E29: 0.53276498 | F29: 0.71595243 | G29: 0.98873932 | H29: 0.69692044 | J29: 2.3167996 | K29: 1.7105176 | L29: 2.458597 | M29: 2.3510577 | N29: 1.3079216 | P29: 4.1072668 | Q29: 0.83911521 | R29: 0.97149027 | S29: 0.9002935 | T29: 0.79435734 | V29: 0.33612345 | W29: 2.8278118 | X29: 1.4480697 | Y29: 0.76047747 | AA29: 0 | AB29: 1.9549913 | AC29: 1.6244756 | AD29: 2.729427 | AF29: 0 | AG29: 0 | AH29: 0 | AJ29: 0.66666667 | AK29: 1.1576597 | AM29: 0.9476036 | AN29: 1.1982056 | AO29: 0.99051794 | AQ29: 4.7640301 | AR29: 10.203357 | AS29: 78.886338 | AU29: 11.366419 | AV29: 6.587118 | AW29: 6.5280188 | AY29: 10.49672 | AZ29: 4.7341577 | BA29: 2.7938619 | BB29: 2.6255411 | BD29: 1.9720659 | BE29: 1.8947657 | BF29: 1.5773992 | BG29: 0.67496871 | BI29: 1.1020791 | BJ29: 0.81667676 | BK29: 0.78988282 | BM29: 12.21489 | BN29: 12.9687 | BO29: 10.572202 | BQ29: 0.48450984 | BR29: 2.1821932 | BT29: 0.79278257 | BU29: 0.22593382 | BV29: 0.86151775
A30: Capital de Trabajo | D30: -19349.06 | E30: -14161.591 | F30: -10814.361 | G30: -343.816 | H30: -12578.515 | J30: 326756 | K30: 290718 | L30: 423593.49 | M30: 470343.34 | N30: 288865.64 | P30: 121733.98 | Q30: 7749.933 | R30: 15653.073 | S30: 18369.666 | T30: 2974.689 | V30: -23454.249 | W30: 16511.032 | X30: 16541.708 | Y30: 64.584 | AA30: 4149 | AB30: 33822.406 | AC30: 26777.071 | AD30: 39117.304 | AF30: 16158.428 | AG30: 16137.416 | AH30: 16139.218 | AJ30: -2.5 | AK30: 3695.3537 | AM30: 13042.317 | AN30: 23538.59 | AO30: 16847.798 | AQ30: 52228.152 | AR30: 72627.858 | AS30: 73714.64 | AU30: 446213.69 | AV30: 420095.13 | AW30: 390195.22 | AY30: 19136.977 | AZ30: 30168.165 | BA30: 38203.282 | BB30: 45579.396 | BD30: 855406.11 | BE30: 878560.08 | BF30: 848079.65 | BG30: 607136.57 | BI30: 133559.78 | BJ30: 86061.333 | BK30: 84937.86 | BM30: 9381.2572 | BN30: 11117.002 | BO30: 15140.567 | BQ30: 65.68939 | BR30: 2090.3477 | BT30: 4062.4 | BU30: 2718.4014 | BV30: 12611.278
A32: Período promedio de cobro (días) | D32: 319.0952 | E32: 232.49789 | F32: 323.72398 | G32: 326.68427 | H32: 281.4713 | J32: 256.00126 | K32: 239.33791 | L32: 487.77804 | M32: 488.48729 | N32: 370.59914 | P32: 2608.4781 | Q32: 119.01166 | R32: 125.78658 | S32: 134.70208 | T32: 165.75094 | V32: 215.46244 | W32: 141.40689 | X32: 262.41122 | Y32: 106.72672 | AA32: 0 | AB32: 281.77593 | AC32: 205.37245 | AD32: 245.89489 | AF32: 0 | AG32: 3927.4309 | AH32: 4082.8039 | AJ32: 0 | AK32: 278.94011 | AM32: 116.79459 | AN32: 154.91912 | AO32: 126.9005 | AQ32: 124.49152 | AR32: 187.1087 | AS32: 156.22171 | AU32: 61.161233 | AV32: 46.739736 | AW32: 40.58706 | AY32: 832.60672 | AZ32: 4084.6757 | BA32: 1266.8023 | BB32: 596.14415 | BD32: 38.420372 | BE32: 36.657843 | BF32: 46.8937 | BG32: 58.663567 | BI32: 63.555346 | BJ32: 64.144733 | BK32: 66.407236 | BM32: 217.87683 | BN32: 186.13114 | BO32: 180.38387 | BQ32: 2.2223598 | BR32: 45.576867 | BT32: 4.5530633 | BU32: 2.0196388 | BV32: 14.550951
A33: Rotación promedio de inventario (días) | F33: 0 | G33: 0 | H33: 0 | J33: 268.7454 | K33: 178.57197 | L33: 125.36564 | M33: 140.17304 | N33: 220.41053 | P33: 1903.6965 | Q33: 220.17859 | R33: 182.05065 | S33: 233.68608 | T33: 218.58791 | V33: 68.330869 | W33: 59.949788 | X33: 55.228232 | Y33: 57.279224 | AA33: 0 | AB33: 166.4898 | AC33: 134.80189 | AD33: 134.32265 | AM33: 96.815932 | AN33: 88.182555 | AO33: 96.010699 | AQ33: 130.20856 | AR33: 188.24076 | AS33: 164.11649 | AU33: 0 | AV33: 0 | AW33: 0 | AY33: 299.9292 | AZ33: 511.79906 | BA33: 155.98912 | BB33: 158.90599 | BD33: 257.6582 | BE33: 228.07861 | BF33: 243.24966 | BG33: 387.99361 | BI33: 38.951673 | BJ33: 44.153758 | BK33: 48.315428 | BM33: 7.5925305 | BN33: 9.6601063 | BO33: 69.126165 | BQ33: 48.679243 | BR33: 231.92323 | BT33: 194.20086 | BU33: 313.18988 | BV33: 422.75617
A34: Período promedio de pago (días) | D34: 0 | E34: 0 | F34: 0 | G34: 0 | H34: 10.618845 | J34: 64.753056 | K34: 104.0788 | L34: 81.384164 | M34: 79.567935 | N34: 97.664171 | P34: 2303.3161 | Q34: 124.73911 | R34: 104.20148 | S34: 113.59445 | T34: 233.47706 | V34: 0 | W34: 0 | X34: 0 | Y34: 26.239633 | AA34: 0 | AB34: 84.600927 | AC34: 84.1156 | AD34: 114.94626 | AF34: 0 | AG34: 0 | AH34: 0 | AJ34: 0 | AK34: 0 | AM34: 0 | AN34: 0 | AO34: 0 | AQ34: 40.760061 | AR34: 27.586512 | AS34: 1.9042813 | AU34: 0 | AV34: 0 | AW34: 0 | AY34: 168.11849 | AZ34: 2313.8668 | BA34: 24.721162 | BB34: 12.664209 | BD34: 3.9208234 | BE34: 0.54370781 | BF34: 4.845431 | BG34: 3.371756 | BI34: 66.625764 | BJ34: 62.422391 | BK34: 88.668214 | BM34: 25.717137 | BN34: 20.663246 | BO34: 22.109912 | BQ34: 67.684648 | BR34: 13.775672 | BT34: 0 | BU34: 84.322116 | BV34: 18.442964
A36: Ciclo de Caja en Días | D36: 319.09646 | E36: 232.498 | F36: 323.72398 | G36: 326.68427 | H36: 270.85245 | J36: 459.9936 | K36: 313.83109 | L36: 531.75951 | M36: 549.0924 | N36: 493.3455 | P36: 2208.8585 | Q36: 214.45114 | R36: 203.63575 | S36: 254.79371 | T36: 150.86179 | V36: 283.79331 | W36: 201.35668 | X36: 317.63946 | Y36: 137.76631 | AA36: 0 | AB36: 363.6648 | AC36: 256.05874 | AD36: 265.27128 | AM36: 213.61052 | AN36: 243.10167 | AO36: 222.9112 | AQ36: 213.94002 | AR36: 347.76295 | AS36: 318.43391 | AU36: 61.161233 | AV36: 46.739736 | AW36: 40.58706 | AY36: 964.41744 | AZ36: 2282.608 | BA36: 1398.0702 | BB36: 742.38594 | BD36: 292.15775 | BE36: 264.19274 | BF36: 285.29793 | BG36: 443.28542 | BI36: 35.881255 | BJ36: 45.876099 | BK36: 26.05445 | BM36: 199.75223 | BN36: 175.128 | BO36: 227.40012 | BQ36: -16.783045 | BR36: 263.72442 | BT36: 198.75392 | BU36: 230.88741 | BV36: 418.86415
A37: EBITDA | D37: 14418.686 | E37: 2893.883 | F37: 5234.476 | G37: 6219.504 | H37: 3790.438 | J37: 55422 | K37: 49227 | L37: 39552.463 | M37: 32077.02 | N37: 43794.466 | P37: -2481 | Q37: 6022.187 | R37: 5992.457 | S37: 8775.025 | T37: 6049.452 | V37: -35.504 | W37: -2708.358 | X37: 962.143 | Y37: 1111.626 | AA37: 0 | AB37: 4038.452 | AC37: 5892.766 | AD37: 8517.153 | AF37: -0.28 | AG37: 5.53129 | AH37: 1.85184 | AJ37: -421.18522 | AK37: 1232.1515 | AM37: 7601.4172 | AN37: 9028.5853 | AO37: 3695.5195 | AQ37: 10861.364 | AR37: 8190.774 | AS37: 2426.61 | AU37: 49706.997 | AV37: 71647.446 | AW37: 84233.029 | AY37: 344.93039 | AZ37: 1020.6891 | BA37: 3318.0811 | BB37: 5383.7008 | BD37: 101848.72 | BE37: 113646.52 | BF37: 155180.48 | BG37: 130015.49 | BI37: 2752.852 | BJ37: -22928.867 | BK37: 36789.63 | BM37: 2352.6003 | BN37: 3277.0267 | BO37: 4907.7649 | BQ37: 71.14404 | BR37: 273.04545 | BT37: 575.682 | BU37: 2230.289 | BV37: 3575.704
A39: Apalancamiento | D39: 3.5584521 | E39: 2.6971286 | F39: 2.1432751 | G39: 1.843065 | H39: 1.6254711 | J39: 1.0532407 | K39: 1.116007 | L39: 1.1155377 | M39: 1.2258233 | N39: 1.4809159 | P39: 0.59448284 | Q39: 0.73638858 | R39: 0.73450034 | S39: 0.78314926 | T39: 0.97160473 | V39: 1.8865132 | W39: 0.34099863 | X39: 1.303573 | Y39: 1.8242812 | AA39: 0 | AB39: 1.1441519 | AC39: 1.0746918 | AD39: 0.96282684 | AF39: 0.00032585678 | AG39: 0 | AH39: 0 | AJ39: 1.5 | AK39: 3.7396717 | AM39: 1.6593059 | AN39: 1.7780132 | AO39: 1.6731429 | AQ39: 1.1455411 | AR39: 1.5954658 | AS39: 1.3923094 | AU39: 2.9201215 | AV39: 2.596349 | AW39: 2.5653728 | AY39: 0.7749158 | AZ39: 2.4559164 | BA39: 2.2000924 | BB39: 1.6067404 | BD39: 1.5683284 | BE39: 1.6624889 | BF39: 1.8361403 | BG39: 3.0472382 | BI39: 1.9783383 | BJ39: 4.6231274 | BK39: 5.7096122 | BM39: 0.18049472 | BN39: 0.11888758 | BO39: 0.26305017 | BQ39: 4.9546413 | BR39: 6.2425058 | BT39: 0.68050507 | BU39: 3.1871796 | BV39: 2.6703501
A40: Apalancamiento Bancario | J40: 0.84349059 | K40: 0.7977405 | L40: 0.47713848 | M40: 0.51855977 | N40: 0.72933114 | P40: 0.30031508 | Q40: 0.29135624 | R40: 0.21246742 | S40: 0.25251266 | T40: 0.41340849 | V40: 0 | W40: 0 | X40: 0 | Y40: 0 | AA40: 0 | AB40: 0.72252822 | AC40: 0.48523395 | AD40: 0.26793166 | AF40: 0 | AG40: 0 | AH40: 0 | AJ40: 0 | AK40: 0.3961134 | AM40: 1.3458261 | AN40: 1.597841 | AO40: 1.4869946 | AQ40: 0.87882628 | AR40: 1.4355182 | AS40: 1.3685266 | AU40: 2.526328 | AV40: 1.9290997 | AW40: 1.6818468 | AY40: 0.64656207 | AZ40: 1.8104316 | BA40: 2.1650561 | BB40: 1.577394 | BD40: 1.3370244 | BE40: 1.3953067 | BF40: 1.4392421 | BG40: 2.1887275 | BI40: 0 | BJ40: 0 | BK40: 0 | BM40: 0.11060554 | BN40: 0.055420881 | BO40: 0.19207589 | BQ40: 0 | BR40: 4.9399811 | BT40: 0.066756475 | BU40: 0.81907403 | BV40: 2.0655959
A41: Apalancamiento Comercial | D41: 3.5502475 | E41: 2.670022 | F41: 1.9462502 | G41: 1.5135245 | H41: 1.325428 | J41: 0.058175677 | K41: 0.065799838 | L41: 0.10266551 | M41: 0.12294651 | N41: 0.13944219 | P41: 0.051756428 | Q41: 0.053049173 | R41: 0.068203244 | S41: 0.052009655 | T41: 0.061848395 | V41: 1.8690515 | W41: 0.30945095 | X41: 1.246281 | Y41: 1.4969901 | AA41: 0 | AB41: 0.022176606 | AC41: 0.057237927 | AD41: 0 | AF41: 0.00032585678 | AG41: 0 | AH41: 0 | AJ41: 0 | AK41: 0 | AM41: 0.29227166 | AN41: 0.1633062 | AO41: 0.15859124 | AQ41: 0.26071208 | AR41: 0.15496972 | AS41: 0.013363547 | AU41: 0.23363981 | AV41: 0.41717451 | AW41: 0.54720674 | AY41: 0.12792554 | AZ41: 0.64532518 | BA41: 0.034735012 | BB41: 0.029346377 | BD41: 0.057396927 | BE41: 0.024453928 | BF41: 0.03239549 | BG41: 0.030289783 | BI41: 1.3386232 | BJ41: 2.5566283 | BK41: 3.7313155 | BM41: 0.065500736 | BN41: 0.053461735 | BO41: 0.063090372 | BQ41: 4.8745208 | BR41: 0.39619216 | BT41: 0 | BU41: 1.3333417 | BV41: 0.18066865
A42: Crecimiento Anual en Ventas | E42: =E10/D10-1 -> -0.014683192 | F42: =F10/E10-1 -> 0.26351927 | G42: =G10/F10-1 -> 0.099887075 | H42: =H10/G10-1 -> -0.26313757 | K42: =K10/J10-1 -> -0.021981474 | L42: =L10/K10-1 -> 0.093713993 | M42: =M10/L10-1 -> 0.16287436 | N42: =N10/M10-1 -> -0.25648732 | Q42: =Q10/P10-1 -> 15.317158 | R42: =R10/Q10-1 -> 0.47388517 | S42: =S10/R10-1 -> 0.055515009 | T42: =T10/S10-1 -> -0.30836004 | W42: =W10/V10-1 -> 0.65183776 | X42: =X10/W10-1 -> 0.27312921 | Y42: =Y10/X10-1 -> -0.21155038 | AC42: =AC10/AB10-1 -> 0.32625776 | AD42: =AD10/AC10-1 -> 0.044512999 | AH42: -0.025495079 | AM42: 0.26145295 | AN42: 0.10998813 | AO42: 0.013886995 | AR42: -0.16290603 | AS42: 0.14321957 | AV42: 0.6699303 | AW42: 0.29114551 | AZ42: -0.60731184 | BA42: 4.1921338 | BB42: 1.2251217 | BE42: 0.22332825 | BF42: 0.039864852 | BG42: -0.12384191 | BJ42: 0.37032508 | BK42: 0.23661006 | BN42: 0.27679282 | BO42: 0.19778174 | BR42: 0.58620664 | BT42: 0.74440575 | BU42: 0.55845628 | BV42: 0.16549705
A43: ROE | D43: 1.0065572 | E43: 0.16806885 | F43: 0.23313125 | G43: 0.21691592 | H43: 0.12990113 | J43: 0.043241836 | K43: 0.04546603 | L43: 0.030679364 | M43: 0.012837603 | N43: 0.005607463 | P43: -0.02200401 | Q43: 0.0092537229 | R43: 0.018560168 | S43: 0.030907011 | T43: -0.025987756 | V43: -0.0016476775 | W43: -0.14375918 | X43: 0.036399844 | Y43: 0.071731102 | AA43: 0 | AB43: 0.031437952 | AC43: 0.02346664 | AD43: 0.073072603 | AF43: -1.5478136e-05 | AG43: 0.00030602023 | AH43: 0.00020488675 | AJ43: -103.82709 | AK43: 0.48232211 | AM43: 0.16536038 | AN43: 0.15189775 | AO43: 0.13948118 | AQ43: 0.24557448 | AR43: 0.13541065 | AS43: 0.16737406 | AU43: 0.089295699 | AV43: 0.14097556 | AW43: 0.20794676 | AY43: 0.0015574141 | AZ43: 0.052966598 | BA43: 0.14595134 | BB43: 0.17932388 | BD43: 0.0075367171 | BE43: 0.019760951 | BF43: 0.053935268 | BG43: 0.0053655263 | BI43: -0.078354346 | BJ43: -0.38036558 | BK43: 0.10883781 | BM43: 0.15105474 | BN43: 0.17341031 | BO43: 0.20616274 | BQ43: 0.93174815 | BR43: 0.75445923 | BT43: 0.090530202 | BU43: 0.81596515 | BV43: 0.49438479
A44: ROA | D44: 0.22081187 | E44: 0.045459291 | F44: 0.074168262 | G44: 0.076296506 | H44: 0.049477267 | J44: 0.021060233 | K44: 0.021486711 | L44: 0.014501923 | M44: 0.0057675749 | N44: 0.0022602391 | P44: -0.01380003 | Q44: 0.0053292926 | R44: 0.010700585 | S44: 0.017332824 | T44: -0.013181017 | V44: -0.00057081931 | W44: -0.10720072 | X44: 0.015801472 | Y44: 0.025398007 | AA44: 0 | AB44: 0.014662185 | AC44: 0.011310904 | AD44: 0.037228248 | AF44: -1.5473094e-05 | AG44: 0.00030602023 | AH44: 0.00020488675 | AJ44: -41.530835 | AK44: 0.10176277 | AM44: 0.062181784 | AN44: 0.054678555 | AO44: 0.052178722 | AQ44: 0.11445806 | AR44: 0.052172005 | AS44: 0.069963381 | AU44: 0.022778809 | AV44: 0.039199633 | AW44: 0.058323987 | AY44: 0.000877458 | AZ44: 0.015326354 | BA44: 0.045608477 | BB44: 0.068792382 | BD44: 0.0029344835 | BE44: 0.0074219844 | BF44: 0.019017137 | BG44: 0.0013257253 | BI44: -0.026308074 | BJ44: -0.067643067 | BK44: 0.016221178 | BM44: 0.12795884 | BN44: 0.15498457 | BO44: 0.16322609 | BQ44: 0.15647427 | BR44: 0.10417102 | BT44: 0.05387083 | BU44: 0.19487226 | BV44: 0.1346969
A47: CALIFICADOR Z
A49: Inventarios | J49: 82040 | K49: 69549 | L49: 58821.594 | M49: 60654.179 | N49: 152555.97 | P49: 5924 | Q49: 9027.959 | R49: 9936.311 | S49: 11853.918 | T49: 20667.477 | V49: 3481.167 | W49: 2275.958 | X49: 2412.788 | Y49: 5320.602 | AA49: 0 | AB49: 3179.649 | AC49: 4199.378 | AD49: 2754.552 | AK49: 1436.0616 | AM49: 14964.555 | AN49: 15742.367 | AO49: 17221.702 | AQ49: 23678.823 | AR49: 28790.548 | AS49: 26819.743 | AZ49: 2449.5644 | BA49: 3641.5624 | BB49: 8278.4365 | BD49: 149388.94 | BE49: 135129.34 | BF49: 140786.46 | BG49: 274342.42 | BI49: 106027.18 | BJ49: 168857.25 | BK49: 216476.4 | BM49: 225.88182 | BN49: 350.88182 | BO49: 3010.9329
A51: Liquidez Corriente | D51: =ActivoCorr/PasivoCorr -> 0.52567621 | E51: =ActivoCorr/PasivoCorr -> 0.53276511 | F51: =ActivoCorr/PasivoCorr -> 0.71595243 | G51: =ActivoCorr/PasivoCorr -> 0.98873932 | H51: =ActivoCorr/PasivoCorr -> 0.69692044 | J51: =ActivoCorr/PasivoCorr -> 3.0118585 | K51: =ActivoCorr/PasivoCorr -> 2.0829301 | L51: =ActivoCorr/PasivoCorr -> 2.804098 | M51: =ActivoCorr/PasivoCorr -> 2.6957203 | N51: =ActivoCorr/PasivoCorr -> 1.6525435 | P51: =ActivoCorr/PasivoCorr -> 4.4775176 | Q51: =ActivoCorr/PasivoCorr -> 1.1819505 | R51: =ActivoCorr/PasivoCorr -> 1.2920412 | S51: =ActivoCorr/PasivoCorr -> 1.2966328 | T51: =ActivoCorr/PasivoCorr -> 1.0345747 | V51: =ActivoCorr/PasivoCorr -> 0.42192369 | W51: =ActivoCorr/PasivoCorr -> 3.7101485 | X51: =ActivoCorr/PasivoCorr -> 1.6541428 | Y51: =ActivoCorr/PasivoCorr -> 1.0029432 | AB51: =ActivoCorr/PasivoCorr -> 2.5345822 | AC51: =ActivoCorr/PasivoCorr -> 2.2879555 | AD51: =ActivoCorr/PasivoCorr -> 3.6693191 | AJ51: =ActivoCorr/PasivoCorr -> 0.66666667 | AK51: =ActivoCorr/PasivoCorr -> 1.2578721 | AM51: =ActivoCorr/PasivoCorr -> 1.3555077 | AN51: =ActivoCorr/PasivoCorr -> 1.5984283 | AO51: =ActivoCorr/PasivoCorr -> 1.427253 | AQ51: =ActivoCorr/PasivoCorr -> 7.8859179 | AR51: =ActivoCorr/PasivoCorr -> 16.247744 | AS51: =ActivoCorr/PasivoCorr -> 123.43045 | AU51: =ActivoCorr/PasivoCorr -> 11.366419 | AV51: =ActivoCorr/PasivoCorr -> 6.587118 | AW51: =ActivoCorr/PasivoCorr -> 6.5280188 | AY51: =ActivoCorr/PasivoCorr -> 12.274803 | AZ51: =ActivoCorr/PasivoCorr -> 5.0641548 | BA51: =ActivoCorr/PasivoCorr -> 2.9828705 | BB51: =ActivoCorr/PasivoCorr -> 2.9863077 | BD51: =ActivoCorr/PasivoCorr -> 3.430633 | BE51: =ActivoCorr/PasivoCorr -> 3.3810184 | BF51: =ActivoCorr/PasivoCorr -> 3.096237 | BG51: =ActivoCorr/PasivoCorr -> 1.8835925 | BI51: =ActivoCorr/PasivoCorr -> 1.4951827 | BJ51: =ActivoCorr/PasivoCorr -> 1.1905534 | BK51: =ActivoCorr/PasivoCorr -> 1.1356781 | BM51: =ActivoCorr/PasivoCorr -> 12.491584 | BN51: =ActivoCorr/PasivoCorr -> 13.358775 | BO51: =ActivoCorr/PasivoCorr -> 12.948305 | BQ51: =ActivoCorr/PasivoCorr -> 1.1920863 | BR51: =ActivoCorr/PasivoCorr -> 5.5008329 | BT51: =ActivoCorr/PasivoCorr -> 2.4537129 | BU51: =ActivoCorr/PasivoCorr -> 1.3233687 | BV51: =ActivoCorr/PasivoCorr -> 5.6987921
A52: Rotación de Activos | D52: =Ventas/ActivoTotal -> 0.36647316 | E52: =Ventas/ActivoTotal -> 0.37039321 | F52: =Ventas/ActivoTotal -> 0.42213182 | G52: =Ventas/ActivoTotal -> 0.40197607 | H52: =Ventas/ActivoTotal -> 0.23638248 | J52: =Ventas/ActivoTotal -> 0.36568627 | K52: =Ventas/ActivoTotal -> 0.33116867 | L52: =Ventas/ActivoTotal -> 0.32468439 | M52: =Ventas/ActivoTotal -> 0.33556258 | N52: =Ventas/ActivoTotal -> 0.24585832 | P52: =Ventas/ActivoTotal -> 0.019884756 | Q52: =Ventas/ActivoTotal -> 0.29421203 | R52: =Ventas/ActivoTotal -> 0.42957098 | S52: =Ventas/ActivoTotal -> 0.41551161 | T52: =Ventas/ActivoTotal -> 0.26421641 | V52: =Ventas/ActivoTotal -> 0.32839735 | W52: =Ventas/ActivoTotal -> 1.3354797 | X52: =Ventas/ActivoTotal -> 0.95376749 | Y52: =Ventas/ActivoTotal -> 0.58035576 | AB52: =Ventas/ActivoTotal -> 0.496397 | AC52: =Ventas/ActivoTotal -> 0.6641641 | AD52: =Ventas/ActivoTotal -> 0.6824403 | AF52: =Ventas/ActivoTotal -> 0 | AG52: =Ventas/ActivoTotal -> 0.0046655818 | AH52: =Ventas/ActivoTotal -> 0.0022730896 | AJ52: =Ventas/ActivoTotal -> 0 | AK52: =Ventas/ActivoTotal -> 0.42952511 | AM52: =Ventas/ActivoTotal -> 1.1140705 | AN52: =Ventas/ActivoTotal -> 1.0433364 | AO52: =Ventas/ActivoTotal -> 0.55771673 | AQ52: =Ventas/ActivoTotal -> 1.3343134 | AR52: =Ventas/ActivoTotal -> 0.86718503 | AS52: =Ventas/ActivoTotal -> 0.2576415 | AU52: =Ventas/ActivoTotal -> 0.2150808 | AV52: =Ventas/ActivoTotal -> 0.33631266 | AW52: =Ventas/ActivoTotal -> 0.44923041 | AY52: =Ventas/ActivoTotal -> 0.23208384 | AZ52: =Ventas/ActivoTotal -> 0.053823324 | BA52: =Ventas/ActivoTotal -> 0.18294138 | BB52: =Ventas/ActivoTotal -> 0.33810169 | BD52: =Ventas/ActivoTotal -> 0.35902818 | BE52: =Ventas/ActivoTotal -> 0.44701736 | BF52: =Ventas/ActivoTotal -> 0.46648648 | BG52: =Ventas/ActivoTotal -> 0.39779325 | BI52: =Ventas/ActivoTotal -> 2.9727812 | BJ52: =Ventas/ActivoTotal -> 3.0485622 | BK52: =Ventas/ActivoTotal -> 2.815562 | BM52: =Ventas/ActivoTotal -> 1.1453744 | BN52: =Ventas/ActivoTotal -> 1.2715995 | BO52: =Ventas/ActivoTotal -> 1.0710886 | BQ52: =Ventas/ActivoTotal -> 6.9170819 | BR52: =Ventas/ActivoTotal -> 1.7462101 | BT52: =Ventas/ActivoTotal -> 2.0535625 | BU52: =Ventas/ActivoTotal -> 1.9768706 | BV52: =Ventas/ActivoTotal -> 1.6696619
A53: Activo/Patrimonio | D53: =ActivoTotal/Patrimonio -> 4.5584382 | E53: =ActivoTotal/Patrimonio -> 3.6971286 | F53: =ActivoTotal/Patrimonio -> 3.1432751 | G53: =ActivoTotal/Patrimonio -> 2.843065 | H53: =ActivoTotal/Patrimonio -> 2.6254711 | J53: =ActivoTotal/Patrimonio -> 2.0532458 | K53: =ActivoTotal/Patrimonio -> 2.116007 | L53: =ActivoTotal/Patrimonio -> 2.1155377 | M53: =ActivoTotal/Patrimonio -> 2.2258233 | N53: =ActivoTotal/Patrimonio -> 2.4809159 | P53: =ActivoTotal/Patrimonio -> 1.59449 | Q53: =ActivoTotal/Patrimonio -> 1.7363886 | R53: =ActivoTotal/Patrimonio -> 1.7345003 | S53: =ActivoTotal/Patrimonio -> 1.7831493 | T53: =ActivoTotal/Patrimonio -> 1.9716047 | V53: =ActivoTotal/Patrimonio -> 2.8865132 | W53: =ActivoTotal/Patrimonio -> 1.3410281 | X53: =ActivoTotal/Patrimonio -> 2.303573 | Y53: =ActivoTotal/Patrimonio -> 2.8242807 | AB53: =ActivoTotal/Patrimonio -> 2.1441519 | AC53: =ActivoTotal/Patrimonio -> 2.0746918 | AD53: =ActivoTotal/Patrimonio -> 1.9628268 | AF53: =ActivoTotal/Patrimonio -> 1.0003259 | AG53: =ActivoTotal/Patrimonio -> 1 | AH53: =ActivoTotal/Patrimonio -> 1 | AJ53: =ActivoTotal/Patrimonio -> 2.5 | AK53: =ActivoTotal/Patrimonio -> 4.7396717 | AM53: =ActivoTotal/Patrimonio -> 2.6593059 | AN53: =ActivoTotal/Patrimonio -> 2.7780132 | AO53: =ActivoTotal/Patrimonio -> 2.6731429 | AQ53: =ActivoTotal/Patrimonio -> 2.1455411 | AR53: =ActivoTotal/Patrimonio -> 2.5954658 | AS53: =ActivoTotal/Patrimonio -> 2.3923094 | AU53: =ActivoTotal/Patrimonio -> 3.9201215 | AV53: =ActivoTotal/Patrimonio -> 3.596349 | AW53: =ActivoTotal/Patrimonio -> 3.5653728 | AY53: =ActivoTotal/Patrimonio -> 1.7749158 | AZ53: =ActivoTotal/Patrimonio -> 3.4559164 | BA53: =ActivoTotal/Patrimonio -> 3.2000924 | BB53: =ActivoTotal/Patrimonio -> 2.6067404 | BD53: =ActivoTotal/Patrimonio -> 2.5683284 | BE53: =ActivoTotal/Patrimonio -> 2.6624889 | BF53: =ActivoTotal/Patrimonio -> 2.8361403 | BG53: =ActivoTotal/Patrimonio -> 4.0472382 | BI53: =ActivoTotal/Patrimonio -> 2.9783383 | BJ53: =ActivoTotal/Patrimonio -> 5.6231274 | BK53: =ActivoTotal/Patrimonio -> 6.7096122 | BM53: =ActivoTotal/Patrimonio -> 1.1804947 | BN53: =ActivoTotal/Patrimonio -> 1.1188876 | BO53: =ActivoTotal/Patrimonio -> 1.2630502 | BQ53: =ActivoTotal/Patrimonio -> 5.9546413 | BR53: =ActivoTotal/Patrimonio -> 7.2425058 | BT53: =ActivoTotal/Patrimonio -> 1.6805051 | BU53: =ActivoTotal/Patrimonio -> 4.1871796 | BV53: =ActivoTotal/Patrimonio -> 3.6703501
A55: CALIFICADOR GRAL. - RIESGO Z
A56: 1. Capital de Trabajo / Activo | D56: =CTrabajo/ActivoTotal -> -0.29631702 | E56: =CTrabajo/ActivoTotal -> -0.22246092 | F56: =CTrabajo/ActivoTotal -> -0.15323069 | G56: =CTrabajo/ActivoTotal -> -0.0042176932 | H56: =CTrabajo/ActivoTotal -> -0.12314221 | J56: =CTrabajo/ActivoTotal -> 0.35408066 | K56: =CTrabajo/ActivoTotal -> 0.29170513 | L56: =CTrabajo/ActivoTotal -> 0.38100425 | M56: =CTrabajo/ActivoTotal -> 0.37598876 | N56: =CTrabajo/ActivoTotal -> 0.227551 | P56: =CTrabajo/ActivoTotal -> 0.56072515 | Q56: =CTrabajo/ActivoTotal -> 0.032369189 | R56: =CTrabajo/ActivoTotal -> 0.064765592 | S56: =CTrabajo/ActivoTotal -> 0.069651393 | T56: =CTrabajo/ActivoTotal -> 0.010369711 | V56: =CTrabajo/ActivoTotal -> -0.37708817 | W56: =CTrabajo/ActivoTotal -> 0.65353051 | X56: =CTrabajo/ActivoTotal -> 0.3672863 | Y56: =CTrabajo/ActivoTotal -> 0.001106693 | AB56: =CTrabajo/ActivoTotal -> 0.42740872 | AC56: =CTrabajo/ActivoTotal -> 0.341366 | AD56: =CTrabajo/ActivoTotal -> 0.49057061 | AF56: =CTrabajo/ActivoTotal -> 0.89293171 | AG56: =CTrabajo/ActivoTotal -> 0.89280725 | AH56: =CTrabajo/ActivoTotal -> 0.89281793 | AJ56: =CTrabajo/ActivoTotal -> -0.2 | AK56: =CTrabajo/ActivoTotal -> 0.20346493 | AM56: =CTrabajo/ActivoTotal -> 0.18513124 | AN56: =CTrabajo/ActivoTotal -> 0.28190238 | AO56: =CTrabajo/ActivoTotal -> 0.21276059 | AQ56: =CTrabajo/ActivoTotal -> 0.84740777 | AR56: =CTrabajo/ActivoTotal -> 0.91489388 | AS56: =CTrabajo/ActivoTotal -> 0.96528514 | AU56: =CTrabajo/ActivoTotal -> 0.79109506 | AV56: =CTrabajo/ActivoTotal -> 0.69739149 | AW56: =CTrabajo/ActivoTotal -> 0.67013404 | AY56: =CTrabajo/ActivoTotal -> 0.81534176 | AZ56: =CTrabajo/ActivoTotal -> 0.75908963 | BA56: =CTrabajo/ActivoTotal -> 0.62927488 | BB56: =CTrabajo/ActivoTotal -> 0.62357674 | BD56: =CTrabajo/ActivoTotal -> 0.35437317 | BE56: =CTrabajo/ActivoTotal -> 0.37043568 | BF56: =CTrabajo/ActivoTotal -> 0.35885232 | BG56: =CTrabajo/ActivoTotal -> 0.25003533 | BI56: =CTrabajo/ActivoTotal -> 0.32465693 | BJ56: =CTrabajo/ActivoTotal -> 0.15655451 | BK56: =CTrabajo/ActivoTotal -> 0.11539741 | BM56: =CTrabajo/ActivoTotal -> 0.68033971 | BN56: =CTrabajo/ActivoTotal -> 0.70102723 | BO56: =CTrabajo/ActivoTotal -> 0.67140828 | BQ56: =CTrabajo/ActivoTotal -> 0.15982801 | BR56: =CTrabajo/ActivoTotal -> 0.80944997 | BT56: =CTrabajo/ActivoTotal -> 0.58866767 | BU56: =CTrabajo/ActivoTotal -> 0.24331943 | BV56: =CTrabajo/ActivoTotal -> 0.81801528
A57: 2. Utilidades Retenidas / Activo | D57: =UtilidadRetenida/ActivoTotal -> 0.21937032 | E57: =UtilidadRetenida/ActivoTotal -> 0.27047703 | F57: =UtilidadRetenida/ActivoTotal -> 0.31813667 | G57: =UtilidadRetenida/ActivoTotal -> 0.35173063 | H57: =UtilidadRetenida/ActivoTotal -> 0.38088207 | J57: =UtilidadRetenida/ActivoTotal -> 0.33176776 | K57: =UtilidadRetenida/ActivoTotal -> 0.32745009 | L57: =UtilidadRetenida/ActivoTotal -> 0.34743517 | M57: =UtilidadRetenida/ActivoTotal -> 0.31397954 | N57: =UtilidadRetenida/ActivoTotal -> 0.28745727 | P57: =UtilidadRetenida/ActivoTotal -> -0.013095289 | Q57: =UtilidadRetenida/ActivoTotal -> -0.0076689203 | R57: =UtilidadRetenida/ActivoTotal -> 0.0014909216 | S57: =UtilidadRetenida/ActivoTotal -> 0.033160676 | T57: =UtilidadRetenida/ActivoTotal -> -0.015822072 | V57: =UtilidadRetenida/ActivoTotal -> 0.0014223054 | W57: =UtilidadRetenida/ActivoTotal -> -0.10369915 | X57: =UtilidadRetenida/ActivoTotal -> -0.043437867 | Y57: =UtilidadRetenida/ActivoTotal -> -0.014474761 | AB57: =UtilidadRetenida/ActivoTotal -> 0.206091 | AC57: =UtilidadRetenida/ActivoTotal -> 0.21940685 | AD57: =UtilidadRetenida/ActivoTotal -> 0.17422182 | AF57: =UtilidadRetenida/ActivoTotal -> 0.064468759 | AG57: =UtilidadRetenida/ActivoTotal -> 0.064849721 | AH57: =UtilidadRetenida/ActivoTotal -> 0.064958456 | AJ57: =UtilidadRetenida/ActivoTotal -> 0 | AK57: =UtilidadRetenida/ActivoTotal -> 0.018826858 | AM57: =UtilidadRetenida/ActivoTotal -> 0.15925792 | AN57: =UtilidadRetenida/ActivoTotal -> 0.17444675 | AO57: =UtilidadRetenida/ActivoTotal -> 0.17846535 | AQ57: =UtilidadRetenida/ActivoTotal -> 0.20346069 | AR57: =UtilidadRetenida/ActivoTotal -> 0.17864426 | AS57: =UtilidadRetenida/ActivoTotal -> 0.2031958 | AU57: =UtilidadRetenida/ActivoTotal -> 0.03764388 | AV57: =UtilidadRetenida/ActivoTotal -> 0.072466718 | AW57: =UtilidadRetenida/ActivoTotal -> 0.0561911 | AY57: =UtilidadRetenida/ActivoTotal -> 0.03266359 | AZ57: =UtilidadRetenida/ActivoTotal -> 0.034616774 | BA57: =UtilidadRetenida/ActivoTotal -> 0.068269638 | BB57: =UtilidadRetenida/ActivoTotal -> 0.12531382 | BD57: =UtilidadRetenida/ActivoTotal -> -0.018037649 | BE57: =UtilidadRetenida/ActivoTotal -> -0.012539622 | BF57: =UtilidadRetenida/ActivoTotal -> 0.014057162 | BG57: =UtilidadRetenida/ActivoTotal -> 0.012891567 | BI57: =UtilidadRetenida/ActivoTotal -> -0.79254588 | BJ57: =UtilidadRetenida/ActivoTotal -> -0.6607499 | BK57: =UtilidadRetenida/ActivoTotal -> 0.023779071 | BM57: =UtilidadRetenida/ActivoTotal -> 0.56395233 | BN57: =UtilidadRetenida/ActivoTotal -> 0.62945696 | BO57: =UtilidadRetenida/ActivoTotal -> 0.59662852 | BQ57: =UtilidadRetenida/ActivoTotal -> 0.15577079 | BR57: =UtilidadRetenida/ActivoTotal -> 0.1361376 | BT57: =UtilidadRetenida/ActivoTotal -> 0.58322687 | BU57: =UtilidadRetenida/ActivoTotal -> 0.22818777 | BV57: =UtilidadRetenida/ActivoTotal -> 0.26298008
A58: 3. EBITDA / Activo | D58: =EBITDA/ActivoTotal -> 0.22081187 | E58: =EBITDA/ActivoTotal -> 0.045459291 | F58: =EBITDA/ActivoTotal -> 0.074168262 | G58: =EBITDA/ActivoTotal -> 0.076296506 | H58: =EBITDA/ActivoTotal -> 0.03710795 | J58: =EBITDA/ActivoTotal -> 0.060056612 | K58: =EBITDA/ActivoTotal -> 0.04939415 | L58: =EBITDA/ActivoTotal -> 0.035575751 | M58: =EBITDA/ActivoTotal -> 0.025642117 | N58: =EBITDA/ActivoTotal -> 0.03449865 | P58: =EBITDA/ActivoTotal -> -0.011427862 | Q58: =EBITDA/ActivoTotal -> 0.025152903 | R58: =EBITDA/ActivoTotal -> 0.024794175 | S58: =EBITDA/ActivoTotal -> 0.033271847 | T58: =EBITDA/ActivoTotal -> 0.021088278 | V58: =EBITDA/ActivoTotal -> -0.00057081931 | W58: =EBITDA/ActivoTotal -> -0.10720072 | X58: =EBITDA/ActivoTotal -> 0.021363087 | Y58: =EBITDA/ActivoTotal -> 0.019048506 | AB58: =EBITDA/ActivoTotal -> 0.051033319 | AC58: =EBITDA/ActivoTotal -> 0.075123601 | AD58: =EBITDA/ActivoTotal -> 0.10681373 | AF58: =EBITDA/ActivoTotal -> -1.5473094e-05 | AG58: =EBITDA/ActivoTotal -> 0.00030602023 | AH58: =EBITDA/ActivoTotal -> 0.00010244337 | AJ58: =EBITDA/ActivoTotal -> -33.694818 | AK58: =EBITDA/ActivoTotal -> 0.067841845 | AM58: =EBITDA/ActivoTotal -> 0.10789952 | AN58: =EBITDA/ActivoTotal -> 0.10812796 | AO58: =EBITDA/ActivoTotal -> 0.046668468 | AQ58: =EBITDA/ActivoTotal -> 0.17622688 | AR58: =EBITDA/ActivoTotal -> 0.10317927 | AS58: =EBITDA/ActivoTotal -> 0.031776192 | AU58: =EBITDA/ActivoTotal -> 0.088125848 | AV58: =EBITDA/ActivoTotal -> 0.11894049 | AW58: =EBITDA/ActivoTotal -> 0.14466456 | AY58: =EBITDA/ActivoTotal -> 0.014695955 | AZ58: =EBITDA/ActivoTotal -> 0.025682521 | BA58: =EBITDA/ActivoTotal -> 0.0546546 | BB58: =EBITDA/ActivoTotal -> 0.073655005 | BD58: =EBITDA/ActivoTotal -> 0.042193358 | BE58: =EBITDA/ActivoTotal -> 0.047917867 | BF58: =EBITDA/ActivoTotal -> 0.065662319 | BG58: =EBITDA/ActivoTotal -> 0.053543911 | BI58: =EBITDA/ActivoTotal -> 0.0066916289 | BJ58: =EBITDA/ActivoTotal -> -0.041709991 | BK58: =EBITDA/ActivoTotal -> 0.049982753 | BM58: =EBITDA/ActivoTotal -> 0.17061331 | BN58: =EBITDA/ActivoTotal -> 0.20664609 | BO58: =EBITDA/ActivoTotal -> 0.21763478 | BQ58: =EBITDA/ActivoTotal -> 0.17309965 | BR58: =EBITDA/ActivoTotal -> 0.10573199 | BT58: =EBITDA/ActivoTotal -> 0.083419993 | BU58: =EBITDA/ActivoTotal -> 0.19962933 | BV58: =EBITDA/ActivoTotal -> 0.23193371
A59: 4. Patrimonio / Pasivo | D59: =Patrimonio/PasivoTotal -> 0.28102106 | E59: =Patrimonio/PasivoTotal -> 0.37076467 | F59: =Patrimonio/PasivoTotal -> 0.46657566 | G59: =Patrimonio/PasivoTotal -> 0.54257447 | H59: =Patrimonio/PasivoTotal -> 0.61520627 | J59: =Patrimonio/PasivoTotal -> 0.94945054 | K59: =Patrimonio/PasivoTotal -> 0.89605176 | L59: =Patrimonio/PasivoTotal -> 0.89642868 | M59: =Patrimonio/PasivoTotal -> 0.81577824 | N59: =Patrimonio/PasivoTotal -> 0.6752578 | P59: =Patrimonio/PasivoTotal -> 1.6821343 | Q59: =Patrimonio/PasivoTotal -> 1.3579787 | R59: =Patrimonio/PasivoTotal -> 1.3614698 | S59: =Patrimonio/PasivoTotal -> 1.2768958 | T59: =Patrimonio/PasivoTotal -> 1.0292251 | V59: =Patrimonio/PasivoTotal -> 0.53007844 | W59: =Patrimonio/PasivoTotal -> 2.9325631 | X59: =Patrimonio/PasivoTotal -> 0.76712235 | Y59: =Patrimonio/PasivoTotal -> 0.54816109 | AB59: =Patrimonio/PasivoTotal -> 0.87400983 | AC59: =Patrimonio/PasivoTotal -> 0.93049936 | AD59: =Patrimonio/PasivoTotal -> 1.0386084 | AJ59: =Patrimonio/PasivoTotal -> 0.66666667 | AK59: =Patrimonio/PasivoTotal -> 0.26740315 | AM59: =Patrimonio/PasivoTotal -> 0.60266165 | AN59: =Patrimonio/PasivoTotal -> 0.56242551 | AO59: =Patrimonio/PasivoTotal -> 0.5976776 | AQ59: =Patrimonio/PasivoTotal -> 0.87294987 | AR59: =Patrimonio/PasivoTotal -> 0.62677621 | AS59: =Patrimonio/PasivoTotal -> 0.71823115 | AU59: =Patrimonio/PasivoTotal -> 0.3424515 | AV59: =Patrimonio/PasivoTotal -> 0.38515623 | AW59: =Patrimonio/PasivoTotal -> 0.38980689 | AY59: =Patrimonio/PasivoTotal -> 1.2904628 | AZ59: =Patrimonio/PasivoTotal -> 0.40717998 | BA59: =Patrimonio/PasivoTotal -> 0.45452636 | BB59: =Patrimonio/PasivoTotal -> 0.62237809 | BD59: =Patrimonio/PasivoTotal -> 0.63762157 | BE59: =Patrimonio/PasivoTotal -> 0.60150779 | BF59: =Patrimonio/PasivoTotal -> 0.54462071 | BG59: =Patrimonio/PasivoTotal -> 0.328166 | BI59: =Patrimonio/PasivoTotal -> 0.50547472 | BJ59: =Patrimonio/PasivoTotal -> 0.21630379 | BK59: =Patrimonio/PasivoTotal -> 0.17514324 | BM59: =Patrimonio/PasivoTotal -> 5.5403283 | BN59: =Patrimonio/PasivoTotal -> 8.4113077 | BO59: =Patrimonio/PasivoTotal -> 3.8015562 | BQ59: =Patrimonio/PasivoTotal -> 0.20183096 | BR59: =Patrimonio/PasivoTotal -> 0.16019208 | BT59: =Patrimonio/PasivoTotal -> 1.4694968 | BU59: =Patrimonio/PasivoTotal -> 0.31375703 | BV59: =Patrimonio/PasivoTotal -> 0.37448273
A60: 5. Ventas / Activo | D60: =Ventas/ActivoTotal -> 0.36647316 | E60: =Ventas/ActivoTotal -> 0.37039321 | F60: =Ventas/ActivoTotal -> 0.42213182 | G60: =Ventas/ActivoTotal -> 0.40197607 | H60: =Ventas/ActivoTotal -> 0.23638248 | J60: =Ventas/ActivoTotal -> 0.36568627 | K60: =Ventas/ActivoTotal -> 0.33116867 | L60: =Ventas/ActivoTotal -> 0.32468439 | M60: =Ventas/ActivoTotal -> 0.33556258 | N60: =Ventas/ActivoTotal -> 0.24585832 | P60: =Ventas/ActivoTotal -> 0.019884756 | Q60: =Ventas/ActivoTotal -> 0.29421203 | R60: =Ventas/ActivoTotal -> 0.42957098 | S60: =Ventas/ActivoTotal -> 0.41551161 | T60: =Ventas/ActivoTotal -> 0.26421641 | V60: =Ventas/ActivoTotal -> 0.32839735 | W60: =Ventas/ActivoTotal -> 1.3354797 | X60: =Ventas/ActivoTotal -> 0.95376749 | Y60: =Ventas/ActivoTotal -> 0.58035576 | AB60: =Ventas/ActivoTotal -> 0.496397 | AC60: =Ventas/ActivoTotal -> 0.6641641 | AD60: =Ventas/ActivoTotal -> 0.6824403 | AF60: =Ventas/ActivoTotal -> 0 | AG60: =Ventas/ActivoTotal -> 0.0046655818 | AH60: =Ventas/ActivoTotal -> 0.0022730896 | AJ60: =Ventas/ActivoTotal -> 0 | AK60: =Ventas/ActivoTotal -> 0.42952511 | AM60: =Ventas/ActivoTotal -> 1.1140705 | AN60: =Ventas/ActivoTotal -> 1.0433364 | AO60: =Ventas/ActivoTotal -> 0.55771673 | AQ60: =Ventas/ActivoTotal -> 1.3343134 | AR60: =Ventas/ActivoTotal -> 0.86718503 | AS60: =Ventas/ActivoTotal -> 0.2576415 | AU60: =Ventas/ActivoTotal -> 0.2150808 | AV60: =Ventas/ActivoTotal -> 0.33631266 | AW60: =Ventas/ActivoTotal -> 0.44923041 | AY60: =Ventas/ActivoTotal -> 0.23208384 | AZ60: =Ventas/ActivoTotal -> 0.053823324 | BA60: =Ventas/ActivoTotal -> 0.18294138 | BB60: =Ventas/ActivoTotal -> 0.33810169 | BD60: =Ventas/ActivoTotal -> 0.35902818 | BE60: =Ventas/ActivoTotal -> 0.44701736 | BF60: =Ventas/ActivoTotal -> 0.46648648 | BG60: =Ventas/ActivoTotal -> 0.39779325 | BI60: =Ventas/ActivoTotal -> 2.9727812 | BJ60: =Ventas/ActivoTotal -> 3.0485622 | BK60: =Ventas/ActivoTotal -> 2.815562 | BM60: =Ventas/ActivoTotal -> 1.1453744 | BN60: =Ventas/ActivoTotal -> 1.2715995 | BO60: =Ventas/ActivoTotal -> 1.0710886 | BQ60: =Ventas/ActivoTotal -> 6.9170819 | BR60: =Ventas/ActivoTotal -> 1.7462101 | BT60: =Ventas/ActivoTotal -> 2.0535625 | BU60: =Ventas/ActivoTotal -> 1.9768706 | BV60: =Ventas/ActivoTotal -> 1.6696619
A62: 1. Altman Original (1968) – Manufactureras Públicas | C62: 1 | D62: =D$56*Altman!$H4+D$57*Altman!$I4+D$58*Altman!$J4+D$59*Altman!$K4+D$60*Altman!$L4 -> 1.215303 | E62: =E$56*Altman!$H4+E$57*Altman!$I4+E$58*Altman!$J4+E$59*Altman!$K4+E$60*Altman!$L4 -> 0.85458241 | F62: =F$56*Altman!$H4+F$57*Altman!$I4+F$58*Altman!$J4+F$59*Altman!$K4+F$60*Altman!$L4 -> 1.208347 | G62: =G$56*Altman!$H4+G$57*Altman!$I4+G$58*Altman!$J4+G$59*Altman!$K4+G$60*Altman!$L4 -> 1.4666609 | H62: =H$56*Altman!$H4+H$57*Altman!$I4+H$58*Altman!$J4+H$59*Altman!$K4+H$60*Altman!$L4 -> 1.1134267 | I62: =I$56*Altman!$H4+I$57*Altman!$I4+I$58*Altman!$J4+I$59*Altman!$K4+I$60*Altman!$L4 -> 0 | J62: =J$56*Altman!$H4+J$57*Altman!$I4+J$58*Altman!$J4+J$59*Altman!$K4+J$60*Altman!$L4 -> 2.0229151 | K62: =K$56*Altman!$H4+K$57*Altman!$I4+K$58*Altman!$J4+K$59*Altman!$K4+K$60*Altman!$L4 -> 1.8402767 | ... BV62: =BV$56*Altman!$H4+BV$57*Altman!$I4+BV$58*Altman!$J4+BV$59*Altman!$K4+BV$60*Altman!$L4 -> 4.0095232
A63: 2. Altman Revisado (1983) – Manufactureras Privadas | C63: 2 | D63: =D$56*Altman!$H5+D$57*Altman!$I5+D$58*Altman!$J5+D$59*Altman!$K5+D$60*Altman!$L5 -> 1.1431789 | E63: =E$56*Altman!$H5+E$57*Altman!$I5+E$58*Altman!$J5+E$59*Altman!$K5+E$60*Altman!$L5 -> 0.73620517 | F63: =F$56*Altman!$H5+F$57*Altman!$I5+F$58*Altman!$J5+F$59*Altman!$K5+F$60*Altman!$L5 -> 1.0072855 | G63: =G$56*Altman!$H5+G$57*Altman!$I5+G$58*Altman!$J5+G$59*Altman!$K5+G$60*Altman!$L5 -> 1.1609984 | H63: =H$56*Altman!$H5+H$57*Altman!$I5+H$58*Altman!$J5+H$59*Altman!$K5+H$60*Altman!$L5 -> 0.8439049 | I63: =I$56*Altman!$H5+I$57*Altman!$I5+I$58*Altman!$J5+I$59*Altman!$K5+I$60*Altman!$L5 -> 0 | J63: =J$56*Altman!$H5+J$57*Altman!$I5+J$58*Altman!$J5+J$59*Altman!$K5+J$60*Altman!$L5 -> 1.4852031 | K63: =K$56*Altman!$H5+K$57*Altman!$I5+K$58*Altman!$J5+K$59*Altman!$K5+K$60*Altman!$L5 -> 1.3468185 | ... BV63: =BV$56*Altman!$H5+BV$57*Altman!$I5+BV$58*Altman!$J5+BV$59*Altman!$K5+BV$60*Altman!$L5 -> 3.3534844
A64: 3. Z'' para No Manufactureras y Mercados Emergentes | C64: 3 | D64: =D$56*Altman!$H6+D$57*Altman!$I6+D$58*Altman!$J6+D$59*Altman!$K6+D$60*Altman!$L6 -> 0.55023545 | E64: =E$56*Altman!$H6+E$57*Altman!$I6+E$58*Altman!$J6+E$59*Altman!$K6+E$60*Altman!$L6 -> 0.11720081 | F64: =F$56*Altman!$H6+F$57*Altman!$I6+F$58*Altman!$J6+F$59*Altman!$K6+F$60*Altman!$L6 -> 1.0202474 | G64: =G$56*Altman!$H6+G$57*Altman!$I6+G$58*Altman!$J6+G$59*Altman!$K6+G$60*Altman!$L6 -> 2.2013895 | H64: =H$56*Altman!$H6+H$57*Altman!$I6+H$58*Altman!$J6+H$59*Altman!$K6+H$60*Altman!$L6 -> 1.3291947 | I64: =I$56*Altman!$H6+I$57*Altman!$I6+I$58*Altman!$J6+I$59*Altman!$K6+I$60*Altman!$L6 -> 0 | J64: =J$56*Altman!$H6+J$57*Altman!$I6+J$58*Altman!$J6+J$59*Altman!$K6+J$60*Altman!$L6 -> 4.8048355 | K64: =K$56*Altman!$H6+K$57*Altman!$I6+K$58*Altman!$J6+K$59*Altman!$K6+K$60*Altman!$L6 -> 4.253856 | ... BV64: =BV$56*Altman!$H6+BV$57*Altman!$I6+BV$58*Altman!$J6+BV$59*Altman!$K6+BV$60*Altman!$L6 -> 8.1752967
A65: 4. Altman Modificado (Ventas Ajustadas) | C65: 4 | D65: =D$56*Altman!$H7+D$57*Altman!$I7+D$58*Altman!$J7+D$59*Altman!$K7+D$60*Altman!$L7 -> 1.2116382 | E65: =E$56*Altman!$H7+E$57*Altman!$I7+E$58*Altman!$J7+E$59*Altman!$K7+E$60*Altman!$L7 -> 0.85087848 | F65: =F$56*Altman!$H7+F$57*Altman!$I7+F$58*Altman!$J7+F$59*Altman!$K7+F$60*Altman!$L7 -> 1.2041257 | G65: =G$56*Altman!$H7+G$57*Altman!$I7+G$58*Altman!$J7+G$59*Altman!$K7+G$60*Altman!$L7 -> 1.4626411 | H65: =H$56*Altman!$H7+H$57*Altman!$I7+H$58*Altman!$J7+H$59*Altman!$K7+H$60*Altman!$L7 -> 1.1110629 | I65: =I$56*Altman!$H7+I$57*Altman!$I7+I$58*Altman!$J7+I$59*Altman!$K7+I$60*Altman!$L7 -> 0 | J65: =J$56*Altman!$H7+J$57*Altman!$I7+J$58*Altman!$J7+J$59*Altman!$K7+J$60*Altman!$L7 -> 2.0192582 | K65: =K$56*Altman!$H7+K$57*Altman!$I7+K$58*Altman!$J7+K$59*Altman!$K7+K$60*Altman!$L7 -> 1.836965 | ... BV65: =BV$56*Altman!$H7+BV$57*Altman!$I7+BV$58*Altman!$J7+BV$59*Altman!$K7+BV$60*Altman!$L7 -> 3.9928266
A66: 5. Z’-Score Revisado para PYMES de Europa Central y Este | C66: 5 | D66: =D$56*Altman!$H8+D$57*Altman!$I8+D$58*Altman!$J8+D$59*Altman!$K8+D$60*Altman!$L8 -> 1.1431789 | E66: =E$56*Altman!$H8+E$57*Altman!$I8+E$58*Altman!$J8+E$59*Altman!$K8+E$60*Altman!$L8 -> 0.73620517 | F66: =F$56*Altman!$H8+F$57*Altman!$I8+F$58*Altman!$J8+F$59*Altman!$K8+F$60*Altman!$L8 -> 1.0072855 | G66: =G$56*Altman!$H8+G$57*Altman!$I8+G$58*Altman!$J8+G$59*Altman!$K8+G$60*Altman!$L8 -> 1.1609984 | H66: =H$56*Altman!$H8+H$57*Altman!$I8+H$58*Altman!$J8+H$59*Altman!$K8+H$60*Altman!$L8 -> 0.8439049 | I66: =I$56*Altman!$H8+I$57*Altman!$I8+I$58*Altman!$J8+I$59*Altman!$K8+I$60*Altman!$L8 -> 0 | J66: =J$56*Altman!$H8+J$57*Altman!$I8+J$58*Altman!$J8+J$59*Altman!$K8+J$60*Altman!$L8 -> 1.4852031 | K66: =K$56*Altman!$H8+K$57*Altman!$I8+K$58*Altman!$J8+K$59*Altman!$K8+K$60*Altman!$L8 -> 1.3468185 | ... BV66: =BV$56*Altman!$H8+BV$57*Altman!$I8+BV$58*Altman!$J8+BV$59*Altman!$K8+BV$60*Altman!$L8 -> 3.3534844
A67: 6. Z''-Score Mercados Emergentes (con constante) | C67: 6 | D67: =D$56*Altman!$H9+D$57*Altman!$I9+D$58*Altman!$J9+D$59*Altman!$K9+D$60*Altman!$L9 -> 0.55023545 | E67: =E$56*Altman!$H9+E$57*Altman!$I9+E$58*Altman!$J9+E$59*Altman!$K9+E$60*Altman!$L9 -> 0.11720081 | F67: =F$56*Altman!$H9+F$57*Altman!$I9+F$58*Altman!$J9+F$59*Altman!$K9+F$60*Altman!$L9 -> 1.0202474 | G67: =G$56*Altman!$H9+G$57*Altman!$I9+G$58*Altman!$J9+G$59*Altman!$K9+G$60*Altman!$L9 -> 2.2013895 | H67: =H$56*Altman!$H9+H$57*Altman!$I9+H$58*Altman!$J9+H$59*Altman!$K9+H$60*Altman!$L9 -> 1.3291947 | I67: =I$56*Altman!$H9+I$57*Altman!$I9+I$58*Altman!$J9+I$59*Altman!$K9+I$60*Altman!$L9 -> 0 | J67: =J$56*Altman!$H9+J$57*Altman!$I9+J$58*Altman!$J9+J$59*Altman!$K9+J$60*Altman!$L9 -> 4.8048355 | K67: =K$56*Altman!$H9+K$57*Altman!$I9+K$58*Altman!$J9+K$59*Altman!$K9+K$60*Altman!$L9 -> 4.253856 | ... BV67: =BV$56*Altman!$H9+BV$57*Altman!$I9+BV$58*Altman!$J9+BV$59*Altman!$K9+BV$60*Altman!$L9 -> 8.1752967
A68: 7. Pesos Iguales (Propuesta Experimental) | C68: 7 | D68: =D$56*Altman!$H10+D$57*Altman!$I10+D$58*Altman!$J10+D$59*Altman!$K10+D$60*Altman!$L10 -> 0.79135938 | E68: =E$56*Altman!$H10+E$57*Altman!$I10+E$58*Altman!$J10+E$59*Altman!$K10+E$60*Altman!$L10 -> 0.83463328 | F68: =F$56*Altman!$H10+F$57*Altman!$I10+F$58*Altman!$J10+F$59*Altman!$K10+F$60*Altman!$L10 -> 1.1277817 | G68: =G$56*Altman!$H10+G$57*Altman!$I10+G$58*Altman!$J10+G$59*Altman!$K10+G$60*Altman!$L10 -> 1.36836 | H68: =H$56*Altman!$H10+H$57*Altman!$I10+H$58*Altman!$J10+H$59*Altman!$K10+H$60*Altman!$L10 -> 1.1464366 | I68: =I$56*Altman!$H10+I$57*Altman!$I10+I$58*Altman!$J10+I$59*Altman!$K10+I$60*Altman!$L10 -> 0 | J68: =J$56*Altman!$H10+J$57*Altman!$I10+J$58*Altman!$J10+J$59*Altman!$K10+J$60*Altman!$L10 -> 2.0610418 | K68: =K$56*Altman!$H10+K$57*Altman!$I10+K$58*Altman!$J10+K$59*Altman!$K10+K$60*Altman!$L10 -> 1.8957698 | ... BV68: =BV$56*Altman!$H10+BV$57*Altman!$I10+BV$58*Altman!$J10+BV$59*Altman!$K10+BV$60*Altman!$L10 -> 3.3570737
A69: 8. Ajuste para Empresas Medianas Latinoamericanas | C69: 8 | D69: =D$56*Altman!$H11+D$57*Altman!$I11+D$58*Altman!$J11+D$59*Altman!$K11+D$60*Altman!$L11 -> 0.83390814 | E69: =E$56*Altman!$H11+E$57*Altman!$I11+E$58*Altman!$J11+E$59*Altman!$K11+E$60*Altman!$L11 -> 0.60620942 | F69: =F$56*Altman!$H11+F$57*Altman!$I11+F$58*Altman!$J11+F$59*Altman!$K11+F$60*Altman!$L11 -> 0.92913095 | G69: =G$56*Altman!$H11+G$57*Altman!$I11+G$58*Altman!$J11+G$59*Altman!$K11+G$60*Altman!$L11 -> 1.2094087 | H69: =H$56*Altman!$H11+H$57*Altman!$I11+H$58*Altman!$J11+H$59*Altman!$K11+H$60*Altman!$L11 -> 0.83292425 | I69: =I$56*Altman!$H11+I$57*Altman!$I11+I$58*Altman!$J11+I$59*Altman!$K11+I$60*Altman!$L11 -> 0 | J69: =J$56*Altman!$H11+J$57*Altman!$I11+J$58*Altman!$J11+J$59*Altman!$K11+J$60*Altman!$L11 -> 1.8534418 | K69: =K$56*Altman!$H11+K$57*Altman!$I11+K$58*Altman!$J11+K$59*Altman!$K11+K$60*Altman!$L11 -> 1.6676877 | ... BV69: =BV$56*Altman!$H11+BV$57*Altman!$I11+BV$58*Altman!$J11+BV$59*Altman!$K11+BV$60*Altman!$L11 -> 3.9267405
D70: {=index(D62:D70,sel)} -> 0.55023545 | E70: {=index(E62:E70,sel)} -> 0.11720081 | F70: {=index(F62:F70,sel)} -> 1.0202474 | G70: {=index(G62:G70,sel)} -> 2.2013895 | H70: {=index(H62:H70,sel)} -> 1.3291947 | I70: {=index(I62:I70,sel)} -> 0 | J70: {=index(J62:J70,sel)} -> 4.8048355 | K70: {=index(K62:K70,sel)} -> 4.253856 | ... BV70: {=index(BV62:BV70,sel)} -> 8.1752967
A71: {=index(A62:A69,sel)} -> 3. Z'' para No Manufactureras y Mercados Emergentes | B71: 3 | D71: {=if(D70<index(low,sel),"Mal",if(D70>index(high,sel),"Bien","Soso"))} -> Mal | E71: {=if(E70<index(low,sel),"Mal",if(E70>index(high,sel),"Bien","Soso"))} -> Mal | F71: {=if(F70<index(low,sel),"Mal",if(F70>index(high,sel),"Bien","Soso"))} -> Mal | G71: {=if(G70<index(low,sel),"Mal",if(G70>index(high,sel),"Bien","Soso"))} -> Soso | H71: {=if(H70<index(low,sel),"Mal",if(H70>index(high,sel),"Bien","Soso"))} -> Soso | J71: {=if(J70<index(low,sel),"Mal",if(J70>index(high,sel),"Bien","Soso"))} -> Bien | K71: {=if(K70<index(low,sel),"Mal",if(K70>index(high,sel),"Bien","Soso"))} -> Bien | L71: {=if(L70<index(low,sel),"Mal",if(L70>index(high,sel),"Bien","Soso"))} -> Bien | M71: {=if(M70<index(low,sel),"Mal",if(M70>index(high,sel),"Bien","Soso"))} -> Bien | N71: {=if(N70<index(low,sel),"Mal",if(N70>index(high,sel),"Bien","Soso"))} -> Bien | P71: {=if(P70<index(low,sel),"Mal",if(P70>index(high,sel),"Bien","Soso"))} -> Bien | Q71: {=if(Q70<index(low,sel),"Mal",if(Q70>index(high,sel),"Bien","Soso"))} -> Soso | R71: {=if(R70<index(low,sel),"Mal",if(R70>index(high,sel),"Bien","Soso"))} -> Soso | S71: {=if(S70<index(low,sel),"Mal",if(S70>index(high,sel),"Bien","Soso"))} -> Soso | T71: {=if(T70<index(low,sel),"Mal",if(T70>index(high,sel),"Bien","Soso"))} -> Soso | V71: {=if(V70<index(low,sel),"Mal",if(V70>index(high,sel),"Bien","Soso"))} -> Mal | W71: {=if(W70<index(low,sel),"Mal",if(W70>index(high,sel),"Bien","Soso"))} -> Bien | X71: {=if(X70<index(low,sel),"Mal",if(X70>index(high,sel),"Bien","Soso"))} -> Bien | Y71: {=if(Y70<index(low,sel),"Mal",if(Y70>index(high,sel),"Bien","Soso"))} -> Mal | AB71: {=if(AB70<index(low,sel),"Mal",if(AB70>index(high,sel),"Bien","Soso"))} -> Bien | AC71: {=if(AC70<index(low,sel),"Mal",if(AC70>index(high,sel),"Bien","Soso"))} -> Bien | AD71: {=if(AD70<index(low,sel),"Mal",if(AD70>index(high,sel),"Bien","Soso"))} -> Bien | AF71: {=if(AF70<index(low,sel),"Mal",if(AF70>index(high,sel),"Bien","Soso"))} -> Bien | AG71: {=if(AG70<index(low,sel),"Mal",if(AG70>index(high,sel),"Bien","Soso"))} -> Bien | AH71: {=if(AH70<index(low,sel),"Mal",if(AH70>index(high,sel),"Bien","Soso"))} -> Bien | AJ71: {=if(AJ70<index(low,sel),"Mal",if(AJ70>index(high,sel),"Bien","Soso"))} -> Mal | AK71: {=if(AK70<index(low,sel),"Mal",if(AK70>index(high,sel),"Bien","Soso"))} -> Soso | AM71: {=if(AM70<index(low,sel),"Mal",if(AM70>index(high,sel),"Bien","Soso"))} -> Bien | AN71: {=if(AN70<index(low,sel),"Mal",if(AN70>index(high,sel),"Bien","Soso"))} -> Bien | AO71: {=if(AO70<index(low,sel),"Mal",if(AO70>index(high,sel),"Bien","Soso"))} -> Bien | AQ71: {=if(AQ70<index(low,sel),"Mal",if(AQ70>index(high,sel),"Bien","Soso"))} -> Bien | AR71: {=if(AR70<index(low,sel),"Mal",if(AR70>index(high,sel),"Bien","Soso"))} -> Bien | AS71: {=if(AS70<index(low,sel),"Mal",if(AS70>index(high,sel),"Bien","Soso"))} -> Bien | AU71: {=if(AU70<index(low,sel),"Mal",if(AU70>index(high,sel),"Bien","Soso"))} -> Bien | AV71: {=if(AV70<index(low,sel),"Mal",if(AV70>index(high,sel),"Bien","Soso"))} -> Bien | AW71: {=if(AW70<index(low,sel),"Mal",if(AW70>index(high,sel),"Bien","Soso"))} -> Bien | AY71: {=if(AY70<index(low,sel),"Mal",if(AY70>index(high,sel),"Bien","Soso"))} -> Bien | AZ71: {=if(AZ70<index(low,sel),"Mal",if(AZ70>index(high,sel),"Bien","Soso"))} -> Bien | BA71: {=if(BA70<index(low,sel),"Mal",if(BA70>index(high,sel),"Bien","Soso"))} -> Bien | BB71: {=if(BB70<index(low,sel),"Mal",if(BB70>index(high,sel),"Bien","Soso"))} -> Bien | BD71: {=if(BD70<index(low,sel),"Mal",if(BD70>index(high,sel),"Bien","Soso"))} -> Bien | BE71: {=if(BE70<index(low,sel),"Mal",if(BE70>index(high,sel),"Bien","Soso"))} -> Bien | BF71: {=if(BF70<index(low,sel),"Mal",if(BF70>index(high,sel),"Bien","Soso"))} -> Bien | BG71: {=if(BG70<index(low,sel),"Mal",if(BG70>index(high,sel),"Bien","Soso"))} -> Soso | BI71: {=if(BI70<index(low,sel),"Mal",if(BI70>index(high,sel),"Bien","Soso"))} -> Mal | BJ71: {=if(BJ70<index(low,sel),"Mal",if(BJ70>index(high,sel),"Bien","Soso"))} -> Mal | BK71: {=if(BK70<index(low,sel),"Mal",if(BK70>index(high,sel),"Bien","Soso"))} -> Soso | BM71: {=if(BM70<index(low,sel),"Mal",if(BM70>index(high,sel),"Bien","Soso"))} -> Bien | BN71: {=if(BN70<index(low,sel),"Mal",if(BN70>index(high,sel),"Bien","Soso"))} -> Bien | BO71: {=if(BO70<index(low,sel),"Mal",if(BO70>index(high,sel),"Bien","Soso"))} -> Bien | BQ71: {=if(BQ70<index(low,sel),"Mal",if(BQ70>index(high,sel),"Bien","Soso"))} -> Bien | BR71: {=if(BR70<index(low,sel),"Mal",if(BR70>index(high,sel),"Bien","Soso"))} -> Bien | BT71: {=if(BT70<index(low,sel),"Mal",if(BT70>index(high,sel),"Bien","Soso"))} -> Bien | BU71: {=if(BU70<index(low,sel),"Mal",if(BU70>index(high,sel),"Bien","Soso"))} -> Bien | BV71: {=if(BV70<index(low,sel),"Mal",if(BV70>index(high,sel),"Bien","Soso"))} -> Bien
A74: ESTRUCTURAS %
A76: Ventas | D76: =D10/D$10 -> 1 | E76: =E10/E$10 -> 1 | F76: =F10/F$10 -> 1 | G76: =G10/G$10 -> 1 | H76: =H10/H$10 -> 1 | J76: =J10/J$10 -> 1 | K76: =K10/K$10 -> 1 | L76: =L10/L$10 -> 1 | M76: =M10/M$10 -> 1 | N76: =N10/N$10 -> 1 | P76: =P10/P$10 -> 1 | Q76: =Q10/Q$10 -> 1 | R76: =R10/R$10 -> 1 | S76: =S10/S$10 -> 1 | T76: =T10/T$10 -> 1 | V76: =V10/V$10 -> 1 | W76: =W10/W$10 -> 1 | X76: =X10/X$10 -> 1 | Y76: =Y10/Y$10 -> 1 | AB76: =AB10/AB$10 -> 1 | AC76: =AC10/AC$10 -> 1 | AD76: =AD10/AD$10 -> 1 | AG76: =AG10/AG$10 -> 1 | AH76: =AH10/AH$10 -> 1 | AK76: =AK10/AK$10 -> 1 | AM76: =AM10/AM$10 -> 1 | AN76: =AN10/AN$10 -> 1 | AO76: =AO10/AO$10 -> 1 | AQ76: =AQ10/AQ$10 -> 1 | AR76: =AR10/AR$10 -> 1 | AS76: =AS10/AS$10 -> 1 | AU76: =AU10/AU$10 -> 1 | AV76: =AV10/AV$10 -> 1 | AW76: =AW10/AW$10 -> 1 | AY76: =AY10/AY$10 -> 1 | AZ76: =AZ10/AZ$10 -> 1 | BA76: =BA10/BA$10 -> 1 | BB76: =BB10/BB$10 -> 1 | BD76: =BD10/BD$10 -> 1 | BE76: =BE10/BE$10 -> 1 | BF76: =BF10/BF$10 -> 1 | BG76: =BG10/BG$10 -> 1 | BI76: =BI10/BI$10 -> 1 | BJ76: =BJ10/BJ$10 -> 1 | BK76: =BK10/BK$10 -> 1 | BM76: =BM10/BM$10 -> 1 | BN76: =BN10/BN$10 -> 1 | BO76: =BO10/BO$10 -> 1 | BQ76: =BQ10/BQ$10 -> 1 | BR76: =BR10/BR$10 -> 1 | BT76: =BT10/BT$10 -> 1 | BU76: =BU10/BU$10 -> 1 | BV76: =BV10/BV$10 -> 1
A77: Utilidad Neta | D77: =D11/D$10 -> 0.60253218 | E77: =E11/E$10 -> 0.12273252 | F77: =F11/F$10 -> 0.17569929 | G77: =G11/G$10 -> 0.1898036 | H77: =H11/H$10 -> 0.15698266 | J77: =J11/J$10 -> 0.057590987 | K77: =K11/K$10 -> 0.064881472 | L77: =L11/L$10 -> 0.044664674 | M77: =M11/M$10 -> 0.017187777 | N77: =N11/N$10 -> 0.0068949439 | P77: =P11/P$10 -> -0.69400046 | Q77: =Q11/Q$10 -> 0.018113782 | R77: =R11/R$10 -> 0.024909934 | S77: =S11/S$10 -> 0.041714415 | T77: =T11/T$10 -> -0.037415401 | V77: =V11/V$10 -> -0.0017381971 | W77: =W11/W$10 -> -0.080271322 | X77: =X11/X$10 -> 0.016567425 | Y77: =Y11/Y$10 -> 0.032822118 | AB77: =AB11/AB$10 -> 0.029537215 | AC77: =AC11/AC$10 -> 0.017030286 | AD77: =AD11/AD$10 -> 0.054551655 | AG77: =AG11/AG$10 -> 0.065591012 | AH77: =AH11/AH$10 -> 0.0450679 | AK77: =AK11/AK$10 -> 0.15794617 | AM77: =AM11/AM$10 -> 0.055814943 | AN77: =AN11/AN$10 -> 0.052407406 | AO77: =AO11/AO$10 -> 0.046778875 | AQ77: =AQ11/AQ$10 -> 0.085780491 | AR77: =AR11/AR$10 -> 0.060162483 | AS77: =AS11/AS$10 -> 0.067888307 | AU77: =AU11/AU$10 -> 0.10590814 | AV77: =AV11/AV$10 -> 0.11655712 | AW77: =AW11/AW$10 -> 0.1298309 | AY77: =AY11/AY$10 -> 0.0037807803 | AZ77: =AZ11/AZ$10 -> 0.28475302 | BA77: =BA11/BA$10 -> 0.24930652 | BB77: =BB11/BB$10 -> 0.20346654 | BD77: =BD11/BD$10 -> 0.0081734071 | BE77: =BE11/BE$10 -> 0.016603347 | BF77: =BF11/BF$10 -> 0.040766748 | BG77: =BG11/BG$10 -> 0.0033326994 | BI77: =BI11/BI$10 -> -0.0088496505 | BJ77: =BJ11/BJ$10 -> -0.022188514 | BK77: =BK11/BK$10 -> 0.0057612576 | BM77: =BM11/BM$10 -> 0.11171792 | BN77: =BN11/BN$10 -> 0.12188159 | BO77: =BO11/BO$10 -> 0.15239271 | BQ77: =BQ11/BQ$10 -> 0.022621428 | BR77: =BR11/BR$10 -> 0.059655492 | BT77: =BT11/BT$10 -> 0.026232866 | BU77: =BU11/BU$10 -> 0.098576132 | BV77: =BV11/BV$10 -> 0.08067316
A79: Activo Corriente | D79: =D13/D$16 -> 0.32839763 | E79: =E13/E$16 -> 0.25366132 | F79: =F13/F$16 -> 0.38622364 | G79: =G13/G$16 -> 0.37033293 | H79: =H13/H$16 -> 0.28316104 | J79: =J13/J$16 -> 0.53007746 | K79: =K13/K$16 -> 0.56107167 | L79: =L13/L$16 -> 0.59219247 | M79: =M13/M$16 -> 0.59771681 | N79: =N13/N$16 -> 0.57626491 | P79: =P13/P$16 -> 0.72196809 | Q79: =Q13/Q$16 -> 0.21027027 | R79: =R13/R$16 -> 0.28653428 | S79: =S13/S$16 -> 0.30445819 | T79: =T13/T$16 -> 0.31029159 | V79: =V13/V$16 -> 0.27522739 | W79: =W13/W$16 -> 0.89467247 | X79: =X13/X$16 -> 0.92876354 | Y79: =Y13/Y$16 -> 0.3771282 | AB79: =AB13/AB$16 -> 0.7059267 | AC79: =AC13/AC$16 -> 0.60641087 | AD79: =AD13/AD$16 -> 0.6743518 | AF79: =AF13/AF$16 -> 0.89293171 | AG79: =AG13/AG$16 -> 0.89280725 | AH79: =AH13/AH$16 -> 0.89281793 | AJ79: =AJ13/AJ$16 -> 0.4 | AK79: =AK13/AK$16 -> 0.99247985 | AM79: =AM13/AM$16 -> 0.70588289 | AN79: =AN13/AN$16 -> 0.75297363 | AO79: =AO13/AO$16 -> 0.71073389 | AQ79: =AQ13/AQ$16 -> 0.97047165 | AR79: =AR13/AR$16 -> 0.9748958 | AS79: =AS13/AS$16 -> 0.9731695 | AU79: =AU13/AU$16 -> 0.8674083 | AV79: =AV13/AV$16 -> 0.82221282 | AW79: =AW13/AW$16 -> 0.79135903 | AY79: =AY13/AY$16 -> 0.88765715 | AZ79: =AZ13/AZ$16 -> 0.94586638 | BA79: =BA13/BA$16 -> 0.94663039 | BB79: =BB13/BB$16 -> 0.93751438 | BD79: =BD13/BD$16 -> 0.50016778 | BE79: =BE13/BE$16 -> 0.52601435 | BF79: =BF13/BF$16 -> 0.53004113 | BG79: =BG13/BG$16 -> 0.53301117 | BI79: =BI13/BI$16 -> 0.98028749 | BJ79: =BJ13/BJ$16 -> 0.97813273 | BK79: =BK13/BK$16 -> 0.96592074 | BM79: =BM13/BM$16 -> 0.73954301 | BN79: =BN13/BN$16 -> 0.75775027 | BO79: =BO13/BO$16 -> 0.72760104 | BQ79: =BQ13/BQ$16 -> 0.99189179 | BR79: =BR13/BR$16 -> 0.98929445 | BT79: =BT13/BT$16 -> 0.99360847 | BU79: =BU13/BU$16 -> 0.99577135 | BV79: =BV13/BV$16 -> 0.99210582
A80: Activo No Corriente | D80: =D14/D$16 -> 0 | E80: =E14/E$16 -> 0 | F80: =F14/F$16 -> 0 | G80: =G14/G$16 -> 0 | H80: =H14/H$16 -> 0 | J80: =J14/J$16 -> 0.12708557 | K80: =K14/K$16 -> 0.10569467 | L80: =L14/L$16 -> 0.16541172 | M80: =M14/M$16 -> 0.17670724 | N80: =N14/N$16 -> 0.075319995 | P80: =P14/P$16 -> 0.11952042 | Q80: =Q14/Q$16 -> 0.10985061 | R80: =R14/R$16 -> 0.098123453 | S80: =S14/S$16 -> 0.10831632 | T80: =T14/T$16 -> 0.10186658 | V80: =V14/V$16 -> 0.72477261 | W80: =W14/W$16 -> 0.10532753 | X80: =X14/X$16 -> 0.071236459 | Y80: =Y14/Y$16 -> 0.087114253 | AB80: =AB14/AB$16 -> 0.15103191 | AC80: =AC14/AC$16 -> 0.1358624 | AD80: =AD14/AD$16 -> 0.1375919 | AF80: =AF14/AF$16 -> 0.10706829 | AG80: =AG14/AG$16 -> 0.10719275 | AH80: =AH14/AH$16 -> 0.10718207 | AJ80: =AJ14/AJ$16 -> 0 | AK80: =AK14/AK$16 -> 0.0071072041 | AM80: =AM14/AM$16 -> 0.23205013 | AN80: =AN14/AN$16 -> 0.2215724 | AO80: =AO14/AO$16 -> 0.26242592 | AQ80: =AQ14/AQ$16 -> 0.029320486 | AR80: =AR14/AR$16 -> 0.02195446 | AS80: =AS14/AS$16 -> 0.02374122 | AU80: =AU14/AU$16 -> 0.12674561 | AV80: =AV14/AV$16 -> 0.17039115 | AW80: =AW14/AW$16 -> 0.19939421 | AY80: =AY14/AY$16 -> 0.02111404 | AZ80: =AZ14/AZ$16 -> 0.0049144442 | BA80: =BA14/BA$16 -> 0.024198956 | BB80: =BB14/BB$16 -> 0.040790049 | BD80: =BD14/BD$16 -> 0.44506397 | BE80: =BE14/BE$16 -> 0.41689899 | BF80: =BF14/BF$16 -> 0.41954887 | BG80: =BG14/BG$16 -> 0.42634356 | BI80: =BI14/BI$16 -> 0.0052452989 | BJ80: =BJ14/BJ$16 -> 0.011040645 | BK80: =BK14/BK$16 -> 0.025993319 | BM80: =BM14/BM$16 -> 0.26045699 | BN80: =BN14/BN$16 -> 0.24224973 | BO80: =BO14/BO$16 -> 0.27239896 | BQ80: =BQ14/BQ$16 -> 0.0081082144 | BR80: =BR14/BR$16 -> 0.01070555 | BT80: =BT14/BT$16 -> 0.0063915305 | BU80: =BU14/BU$16 -> 0.0042286513 | BV80: =BV14/BV$16 -> 0.0078941755
A81: Activo Diferido | D81: =D15/D$16 -> 0.67160237 | E81: =E15/E$16 -> 0.74633868 | F81: =F15/F$16 -> 0.61377636 | G81: =G15/G$16 -> 0.62966707 | H81: =H15/H$16 -> 0.71683896 | J81: =J15/J$16 -> 0.34283698 | K81: =K15/K$16 -> 0.33323366 | L81: =L15/L$16 -> 0.24239581 | M81: =M15/M$16 -> 0.22557595 | N81: =N15/N$16 -> 0.3484151 | P81: =P15/P$16 -> 0.15851149 | Q81: =Q15/Q$16 -> 0.67987912 | R81: =R15/R$16 -> 0.61534226 | S81: =S15/S$16 -> 0.58722549 | T81: =T15/T$16 -> 0.58784183 | V81: =V15/V$16 -> 0 | W81: =W15/W$16 -> 0 | X81: =X15/X$16 -> 0 | Y81: =Y15/Y$16 -> 0.53575755 | AB81: =AB15/AB$16 -> 0.14304139 | AC81: =AC15/AC$16 -> 0.25772672 | AD81: =AD15/AD$16 -> 0.1880563 | AF81: =AF15/AF$16 -> 0 | AG81: =AG15/AG$16 -> 0 | AH81: =AH15/AH$16 -> 0 | AJ81: =AJ15/AJ$16 -> 0.6 | AK81: =AK15/AK$16 -> 0.00041294746 | AM81: =AM15/AM$16 -> 0.06206698 | AN81: =AN15/AN$16 -> 0.025453974 | AO81: =AO15/AO$16 -> 0.026840193 | AQ81: =AQ15/AQ$16 -> 0.00020785995 | AR81: =AR15/AR$16 -> 0.0031497439 | AS81: =AS15/AS$16 -> 0.0030892811 | AU81: =AU15/AU$16 -> 0.0058460894 | AV81: =AV15/AV$16 -> 0.0073960329 | AW81: =AW15/AW$16 -> 0.0092467575 | AY81: =AY15/AY$16 -> 0.091228812 | AZ81: =AZ15/AZ$16 -> 0.049219175 | BA81: =BA15/BA$16 -> 0.02917065 | BB81: =BB15/BB$16 -> 0.02169557 | BD81: =BD15/BD$16 -> 0.05476825 | BE81: =BE15/BE$16 -> 0.057086666 | BF81: =BF15/BF$16 -> 0.050409998 | BG81: =BG15/BG$16 -> 0.040645264 | BI81: =BI15/BI$16 -> 0.014467207 | BJ81: =BJ15/BJ$16 -> 0.010826628 | BK81: =BK15/BK$16 -> 0.008085939 | BM81: =BM15/BM$16 -> 0 | BN81: =BN15/BN$16 -> 0 | BO81: =BO15/BO$16 -> 0 | BQ81: =BQ15/BQ$16 -> 0 | BR81: =BR15/BR$16 -> 0 | BT81: =BT15/BT$16 -> 0 | BU81: =BU15/BU$16 -> 0 | BV81: =BV15/BV$16 -> 0
A82: Total de Activo | D82: =D16/D$16 -> 1 | E82: =E16/E$16 -> 1 | F82: =F16/F$16 -> 1 | G82: =G16/G$16 -> 1 | H82: =H16/H$16 -> 1 | J82: =J16/J$16 -> 1 | K82: =K16/K$16 -> 1 | L82: =L16/L$16 -> 1 | M82: =M16/M$16 -> 1 | N82: =N16/N$16 -> 1 | P82: =P16/P$16 -> 1 | Q82: =Q16/Q$16 -> 1 | R82: =R16/R$16 -> 1 | S82: =S16/S$16 -> 1 | T82: =T16/T$16 -> 1 | V82: =V16/V$16 -> 1 | W82: =W16/W$16 -> 1 | X82: =X16/X$16 -> 1 | Y82: =Y16/Y$16 -> 1 | AB82: =AB16/AB$16 -> 1 | AC82: =AC16/AC$16 -> 1 | AD82: =AD16/AD$16 -> 1 | AF82: =AF16/AF$16 -> 1 | AG82: =AG16/AG$16 -> 1 | AH82: =AH16/AH$16 -> 1 | AJ82: =AJ16/AJ$16 -> 1 | AK82: =AK16/AK$16 -> 1 | AM82: =AM16/AM$16 -> 1 | AN82: =AN16/AN$16 -> 1 | AO82: =AO16/AO$16 -> 1 | AQ82: =AQ16/AQ$16 -> 1 | AR82: =AR16/AR$16 -> 1 | AS82: =AS16/AS$16 -> 1 | AU82: =AU16/AU$16 -> 1 | AV82: =AV16/AV$16 -> 1 | AW82: =AW16/AW$16 -> 1 | AY82: =AY16/AY$16 -> 1 | AZ82: =AZ16/AZ$16 -> 1 | BA82: =BA16/BA$16 -> 1 | BB82: =BB16/BB$16 -> 1 | BD82: =BD16/BD$16 -> 1 | BE82: =BE16/BE$16 -> 1 | BF82: =BF16/BF$16 -> 1 | BG82: =BG16/BG$16 -> 1 | BI82: =BI16/BI$16 -> 1 | BJ82: =BJ16/BJ$16 -> 1 | BK82: =BK16/BK$16 -> 1 | BM82: =BM16/BM$16 -> 1 | BN82: =BN16/BN$16 -> 1 | BO82: =BO16/BO$16 -> 1 | BQ82: =BQ16/BQ$16 -> 1 | BR82: =BR16/BR$16 -> 1 | BT82: =BT16/BT$16 -> 1 | BU82: =BU16/BU$16 -> 1 | BV82: =BV16/BV$16 -> 1
A84: Pasivo Corriente | D84: =D18/D$16 -> 0.62471465 | E84: =E18/E$16 -> 0.47612224 | F84: =F18/F$16 -> 0.53945432 | G84: =G18/G$16 -> 0.37455062 | H84: =H18/H$16 -> 0.40630325 | J84: =J18/J$16 -> 0.1759968 | K84: =K18/K$16 -> 0.26936654 | L84: =L18/L$16 -> 0.21118822 | M84: =M18/M$16 -> 0.22172805 | N84: =N18/N$16 -> 0.34871391 | P84: =P18/P$16 -> 0.16124294 | Q84: =Q18/Q$16 -> 0.17790108 | R84: =R18/R$16 -> 0.22176869 | S84: =S18/S$16 -> 0.2348068 | T84: =T18/T$16 -> 0.29992188 | V84: =V18/V$16 -> 0.65231555 | W84: =W18/W$16 -> 0.24114196 | X84: =X18/X$16 -> 0.56147724 | Y84: =Y18/Y$16 -> 0.3760215 | AB84: =AB18/AB$16 -> 0.27851798 | AC84: =AC18/AC$16 -> 0.26504487 | AD84: =AD18/AD$16 -> 0.18378118 | AF84: =AF18/AF$16 -> 0 | AG84: =AG18/AG$16 -> 0 | AH84: =AH18/AH$16 -> 0 | AJ84: =AJ18/AJ$16 -> 0.6 | AK84: =AK18/AK$16 -> 0.78901492 | AM84: =AM18/AM$16 -> 0.52075165 | AN84: =AN18/AN$16 -> 0.47107125 | AO84: =AO18/AO$16 -> 0.4979733 | AQ84: =AQ18/AQ$16 -> 0.12306388 | AR84: =AR18/AR$16 -> 0.060001916 | AS84: =AS18/AS$16 -> 0.007884355 | AU84: =AU18/AU$16 -> 0.076313241 | AV84: =AV18/AV$16 -> 0.12482133 | AW84: =AW18/AW$16 -> 0.12122499 | AY84: =AY18/AY$16 -> 0.072315391 | AZ84: =AZ18/AZ$16 -> 0.18677675 | BA84: =BA18/BA$16 -> 0.31735551 | BB84: =BB18/BB$16 -> 0.31393764 | BD84: =BD18/BD$16 -> 0.1457946 | BE84: =BE18/BE$16 -> 0.15557867 | BF84: =BF18/BF$16 -> 0.17118881 | BG84: =BG18/BG$16 -> 0.28297584 | BI84: =BI18/BI$16 -> 0.65563057 | BJ84: =BJ18/BJ$16 -> 0.82157822 | BK84: =BK18/BK$16 -> 0.85052333 | BM84: =BM18/BM$16 -> 0.0592033 | BN84: =BN18/BN$16 -> 0.056723033 | BO84: =BO18/BO$16 -> 0.056192762 | BQ84: =BQ18/BQ$16 -> 0.83206377 | BR84: =BR18/BR$16 -> 0.17984448 | BT84: =BT18/BT$16 -> 0.4049408 | BU84: =BU18/BU$16 -> 0.75245192 | BV84: =BV18/BV$16 -> 0.17409055
A85: Pasivo No Corriente | D85: =D19/D$16 -> 0.15591503 | E85: =E19/E$16 -> 0.25339758 | F85: =F19/F$16 -> 0.14240617 | G85: =G19/G$16 -> 0.2737163 | H85: =H19/H$16 -> 0.21281272 | J85: =J19/J$16 -> 0.33696698 | K85: =K19/K$16 -> 0.25804522 | L85: =L19/L$16 -> 0.31611871 | M85: =M19/M$16 -> 0.32899999 | N85: =N19/N$16 -> 0.24820914 | P85: =P19/P$16 -> 0.21159278 | Q85: =Q19/Q$16 -> 0.24619096 | R85: =R19/R$16 -> 0.2016964 | S85: =S19/S$16 -> 0.20438765 | T85: =T19/T$16 -> 0.19287707 | V85: =V19/V$16 -> 0.001245709 | W85: =W19/W$16 -> 0.013139536 | X85: =X19/X$16 -> 0.0044145297 | Y85: =Y19/Y$16 -> 0.26990623 | AB85: =AB19/AB$16 -> 0.25509715 | AC85: =AC19/AC$16 -> 0.25295582 | AD85: =AD19/AD$16 -> 0.30674953 | AF85: =AF19/AF$16 -> 0.00032575064 | AG85: =AG19/AG$16 -> 0 | AH85: =AH19/AH$16 -> 0 | AJ85: =AJ19/AJ$16 -> 0 | AK85: =AK19/AK$16 -> 0 | AM85: =AM19/AM$16 -> 0.10321038 | AN85: =AN19/AN$16 -> 0.16895926 | AO85: =AO19/AO$16 -> 0.1279352 | AQ85: =AQ19/AQ$16 -> 0.41085324 | AR85: =AR19/AR$16 -> 0.55471079 | AS85: =AS19/AS$16 -> 0.57410952 | AU85: =AU19/AU$16 -> 0.66859263 | AV85: =AV19/AV$16 -> 0.5971189 | AW85: =AW19/AW$16 -> 0.59829943 | AY85: =AY19/AY$16 -> 0.3642776 | AZ85: =AZ19/AZ$16 -> 0.5238644 | BA85: =BA19/BA$16 -> 0.37015351 | BB85: =BB19/BB$16 -> 0.30244149 | BD85: =BD19/BD$16 -> 0.46484708 | BE85: =BE19/BE$16 -> 0.4688329 | BF85: =BF19/BF$16 -> 0.47621932 | BG85: =BG19/BG$16 -> 0.46994209 | BI85: =BI19/BI$16 -> 0.0086117387 | BJ85: =BJ19/BJ$16 -> 0.00058479824 | BK85: =BK19/BK$16 -> 0.00043676046 | BM85: =BM19/BM$16 -> 0.093694224 | BN85: =BN19/BN$16 -> 0.049532126 | BO85: =BO19/BO$16 -> 0.15207305 | BQ85: =BQ19/BQ$16 -> 0 | BR85: =BR19/BR$16 -> 0.68208176 | BT85: =BT19/BT$16 -> 0 | BU85: =BU19/BU$16 -> 0.0087238367 | BV85: =BV19/BV$16 -> 0.55345587
A86: Total Pasivo | D86: =D20/D$16 -> 0.78062968 | E86: =E20/E$16 -> 0.72951982 | F86: =F20/F$16 -> 0.68186049 | G86: =G20/G$16 -> 0.64826692 | H86: =H20/H$16 -> 0.61911597 | J86: =J20/J$16 -> 0.51296378 | K86: =K20/K$16 -> 0.52741176 | L86: =L20/L$16 -> 0.52730694 | M86: =M20/M$16 -> 0.55072804 | N86: =N20/N$16 -> 0.59692305 | P86: =P20/P$16 -> 0.37283572 | Q86: =Q20/Q$16 -> 0.42409204 | R86: =R20/R$16 -> 0.42346509 | S86: =S20/S$16 -> 0.43919445 | T86: =T20/T$16 -> 0.49279894 | V86: =V20/V$16 -> 0.65356126 | W86: =W20/W$16 -> 0.2542815 | X86: =X20/X$16 -> 0.56589177 | Y86: =Y20/Y$16 -> 0.64592773 | AB86: =AB20/AB$16 -> 0.53361513 | AC86: =AC20/AC$16 -> 0.51800069 | AD86: =AD20/AD$16 -> 0.49053071 | AF86: =AF20/AF$16 -> 0.00032575064 | AG86: =AG20/AG$16 -> 0 | AH86: =AH20/AH$16 -> 0 | AJ86: =AJ20/AJ$16 -> 0.6 | AK86: =AK20/AK$16 -> 0.78901492 | AM86: =AM20/AM$16 -> 0.62396202 | AN86: =AN20/AN$16 -> 0.64003051 | AO86: =AO20/AO$16 -> 0.62590851 | AQ86: =AQ20/AQ$16 -> 0.53391712 | AR86: =AR20/AR$16 -> 0.6147127 | AS86: =AS20/AS$16 -> 0.58199387 | AU86: =AU20/AU$16 -> 0.74490587 | AV86: =AV20/AV$16 -> 0.72194023 | AW86: =AW20/AW$16 -> 0.71952442 | AY86: =AY20/AY$16 -> 0.43659299 | AZ86: =AZ20/AZ$16 -> 0.71064115 | BA86: =BA20/BA$16 -> 0.68750902 | BB86: =BB20/BB$16 -> 0.61637913 | BD86: =BD20/BD$16 -> 0.61064169 | BE86: =BE20/BE$16 -> 0.62441157 | BF86: =BF20/BF$16 -> 0.64740813 | BG86: =BG20/BG$16 -> 0.75291793 | BI86: =BI20/BI$16 -> 0.66424231 | BJ86: =BJ20/BJ$16 -> 0.82216302 | BK86: =BK20/BK$16 -> 0.85096009 | BM86: =BM20/BM$16 -> 0.15289752 | BN86: =BN20/BN$16 -> 0.10625516 | BO86: =BO20/BO$16 -> 0.20826581 | BQ86: =BQ20/BQ$16 -> 0.83206377 | BR86: =BR20/BR$16 -> 0.86192624 | BT86: =BT20/BT$16 -> 0.4049408 | BU86: =BU20/BU$16 -> 0.76117576 | BV86: =BV20/BV$16 -> 0.72754641
A88: Capital | D88: =D22/D$16 -> 0 | E88: =E22/E$16 -> 0 | F88: =F22/F$16 -> 0 | G88: =G22/G$16 -> 0 | H88: =H22/H$16 -> 0 | J88: =J22/J$16 -> 0.12458967 | K88: =K22/K$16 -> 0.11538546 | L88: =L22/L$16 -> 0.10343309 | M88: =M22/M$16 -> 0.091926095 | N88: =N22/N$16 -> 0.090586154 | P88: =P22/P$16 -> 0.59119033 | Q88: =Q22/Q$16 -> 0.53616777 | R88: =R22/R$16 -> 0.53125464 | S88: =S22/S$16 -> 0.48684033 | T88: =T22/T$16 -> 0.44764886 | V88: =V22/V$16 -> 0.34386783 | W88: =W22/W$16 -> 0.84656795 | X88: =X22/X$16 -> 0.47489167 | Y88: =Y22/Y$16 -> 0.36649866 | AB88: =AB22/AB$16 -> 0.26029387 | AC88: =AC22/AC$16 -> 0.26259246 | AD88: =AD22/AD$16 -> 0.25831978 | AF88: =AF22/AF$16 -> 0.1105221 | AG88: =AG22/AG$16 -> 0.11065058 | AH88: =AH22/AH$16 -> 0.11063955 | AJ88: =AJ22/AJ$16 -> 0.4 | AK88: =AK22/AK$16 -> 0.026979234 | AM88: =AM22/AM$16 -> 0.21291988 | AN88: =AN22/AN$16 -> 0.17964269 | AO88: =AO22/AO$16 -> 0.18942587 | AQ88: =AQ22/AQ$16 -> 0.081206701 | AR88: =AR22/AR$16 -> 0.063048037 | AS88: =AS22/AS$16 -> 0.065539927 | AU88: =AU22/AU$16 -> 0.19781167 | AV88: =AV22/AV$16 -> 0.18522308 | AW88: =AW22/AW$16 -> 0.19162221 | AY88: =AY22/AY$16 -> 0.32261788 | AZ88: =AZ22/AZ$16 -> 0.19053126 | BA88: =BA22/BA$16 -> 0.12472738 | BB88: =BB22/BB$16 -> 0.22034249 | BD88: =BD22/BD$16 -> 0.055534113 | BE88: =BE22/BE$16 -> 0.056521372 | BF88: =BF22/BF$16 -> 0.056721861 | BG88: =BG22/BG$16 -> 0.055206008 | BI88: =BI22/BI$16 -> 1.1205714 | BJ88: =BJ22/BJ$16 -> 0.83858688 | BK88: =BK22/BK$16 -> 0.12526084 | BM88: =BM22/BM$16 -> 0.22517822 | BN88: =BN22/BN$16 -> 0.19579826 | BO88: =BO22/BO$16 -> 0.13769119 | BQ88: =BQ22/BQ$16 -> 0.012165436 | BR88: =BR22/BR$16 -> 0.0019361611 | BT88: =BT22/BT$16 -> 0.00086943827 | BU88: =BU22/BU$16 -> 0.00053704967 | BV88: =BV22/BV$16 -> 0.00038918274
A89: Otros | D89: =D23/D$16 -> 0 | E89: =E23/E$16 -> 0 | F89: =F23/F$16 -> 0 | G89: =G23/G$16 -> 0 | H89: =H23/H$16 -> 0 | J89: =J23/J$16 -> 0 | K89: =K23/K$16 -> 0 | L89: =L23/L$16 -> -0.0061166936 | M89: =M23/M$16 -> 0.017962503 | N89: =N23/N$16 -> 0 | P89: =P23/P$16 -> 0.032169362 | Q89: =Q23/Q$16 -> 0.031390495 | R89: =R23/R$16 -> 0.0051909465 | S89: =S23/S$16 -> 0.0036001173 | T89: =T23/T$16 -> 0.010787356 | V89: =V23/V$16 -> 0 | W89: =W23/W$16 -> 0 | X89: =X23/X$16 -> 0 | Y89: =Y23/Y$16 -> 0 | AB89: =AB23/AB$16 -> 0 | AC89: =AC23/AC$16 -> 0 | AD89: =AD23/AD$16 -> 0.06821684 | AF89: =AF23/AF$16 -> 0.82223942 | AG89: =AG23/AG$16 -> 0.82205289 | AH89: =AH23/AH$16 -> 0.82195543 | AJ89: =AJ23/AJ$16 -> 0 | AK89: =AK23/AK$16 -> 0.16517898 | AM89: =AM23/AM$16 -> 0 | AN89: =AN23/AN$16 -> 0 | AO89: =AO23/AO$16 -> 0 | AQ89: =AQ23/AQ$16 -> 0.16217002 | AR89: =AR23/AR$16 -> 0.12590712 | AS89: =AS23/AS$16 -> 0.13088343 | AU89: =AU23/AU$16 -> 0.015801208 | AV89: =AV23/AV$16 -> 0.014795632 | AW89: =AW23/AW$16 -> 0.023893919 | AY89: =AY23/AY$16 -> 0.20614444 | AZ89: =AZ23/AZ$16 -> 0.062234165 | BA89: =BA23/BA$16 -> 0.11872805 | BB89: =BB23/BB$16 -> 0.036326086 | BD89: =BD23/BD$16 -> 0.34279582 | BE89: =BE23/BE$16 -> 0.32196418 | BF89: =BF23/BF$16 -> 0.27139282 | BG89: =BG23/BG$16 -> 0.16759719 | BI89: =BI23/BI$16 -> 0.0077321347 | BJ89: =BJ23/BJ$16 -> 0 | BK89: =BK23/BK$16 -> 0 | BM89: =BM23/BM$16 -> 0.00020693915 | BN89: =BN23/BN$16 -> 0.00017993892 | BO89: =BO23/BO$16 -> 0.00012653843 | BQ89: =BQ23/BQ$16 -> 0 | BR89: =BR23/BR$16 -> 0 | BT89: =BT23/BT$16 -> 0 | BU89: =BU23/BU$16 -> 0 | BV89: =BV23/BV$16 -> 0
A90: Reserva Legal | D90: =D24/D$16 -> 0 | E90: =E24/E$16 -> 0 | F90: =F24/F$16 -> 0 | G90: =G24/G$16 -> 0 | H90: =H24/H$16 -> 0 | J90: =J24/J$16 -> 0.030676313 | K90: =K24/K$16 -> 0.029752683 | L90: =L24/L$16 -> 0.027941494 | M90: =M24/M$16 -> 0.025403818 | N90: =N24/N$16 -> 0.025033524 | P90: =P24/P$16 -> 0.016895364 | Q90: =Q24/Q$16 -> 0.016018614 | R90: =R24/R$16 -> 0.016908549 | S90: =S24/S$16 -> 0.01583338 | T90: =T24/T$16 -> 0.015830641 | V90: =V24/V$16 -> 0.0011486002 | W90: =W24/W$16 -> 0.002827738 | X90: =X24/X$16 -> 0.0026544242 | Y90: =Y24/Y$16 -> 0.0020485575 | AB90: =AB24/AB$16 -> 0 | AC90: =AC24/AC$16 -> 0 | AD90: =AD24/AD$16 -> 0.0087108496 | AF90: =AF24/AF$16 -> 0.0024439686 | AG90: =AG24/AG$16 -> 0.0024468097 | AH90: =AH24/AH$16 -> 0.0024465658 | AJ90: =AJ24/AJ$16 -> 0 | AK90: =AK24/AK$16 -> 0 | AM90: =AM24/AM$16 -> 0.0038601806 | AN90: =AN24/AN$16 -> 0.0058800445 | AO90: =AO24/AO$16 -> 0.0062002665 | AQ90: =AQ24/AQ$16 -> 0.019245469 | AR90: =AR24/AR$16 -> 0.017687878 | AS90: =AS24/AS$16 -> 0.018386968 | AU90: =AU24/AU$16 -> 0.0038373794 | AV90: =AV24/AV$16 -> 0.0055743392 | AW90: =AW24/AW$16 -> 0.0087683426 | AY90: =AY24/AY$16 -> 0.0019811022 | AZ90: =AZ24/AZ$16 -> 0.001976647 | BA90: =BA24/BA$16 -> 0.00076591443 | BB90: =BB24/BB$16 -> 0.0016384718 | BD90: =BD24/BD$16 -> 0.009066031 | BE90: =BE24/BE$16 -> 0.0096424935 | BF90: =BF24/BF$16 -> 0.010420029 | BG90: =BG24/BG$16 -> 0.011387309 | BI90: =BI24/BI$16 -> 0 | BJ90: =BJ24/BJ$16 -> 0 | BK90: =BK24/BK$16 -> 0 | BM90: =BM24/BM$16 -> 0.057764989 | BN90: =BN24/BN$16 -> 0.068309678 | BO90: =BO24/BO$16 -> 0.057287936 | BQ90: =BQ24/BQ$16 -> 0 | BR90: =BR24/BR$16 -> 0 | BT90: =BT24/BT$16 -> 0.010962892 | BU90: =BU24/BU$16 -> 0.010099423 | BV90: =BV24/BV$16 -> 0.0090843105
A91: Utilidades Retenidas | D91: =D25/D$16 -> 0.21937032 | E91: =E25/E$16 -> 0.27047703 | F91: =F25/F$16 -> 0.31813667 | G91: =G25/G$16 -> 0.35173063 | H91: =H25/H$16 -> 0.38088207 | J91: =J25/J$16 -> 0.33176776 | K91: =K25/K$16 -> 0.32745009 | L91: =L25/L$16 -> 0.34743517 | M91: =M25/M$16 -> 0.31397954 | N91: =N25/N$16 -> 0.28745727 | P91: =P25/P$16 -> -0.013095289 | Q91: =Q25/Q$16 -> -0.0076689203 | R91: =R25/R$16 -> 0.0014909216 | S91: =S25/S$16 -> 0.033160676 | T91: =T25/T$16 -> -0.015822072 | V91: =V25/V$16 -> 0.0014223054 | W91: =W25/W$16 -> -0.10369915 | X91: =X25/X$16 -> -0.043437867 | Y91: =Y25/Y$16 -> -0.014474761 | AB91: =AB25/AB$16 -> 0.206091 | AC91: =AC25/AC$16 -> 0.21940685 | AD91: =AD25/AD$16 -> 0.17422182 | AF91: =AF25/AF$16 -> 0.064468759 | AG91: =AG25/AG$16 -> 0.064849721 | AH91: =AH25/AH$16 -> 0.064958456 | AJ91: =AJ25/AJ$16 -> 0 | AK91: =AK25/AK$16 -> 0.018826858 | AM91: =AM25/AM$16 -> 0.15925792 | AN91: =AN25/AN$16 -> 0.17444675 | AO91: =AO25/AO$16 -> 0.17846535 | AQ91: =AQ25/AQ$16 -> 0.20346069 | AR91: =AR25/AR$16 -> 0.17864426 | AS91: =AS25/AS$16 -> 0.2031958 | AU91: =AU25/AU$16 -> 0.03764388 | AV91: =AV25/AV$16 -> 0.072466718 | AW91: =AW25/AW$16 -> 0.0561911 | AY91: =AY25/AY$16 -> 0.03266359 | AZ91: =AZ25/AZ$16 -> 0.034616774 | BA91: =BA25/BA$16 -> 0.068269638 | BB91: =BB25/BB$16 -> 0.12531382 | BD91: =BD25/BD$16 -> -0.018037649 | BE91: =BE25/BE$16 -> -0.012539622 | BF91: =BF25/BF$16 -> 0.014057162 | BG91: =BG25/BG$16 -> 0.012891567 | BI91: =BI25/BI$16 -> -0.79254588 | BJ91: =BJ25/BJ$16 -> -0.6607499 | BK91: =BK25/BK$16 -> 0.023779071 | BM91: =BM25/BM$16 -> 0.56395233 | BN91: =BN25/BN$16 -> 0.62945696 | BO91: =BO25/BO$16 -> 0.59662852 | BQ91: =BQ25/BQ$16 -> 0.15577079 | BR91: =BR25/BR$16 -> 0.1361376 | BT91: =BT25/BT$16 -> 0.58322687 | BU91: =BU25/BU$16 -> 0.22818777 | BV91: =BV25/BV$16 -> 0.26298008
A92: Total Patrimonio | D92: =D26/D$16 -> 0.21937338 | E92: =E26/E$16 -> 0.27048018 | F92: =F26/F$16 -> 0.31813951 | G92: =G26/G$16 -> 0.35173308 | H92: =H26/H$16 -> 0.38088403 | J92: =J26/J$16 -> 0.48703374 | K92: =K26/K$16 -> 0.47258824 | L92: =L26/L$16 -> 0.47269306 | M92: =M26/M$16 -> 0.44927196 | N92: =N26/N$16 -> 0.40307695 | P92: =P26/P$16 -> 0.62715977 | Q92: =Q26/Q$16 -> 0.57590796 | R92: =R26/R$16 -> 0.57653491 | S92: =S26/S$16 -> 0.56080555 | T92: =T26/T$16 -> 0.50720106 | V92: =V26/V$16 -> 0.34643874 | W92: =W26/W$16 -> 0.74569654 | X92: =X26/X$16 -> 0.43410823 | Y92: =Y26/Y$16 -> 0.35407245 | AB92: =AB26/AB$16 -> 0.46638487 | AC92: =AC26/AC$16 -> 0.48199931 | AD92: =AD26/AD$16 -> 0.50946929 | AF92: =AF26/AF$16 -> 0.99967425 | AG92: =AG26/AG$16 -> 1 | AH92: =AH26/AH$16 -> 1 | AJ92: =AJ26/AJ$16 -> 0.4 | AK92: =AK26/AK$16 -> 0.21098508 | AM92: =AM26/AM$16 -> 0.37603798 | AN92: =AN26/AN$16 -> 0.35996949 | AO92: =AO26/AO$16 -> 0.37409149 | AQ92: =AQ26/AQ$16 -> 0.46608288 | AR92: =AR26/AR$16 -> 0.3852873 | AS92: =AS26/AS$16 -> 0.41800613 | AU92: =AU26/AU$16 -> 0.25509413 | AV92: =AV26/AV$16 -> 0.27805977 | AW92: =AW26/AW$16 -> 0.28047558 | AY92: =AY26/AY$16 -> 0.56340701 | AZ92: =AZ26/AZ$16 -> 0.28935885 | BA92: =BA26/BA$16 -> 0.31249098 | BB92: =BB26/BB$16 -> 0.38362087 | BD92: =BD26/BD$16 -> 0.38935831 | BE92: =BE26/BE$16 -> 0.37558843 | BF92: =BF26/BF$16 -> 0.35259187 | BG92: =BG26/BG$16 -> 0.24708207 | BI92: =BI26/BI$16 -> 0.33575769 | BJ92: =BJ26/BJ$16 -> 0.17783698 | BK92: =BK26/BK$16 -> 0.14903991 | BM92: =BM26/BM$16 -> 0.84710248 | BN92: =BN26/BN$16 -> 0.89374484 | BO92: =BO26/BO$16 -> 0.79173419 | BQ92: =BQ26/BQ$16 -> 0.16793623 | BR92: =BR26/BR$16 -> 0.13807376 | BT92: =BT26/BT$16 -> 0.5950592 | BU92: =BU26/BU$16 -> 0.23882424 | BV92: =BV26/BV$16 -> 0.27245357
A94: EBITDA | D94: =D37/D$16 -> 0.22081187 | E94: =E37/E$16 -> 0.045459291 | F94: =F37/F$16 -> 0.074168262 | G94: =G37/G$16 -> 0.076296506 | H94: =H37/H$16 -> 0.03710795 | J94: =J37/J$16 -> 0.060056612 | K94: =K37/K$16 -> 0.04939415 | L94: =L37/L$16 -> 0.035575751 | M94: =M37/M$16 -> 0.025642117 | N94: =N37/N$16 -> 0.03449865 | P94: =P37/P$16 -> -0.011427862 | Q94: =Q37/Q$16 -> 0.025152903 | R94: =R37/R$16 -> 0.024794175 | S94: =S37/S$16 -> 0.033271847 | T94: =T37/T$16 -> 0.021088278 | V94: =V37/V$16 -> -0.00057081931 | W94: =W37/W$16 -> -0.10720072 | X94: =X37/X$16 -> 0.021363087 | Y94: =Y37/Y$16 -> 0.019048506 | AB94: =AB37/AB$16 -> 0.051033319 | AC94: =AC37/AC$16 -> 0.075123601 | AD94: =AD37/AD$16 -> 0.10681373 | AF94: =AF37/AF$16 -> -1.5473094e-05 | AG94: =AG37/AG$16 -> 0.00030602023 | AH94: =AH37/AH$16 -> 0.00010244337 | AJ94: =AJ37/AJ$16 -> -33.694818 | AK94: =AK37/AK$16 -> 0.067841845 | AM94: =AM37/AM$16 -> 0.10789952 | AN94: =AN37/AN$16 -> 0.10812796 | AO94: =AO37/AO$16 -> 0.046668468 | AQ94: =AQ37/AQ$16 -> 0.17622688 | AR94: =AR37/AR$16 -> 0.10317927 | AS94: =AS37/AS$16 -> 0.031776192 | AU94: =AU37/AU$16 -> 0.088125848 | AV94: =AV37/AV$16 -> 0.11894049 | AW94: =AW37/AW$16 -> 0.14466456 | AY94: =AY37/AY$16 -> 0.014695955 | AZ94: =AZ37/AZ$16 -> 0.025682521 | BA94: =BA37/BA$16 -> 0.0546546 | BB94: =BB37/BB$16 -> 0.073655005 | BD94: =BD37/BD$16 -> 0.042193358 | BE94: =BE37/BE$16 -> 0.047917867 | BF94: =BF37/BF$16 -> 0.065662319 | BG94: =BG37/BG$16 -> 0.053543911 | BI94: =BI37/BI$16 -> 0.0066916289 | BJ94: =BJ37/BJ$16 -> -0.041709991 | BK94: =BK37/BK$16 -> 0.049982753 | BM94: =BM37/BM$16 -> 0.17061331 | BN94: =BN37/BN$16 -> 0.20664609 | BO94: =BO37/BO$16 -> 0.21763478 | BQ94: =BQ37/BQ$16 -> 0.17309965 | BR94: =BR37/BR$16 -> 0.10573199 | BT94: =BT37/BT$16 -> 0.083419993 | BU94: =BU37/BU$16 -> 0.19962933 | BV94: =BV37/BV$16 -> 0.23193371
A97: CRECIMIENTOS %
A99: Ventas | E99: =if(D10=0,"",E10/D10-1) -> -0.014683192 | F99: =if(E10=0,"",F10/E10-1) -> 0.26351927 | G99: =if(F10=0,"",G10/F10-1) -> 0.099887075 | H99: =if(G10=0,"",H10/G10-1) -> -0.26313757 | K99: =if(J10=0,"",K10/J10-1) -> -0.021981474 | L99: =if(K10=0,"",L10/K10-1) -> 0.093713993 | M99: =if(L10=0,"",M10/L10-1) -> 0.16287436 | N99: =if(M10=0,"",N10/M10-1) -> -0.25648732 | Q99: =if(P10=0,"",Q10/P10-1) -> 15.317158 | R99: =if(Q10=0,"",R10/Q10-1) -> 0.47388517 | S99: =if(R10=0,"",S10/R10-1) -> 0.055515009 | T99: =if(S10=0,"",T10/S10-1) -> -0.30836004 | V99: =if(U10=0,"",V10/U10-1) | W99: =if(V10=0,"",W10/V10-1) -> 0.65183776 | X99: =if(W10=0,"",X10/W10-1) -> 0.27312921 | Y99: =if(X10=0,"",Y10/X10-1) -> -0.21155038 | AB99: =if(AA10=0,"",AB10/AA10-1) | AC99: =if(AB10=0,"",AC10/AB10-1) -> 0.32625776 | AD99: =if(AC10=0,"",AD10/AC10-1) -> 0.044512999 | AF99: =if(AE10=0,"",AF10/AE10-1) | AG99: =if(AF10=0,"",AG10/AF10-1) | AH99: =if(AG10=0,"",AH10/AG10-1) -> -0.51274754 | AJ99: =if(AI10=0,"",AJ10/AI10-1) | AM99: =if(AL10=0,"",AM10/AL10-1) | AN99: =if(AM10=0,"",AN10/AM10-1) -> 0.10998813 | AO99: =if(AN10=0,"",AO10/AN10-1) -> -0.4930565 | AQ99: =if(AP10=0,"",AQ10/AP10-1) | AR99: =if(AQ10=0,"",AR10/AQ10-1) -> -0.16290603 | AS99: =if(AR10=0,"",AS10/AR10-1) -> -0.71419511 | AU99: =if(AT10=0,"",AU10/AT10-1) | AV99: =if(AU10=0,"",AV10/AU10-1) -> 0.6699303 | AW99: =if(AV10=0,"",AW10/AV10-1) -> 0.29114551 | AY99: =if(AX10=0,"",AY10/AX10-1) | AZ99: =if(AY10=0,"",AZ10/AY10-1) -> -0.60731184 | BA99: =if(AZ10=0,"",BA10/AZ10-1) -> 4.1921338 | BB99: =if(BA10=0,"",BB10/BA10-1) -> 1.2251217 | BD99: =if(BC10=0,"",BD10/BC10-1) | BE99: =if(BD10=0,"",BE10/BD10-1) -> 0.22332825 | BF99: =if(BE10=0,"",BF10/BE10-1) -> 0.039864852 | BG99: =if(BF10=0,"",BG10/BF10-1) -> -0.12384191 | BI99: =if(BH10=0,"",BI10/BH10-1) | BJ99: =if(BI10=0,"",BJ10/BI10-1) -> 0.37032508 | BK99: =if(BJ10=0,"",BK10/BJ10-1) -> 0.23661006 | BM99: =if(BL10=0,"",BM10/BL10-1) | BN99: =if(BM10=0,"",BN10/BM10-1) -> 0.27679282 | BO99: =if(BN10=0,"",BO10/BN10-1) -> 0.19778174 | BQ99: =if(BP10=0,"",BQ10/BP10-1) | BR99: =if(BQ10=0,"",BR10/BQ10-1) -> 0.58620664 | BT99: =if(BS10=0,"",BT10/BS10-1) | BU99: =if(BT10=0,"",BU10/BT10-1) -> 0.55845628 | BV99: =if(BU10=0,"",BV10/BU10-1) -> 0.16549705
A100: Utilidad Neta | E100: =if(D11=0,"",E11/D11-1) -> -0.79929634 | F100: =if(E11=0,"",F11/E11-1) -> 0.80880706 | G100: =if(F11=0,"",G11/F11-1) -> 0.18818082 | H100: =if(G11=0,"",H11/G11-1) -> -0.39055622 | K100: =if(J11=0,"",K11/J11-1) -> 0.1018266 | L100: =if(K11=0,"",L11/K11-1) -> -0.24708275 | M100: =if(L11=0,"",M11/L11-1) -> -0.55250484 | N100: =if(M11=0,"",N11/M11-1) -> -0.70173699 | Q100: =if(P11=0,"",Q11/P11-1) -> -1.4258865 | R100: =if(Q11=0,"",R11/Q11-1) -> 1.0268755 | S100: =if(R11=0,"",S11/R11-1) -> 0.76757557 | T100: =if(S11=0,"",T11/S11-1) -> -1.6203608 | V100: =if(U11=0,"",V11/U11-1) | W100: =if(V11=0,"",W11/V11-1) -> 75.283179 | X100: =if(W11=0,"",X11/W11-1) -> -1.2627647 | Y100: =if(X11=0,"",Y11/X11-1) -> 0.56201618 | AB100: =if(AA11=0,"",AB11/AA11-1) | AC100: =if(AB11=0,"",AC11/AB11-1) -> -0.23531896 | AD100: =if(AC11=0,"",AD11/AC11-1) -> 2.345799 | AF100: =if(AE11=0,"",AF11/AE11-1) | AH100: =if(AG11=0,"",AH11/AG11-1) -> -0.66520649 | AJ100: =if(AI11=0,"",AJ11/AI11-1) | AM100: =if(AL11=0,"",AM11/AL11-1) | AN100: =if(AM11=0,"",AN11/AM11-1) -> 0.042222647 | AO100: =if(AN11=0,"",AO11/AN11-1) -> -0.547502 | AQ100: =if(AP11=0,"",AQ11/AP11-1) | AR100: =if(AQ11=0,"",AR11/AQ11-1) -> -0.41290087 | AS100: =if(AR11=0,"",AS11/AR11-1) -> -0.67749319 | AU100: =if(AT11=0,"",AU11/AT11-1) | AV100: =if(AU11=0,"",AV11/AU11-1) -> 0.83784033 | AW100: =if(AV11=0,"",AW11/AV11-1) -> 0.43818402 | AY100: =if(AX11=0,"",AY11/AX11-1) | AZ100: =if(AY11=0,"",AZ11/AY11-1) -> 28.575677 | BA100: =if(AZ11=0,"",BA11/AZ11-1) -> 3.5458089 | BB100: =if(BA11=0,"",BB11/BA11-1) -> 0.81598873 | BD100: =if(BC11=0,"",BD11/BC11-1) | BE100: =if(BD11=0,"",BE11/BD11-1) -> 1.4850522 | BF100: =if(BE11=0,"",BF11/BE11-1) -> 1.5532146 | BG100: =if(BF11=0,"",BG11/BF11-1) -> -0.92837369 | BI100: =if(BH11=0,"",BI11/BH11-1) | BJ100: =if(BI11=0,"",BJ11/BI11-1) -> 2.4357829 | BK100: =if(BJ11=0,"",BK11/BJ11-1) -> -1.3210863 | BM100: =if(BL11=0,"",BM11/BL11-1) | BN100: =if(BM11=0,"",BN11/BM11-1) -> 0.39295059 | BO100: =if(BN11=0,"",BO11/BN11-1) -> 0.49762739 | BQ100: =if(BP11=0,"",BQ11/BP11-1) | BR100: =if(BQ11=0,"",BR11/BQ11-1) -> 3.1830223 | BT100: =if(BS11=0,"",BT11/BS11-1) | BU100: =if(BT11=0,"",BU11/BT11-1) -> 4.8562641 | BV100: =if(BU11=0,"",BV11/BU11-1) -> -0.046175503
E101: =if(D12=0,"",E12/D12-1) | F101: =if(E12=0,"",F12/E12-1) | G101: =if(F12=0,"",G12/F12-1) | H101: =if(G12=0,"",H12/G12-1) | K101: =if(J12=0,"",K12/J12-1) | L101: =if(K12=0,"",L12/K12-1) | M101: =if(L12=0,"",M12/L12-1) | N101: =if(M12=0,"",N12/M12-1) | Q101: =if(P12=0,"",Q12/P12-1) | R101: =if(Q12=0,"",R12/Q12-1) | S101: =if(R12=0,"",S12/R12-1) | T101: =if(S12=0,"",T12/S12-1) | V101: =if(U12=0,"",V12/U12-1) | W101: =if(V12=0,"",W12/V12-1) | X101: =if(W12=0,"",X12/W12-1) | Y101: =if(X12=0,"",Y12/X12-1) | AB101: =if(AA12=0,"",AB12/AA12-1) | AC101: =if(AB12=0,"",AC12/AB12-1) | AD101: =if(AC12=0,"",AD12/AC12-1) | AF101: =if(AE12=0,"",AF12/AE12-1) | AG101: =if(AF12=0,"",AG12/AF12-1) | AH101: =if(AG12=0,"",AH12/AG12-1) | AJ101: =if(AI12=0,"",AJ12/AI12-1) | AM101: =if(AL12=0,"",AM12/AL12-1) | AN101: =if(AM12=0,"",AN12/AM12-1) | AO101: =if(AN12=0,"",AO12/AN12-1) | AQ101: =if(AP12=0,"",AQ12/AP12-1) | AR101: =if(AQ12=0,"",AR12/AQ12-1) | AS101: =if(AR12=0,"",AS12/AR12-1) | AU101: =if(AT12=0,"",AU12/AT12-1) | AV101: =if(AU12=0,"",AV12/AU12-1) | AW101: =if(AV12=0,"",AW12/AV12-1) | AY101: =if(AX12=0,"",AY12/AX12-1) | AZ101: =if(AY12=0,"",AZ12/AY12-1) | BA101: =if(AZ12=0,"",BA12/AZ12-1) | BB101: =if(BA12=0,"",BB12/BA12-1) | BD101: =if(BC12=0,"",BD12/BC12-1) | BE101: =if(BD12=0,"",BE12/BD12-1) | BF101: =if(BE12=0,"",BF12/BE12-1) | BG101: =if(BF12=0,"",BG12/BF12-1) | BI101: =if(BH12=0,"",BI12/BH12-1) | BJ101: =if(BI12=0,"",BJ12/BI12-1) | BK101: =if(BJ12=0,"",BK12/BJ12-1) | BM101: =if(BL12=0,"",BM12/BL12-1) | BN101: =if(BM12=0,"",BN12/BM12-1) | BO101: =if(BN12=0,"",BO12/BN12-1) | BQ101: =if(BP12=0,"",BQ12/BP12-1) | BR101: =if(BQ12=0,"",BR12/BQ12-1) | BT101: =if(BS12=0,"",BT12/BS12-1) | BU101: =if(BT12=0,"",BU12/BT12-1) | BV101: =if(BU12=0,"",BV12/BU12-1)
A102: Activo Corriente | E102: =if(D13=0,"",E13/D13-1) -> -0.24697522 | F102: =if(E13=0,"",F13/E13-1) -> 0.68803482 | G102: =if(F13=0,"",G13/F13-1) -> 0.10751465 | H102: =if(G13=0,"",H13/G13-1) -> -0.041896334 | K102: =if(J13=0,"",K13/J13-1) -> 0.14310333 | L102: =if(K13=0,"",L13/K13-1) -> 0.17743285 | M102: =if(L13=0,"",M13/L13-1) -> 0.13567293 | N102: =if(M13=0,"",N13/M13-1) -> -0.021628711 | Q102: =if(P13=0,"",Q13/P13-1) -> -0.67880837 | R102: =if(Q13=0,"",R13/Q13-1) -> 0.37558636 | S102: =if(R13=0,"",S13/R13-1) -> 0.15949065 | T102: =if(S13=0,"",T13/S13-1) -> 0.10852577 | V102: =if(U13=0,"",V13/U13-1) | W102: =if(V13=0,"",W13/V13-1) -> 0.32038977 | X102: =if(W13=0,"",X13/W13-1) -> 0.8505821 | Y102: =if(X13=0,"",Y13/X13-1) -> -0.47385432 | AC102: =if(AB13=0,"",AC13/AB13-1) -> -0.14849137 | AD102: =if(AC13=0,"",AD13/AC13-1) -> 0.13043117 | AF102: =if(AE13=0,"",AF13/AE13-1) | AH102: =if(AG13=0,"",AH13/AG13-1) -> 0.00011165604 | AJ102: =if(AI13=0,"",AJ13/AI13-1) | AM102: =if(AL13=0,"",AM13/AL13-1) | AN102: =if(AM13=0,"",AN13/AM13-1) -> 0.26431056 | AO102: =if(AN13=0,"",AO13/AN13-1) -> -0.1048465 | AQ102: =if(AP13=0,"",AQ13/AP13-1) | AR102: =if(AQ13=0,"",AR13/AQ13-1) -> 0.29388489 | AS102: =if(AR13=0,"",AS13/AR13-1) -> -0.039724376 | AU102: =if(AT13=0,"",AU13/AT13-1) | AV102: =if(AU13=0,"",AV13/AU13-1) -> 0.012319159 | AW102: =if(AV13=0,"",AW13/AV13-1) -> -0.069666673 | AY102: =if(AX13=0,"",AY13/AX13-1) | AZ102: =if(AY13=0,"",AZ13/AY13-1) -> 0.80429156 | BA102: =if(AZ13=0,"",BA13/AZ13-1) -> 0.5288156 | BB102: =if(BA13=0,"",BB13/BA13-1) -> 0.19238325 | BD102: =if(BC13=0,"",BD13/BC13-1) | BE102: =if(BD13=0,"",BE13/BD13-1) -> 0.033306185 | BF102: =if(BE13=0,"",BF13/BE13-1) -> 0.004093622 | BG102: =if(BF13=0,"",BG13/BF13-1) -> 0.033215393 | BI102: =if(BH13=0,"",BI13/BH13-1) | BJ102: =if(BI13=0,"",BJ13/BI13-1) -> 0.33332436 | BK102: =if(BJ13=0,"",BK13/BJ13-1) -> 0.3222283 | BM102: =if(BL13=0,"",BM13/BL13-1) | BN102: =if(BM13=0,"",BN13/BM13-1) -> 0.17836604 | BO102: =if(BN13=0,"",BO13/BN13-1) -> 0.36543138 | BQ102: =if(BP13=0,"",BQ13/BP13-1) | BR102: =if(BQ13=0,"",BR13/BQ13-1) -> 5.2668236 | BT102: =if(BS13=0,"",BT13/BS13-1) | BU102: =if(BT13=0,"",BU13/BT13-1) -> 0.62243997 | BV102: =if(BU13=0,"",BV13/BU13-1) -> 0.37486249
A103: Activo No Corriente | E103: =if(D14=0,"",E14/D14-1) | F103: =if(E14=0,"",F14/E14-1) | G103: =if(F14=0,"",G14/F14-1) | H103: =if(G14=0,"",H14/G14-1) | K103: =if(J14=0,"",K14/J14-1) -> -0.10182006 | L103: =if(K14=0,"",L14/K14-1) -> 0.74584141 | M103: =if(L14=0,"",M14/L14-1) -> 0.20201184 | N103: =if(M14=0,"",N14/M14-1) -> -0.56745337 | Q103: =if(P14=0,"",Q14/P14-1) -> 0.013595576 | R103: =if(Q14=0,"",R14/Q14-1) -> -0.098305343 | S103: =if(R14=0,"",S14/R14-1) -> 0.20458446 | T103: =if(S14=0,"",T14/S14-1) -> 0.0229191 | V103: =if(U14=0,"",V14/U14-1) | W103: =if(V14=0,"",W14/V14-1) -> -0.9409704 | X103: =if(W14=0,"",X14/W14-1) -> 0.20566787 | Y103: =if(X14=0,"",Y14/X14-1) -> 0.58456134 | AC103: =if(AB14=0,"",AC14/AB14-1) -> -0.10831334 | AD103: =if(AC14=0,"",AD14/AC14-1) -> 0.029480608 | AF103: =if(AE14=0,"",AF14/AE14-1) | AH103: =if(AG14=0,"",AH14/AG14-1) -> 0 | AJ103: =if(AI14=0,"",AJ14/AI14-1) | AM103: =if(AL14=0,"",AM14/AL14-1) | AN103: =if(AM14=0,"",AN14/AM14-1) -> 0.13172391 | AO103: =if(AN14=0,"",AO14/AN14-1) -> 0.12321091 | AQ103: =if(AP14=0,"",AQ14/AP14-1) | AR103: =if(AQ14=0,"",AR14/AQ14-1) -> -0.035567385 | AS103: =if(AR14=0,"",AS14/AR14-1) -> 0.040269538 | AU103: =if(AT14=0,"",AU14/AT14-1) | AV103: =if(AU14=0,"",AV14/AU14-1) -> 0.43572377 | AW103: =if(AV14=0,"",AW14/AV14-1) -> 0.13113585 | AY103: =if(AX14=0,"",AY14/AX14-1) | AZ103: =if(AY14=0,"",AZ14/AY14-1) -> -0.60588292 | BA103: =if(AZ14=0,"",BA14/AZ14-1) -> 6.5218847 | BB103: =if(BA14=0,"",BB14/BA14-1) -> 1.0294388 | BD103: =if(BC14=0,"",BD14/BC14-1) | BE103: =if(BD14=0,"",BE14/BD14-1) -> -0.079644648 | BF103: =if(BE14=0,"",BF14/BE14-1) -> 0.0027991281 | BG103: =if(BF14=0,"",BG14/BF14-1) -> 0.04409804 | BI103: =if(BH14=0,"",BI14/BH14-1) | BJ103: =if(BI14=0,"",BJ14/BI14-1) -> 1.8126501 | BK103: =if(BJ14=0,"",BK14/BJ14-1) -> 2.152318 | BM103: =if(BL14=0,"",BM14/BL14-1) | BN103: =if(BM14=0,"",BN14/BM14-1) -> 0.06965777 | BO103: =if(BN14=0,"",BO14/BN14-1) -> 0.59898652 | BQ103: =if(BP14=0,"",BQ14/BP14-1) | BR103: =if(BQ14=0,"",BR14/BQ14-1) -> 7.2960228 | BT103: =if(BS14=0,"",BT14/BS14-1) | BU103: =if(BT14=0,"",BU14/BT14-1) -> 0.071078489 | BV103: =if(BU14=0,"",BV14/BU14-1) -> 1.5761183
A104: Activo Diferido | E104: =if(D15=0,"",E15/D15-1) -> 0.083374906 | F104: =if(E15=0,"",F15/E15-1) -> -0.088260005 | G104: =if(F15=0,"",G15/F15-1) -> 0.18494124 | H104: =if(G15=0,"",H15/G15-1) -> 0.42653343 | K104: =if(J15=0,"",K15/J15-1) -> 0.04970605 | L104: =if(K15=0,"",L15/K15-1) -> -0.18853863 | M104: =if(L15=0,"",M15/L15-1) -> 0.047100527 | N104: =if(M15=0,"",N15/M15-1) -> 0.56740473 | Q104: =if(P15=0,"",Q15/P15-1) -> 3.7301542 | R104: =if(Q15=0,"",R15/Q15-1) -> -0.086361948 | S104: =if(R15=0,"",S15/R15-1) -> 0.041368267 | T104: =if(S15=0,"",T15/S15-1) -> 0.088827398 | V104: =if(U15=0,"",V15/U15-1) | W104: =if(V15=0,"",W15/V15-1) | X104: =if(W15=0,"",X15/W15-1) | Y104: =if(X15=0,"",Y15/X15-1) | AC104: =if(AB15=0,"",AC15/AB15-1) -> 0.78599164 | AD104: =if(AC15=0,"",AD15/AC15-1) -> -0.25825774 | AF104: =if(AE15=0,"",AF15/AE15-1) | AH104: =if(AG15=0,"",AH15/AG15-1) | AJ104: =if(AI15=0,"",AJ15/AI15-1) | AM104: =if(AL15=0,"",AM15/AL15-1) | AN104: =if(AM15=0,"",AN15/AM15-1) -> -0.51392684 | AO104: =if(AN15=0,"",AO15/AN15-1) -> 6.4458955e-07 | AQ104: =if(AP15=0,"",AQ15/AP15-1) | AR104: =if(AQ15=0,"",AR15/AQ15-1) -> 18.517524 | AS104: =if(AR15=0,"",AS15/AR15-1) -> -0.056487188 | AU104: =if(AT15=0,"",AU15/AT15-1) | AV104: =if(AU15=0,"",AV15/AU15-1) -> 0.35110832 | AW104: =if(AV15=0,"",AW15/AV15-1) -> 0.20848118 | AY104: =if(AX15=0,"",AY15/AX15-1) | AZ104: =if(AY15=0,"",AZ15/AY15-1) -> -0.086466465 | BA104: =if(AZ15=0,"",BA15/AZ15-1) -> -0.09465057 | BB104: =if(BA15=0,"",BB15/BA15-1) -> -0.1045459 | BD104: =if(BC15=0,"",BD15/BC15-1) | BE104: =if(BD15=0,"",BE15/BD15-1) -> 0.024124973 | BF104: =if(BE15=0,"",BF15/BE15-1) -> -0.12007788 | BG104: =if(BF15=0,"",BG15/BF15-1) -> -0.171567 | BI104: =if(BH15=0,"",BI15/BH15-1) | BJ104: =if(BI15=0,"",BJ15/BI15-1) -> 0 | BK104: =if(BJ15=0,"",BK15/BJ15-1) -> 0 | BM104: =if(BL15=0,"",BM15/BL15-1) | BN104: =if(BM15=0,"",BN15/BM15-1) | BO104: =if(BN15=0,"",BO15/BN15-1) | BQ104: =if(BP15=0,"",BQ15/BP15-1) | BR104: =if(BQ15=0,"",BR15/BQ15-1) | BT104: =if(BS15=0,"",BT15/BS15-1) | BU104: =if(BT15=0,"",BU15/BT15-1) | BV104: =if(BU15=0,"",BV15/BU15-1)
A105: Total de Activo | E105: =if(D16=0,"",E16/D16-1) -> -0.025111293 | F105: =if(E16=0,"",F16/E16-1) -> 0.10865596 | G105: =if(F16=0,"",G16/F16-1) -> 0.15503726 | H105: =if(G16=0,"",H16/G16-1) -> 0.25305846 | K105: =if(J16=0,"",K16/J16-1) -> 0.079957062 | L105: =if(K16=0,"",L16/K16-1) -> 0.11555659 | M105: =if(L16=0,"",M16/L16-1) -> 0.12517658 | N105: =if(M16=0,"",N16/M16-1) -> 0.014791901 | Q105: =if(P16=0,"",Q16/P16-1) -> 0.10281927 | R105: =if(Q16=0,"",R16/Q16-1) -> 0.0094600587 | S105: =if(R16=0,"",S16/R16-1) -> 0.091229717 | T105: =if(S16=0,"",T16/S16-1) -> 0.087685786 | V105: =if(U16=0,"",V16/U16-1) | W105: =if(V16=0,"",W16/V16-1) -> -0.59380953 | X105: =if(W16=0,"",X16/W16-1) -> 0.78265488 | Y105: =if(X16=0,"",Y16/X16-1) -> 0.29575282 | AC105: =if(AB16=0,"",AC16/AB16-1) -> -0.0087534586 | AD105: =if(AC16=0,"",AD16/AC16-1) -> 0.016540265 | AF105: =if(AE16=0,"",AF16/AE16-1) | AH105: =if(AG16=0,"",AH16/AG16-1) -> 9.9687322e-05 | AJ105: =if(AI16=0,"",AJ16/AI16-1) | AM105: =if(AL16=0,"",AM16/AL16-1) | AN105: =if(AM16=0,"",AN16/AM16-1) -> 0.18524096 | AO105: =if(AN16=0,"",AO16/AN16-1) -> -0.051646498 | AQ105: =if(AP16=0,"",AQ16/AP16-1) | AR105: =if(AQ16=0,"",AR16/AQ16-1) -> 0.28801315 | AS105: =if(AR16=0,"",AS16/AR16-1) -> -0.038020952 | AU105: =if(AT16=0,"",AU16/AT16-1) | AV105: =if(AU16=0,"",AV16/AU16-1) -> 0.067964427 | AW105: =if(AV16=0,"",AW16/AV16-1) -> -0.03339451 | AY105: =if(AX16=0,"",AY16/AX16-1) | AZ105: =if(AY16=0,"",AZ16/AY16-1) -> 0.69325429 | BA105: =if(AZ16=0,"",BA16/AZ16-1) -> 0.52758171 | BB105: =if(BA16=0,"",BB16/BA16-1) -> 0.20397751 | BD105: =if(BC16=0,"",BD16/BC16-1) | BE105: =if(BD16=0,"",BE16/BD16-1) -> -0.017467001 | BF105: =if(BE16=0,"",BF16/BE16-1) -> -0.0035345883 | BG105: =if(BF16=0,"",BG16/BF16-1) -> 0.027458115 | BI105: =if(BH16=0,"",BI16/BH16-1) | BJ105: =if(BI16=0,"",BJ16/BI16-1) -> 0.33626159 | BK105: =if(BJ16=0,"",BK16/BJ16-1) -> 0.33894502 | BM105: =if(BL16=0,"",BM16/BL16-1) | BN105: =if(BM16=0,"",BN16/BM16-1) -> 0.15005221 | BO105: =if(BN16=0,"",BO16/BN16-1) -> 0.42201005 | BQ105: =if(BP16=0,"",BQ16/BP16-1) | BR105: =if(BQ16=0,"",BR16/BQ16-1) -> 5.2832768 | BT105: =if(BS16=0,"",BT16/BS16-1) | BU105: =if(BT16=0,"",BU16/BT16-1) -> 0.61891592 | BV105: =if(BU16=0,"",BV16/BU16-1) -> 0.37994218
E106: =if(D17=0,"",E17/D17-1) | F106: =if(E17=0,"",F17/E17-1) | G106: =if(F17=0,"",G17/F17-1) | H106: =if(G17=0,"",H17/G17-1) | K106: =if(J17=0,"",K17/J17-1) | L106: =if(K17=0,"",L17/K17-1) | M106: =if(L17=0,"",M17/L17-1) | N106: =if(M17=0,"",N17/M17-1) | Q106: =if(P17=0,"",Q17/P17-1) | R106: =if(Q17=0,"",R17/Q17-1) | S106: =if(R17=0,"",S17/R17-1) | T106: =if(S17=0,"",T17/S17-1) | V106: =if(U17=0,"",V17/U17-1) | W106: =if(V17=0,"",W17/V17-1) | X106: =if(W17=0,"",X17/W17-1) | Y106: =if(X17=0,"",Y17/X17-1) | AC106: =if(AB17=0,"",AC17/AB17-1) | AD106: =if(AC17=0,"",AD17/AC17-1) | AF106: =if(AE17=0,"",AF17/AE17-1) | AH106: =if(AG17=0,"",AH17/AG17-1) | AJ106: =if(AI17=0,"",AJ17/AI17-1) | AM106: =if(AL17=0,"",AM17/AL17-1) | AN106: =if(AM17=0,"",AN17/AM17-1) | AO106: =if(AN17=0,"",AO17/AN17-1) | AQ106: =if(AP17=0,"",AQ17/AP17-1) | AR106: =if(AQ17=0,"",AR17/AQ17-1) | AS106: =if(AR17=0,"",AS17/AR17-1) | AU106: =if(AT17=0,"",AU17/AT17-1) | AV106: =if(AU17=0,"",AV17/AU17-1) | AW106: =if(AV17=0,"",AW17/AV17-1) | AY106: =if(AX17=0,"",AY17/AX17-1) | AZ106: =if(AY17=0,"",AZ17/AY17-1) | BA106: =if(AZ17=0,"",BA17/AZ17-1) | BB106: =if(BA17=0,"",BB17/BA17-1) | BD106: =if(BC17=0,"",BD17/BC17-1) | BE106: =if(BD17=0,"",BE17/BD17-1) | BF106: =if(BE17=0,"",BF17/BE17-1) | BG106: =if(BF17=0,"",BG17/BF17-1) | BI106: =if(BH17=0,"",BI17/BH17-1) | BJ106: =if(BI17=0,"",BJ17/BI17-1) | BK106: =if(BJ17=0,"",BK17/BJ17-1) | BM106: =if(BL17=0,"",BM17/BL17-1) | BN106: =if(BM17=0,"",BN17/BM17-1) | BO106: =if(BN17=0,"",BO17/BN17-1) | BQ106: =if(BP17=0,"",BQ17/BP17-1) | BR106: =if(BQ17=0,"",BR17/BQ17-1) | BT106: =if(BS17=0,"",BT17/BS17-1) | BU106: =if(BT17=0,"",BU17/BT17-1) | BV106: =if(BU17=0,"",BV17/BU17-1)
A107: Pasivo Corriente | E107: =if(D18=0,"",E18/D18-1) -> -0.25699486 | F107: =if(E18=0,"",F18/E18-1) -> 0.25612543 | G107: =if(F18=0,"",G18/F18-1) -> -0.1980416 | H107: =if(G18=0,"",H18/G18-1) -> 0.35928682 | K107: =if(J18=0,"",K18/J18-1) -> 0.65289536 | L107: =if(K18=0,"",L18/K18-1) -> -0.12538351 | M107: =if(L18=0,"",M18/L18-1) -> 0.18133108 | N107: =if(M18=0,"",N18/M18-1) -> 0.59597332 | Q107: =if(P18=0,"",Q18/P18-1) -> 0.21675244 | R107: =if(Q18=0,"",R18/Q18-1) -> 0.25837705 | S107: =if(R18=0,"",S18/R18-1) -> 0.1553847 | T107: =if(S18=0,"",T18/S18-1) -> 0.38931567 | V107: =if(U18=0,"",V18/U18-1) | W107: =if(V18=0,"",W18/V18-1) -> -0.84984328 | X107: =if(W18=0,"",X18/W18-1) -> 3.1507507 | Y107: =if(X18=0,"",Y18/X18-1) -> -0.13223389 | AB107: =if(AA18=0,"",AB18/AA18-1) | AC107: =if(AB18=0,"",AC18/AB18-1) -> -0.056704313 | AD107: =if(AC18=0,"",AD18/AC18-1) -> -0.29513454 | AF107: =if(AE18=0,"",AF18/AE18-1) | AH107: =if(AG18=0,"",AH18/AG18-1) | AJ107: =if(AI18=0,"",AJ18/AI18-1) | AM107: =if(AL18=0,"",AM18/AL18-1) | AN107: =if(AM18=0,"",AN18/AM18-1) -> 0.07216741 | AO107: =if(AN18=0,"",AO18/AN18-1) -> 0.0025123078 | AQ107: =if(AP18=0,"",AQ18/AP18-1) | AR107: =if(AQ18=0,"",AR18/AQ18-1) -> -0.37200698 | AS107: =if(AR18=0,"",AS18/AR18-1) -> -0.8735943 | AU107: =if(AT18=0,"",AU18/AT18-1) | AV107: =if(AU18=0,"",AV18/AU18-1) -> 0.74681007 | AW107: =if(AV18=0,"",AW18/AV18-1) -> -0.061244221 | AY107: =if(AX18=0,"",AY18/AX18-1) | AZ107: =if(AY18=0,"",AZ18/AY18-1) -> 3.3733502 | BA107: =if(AZ18=0,"",BA18/AZ18-1) -> 1.5955398 | BB107: =if(BA18=0,"",BB18/BA18-1) -> 0.19101083 | BD107: =if(BC18=0,"",BD18/BC18-1) | BE107: =if(BD18=0,"",BE18/BD18-1) -> 0.048469391 | BF107: =if(BE18=0,"",BF18/BE18-1) -> 0.096446749 | BG107: =if(BF18=0,"",BG18/BF18-1) -> 0.69839269 | BI107: =if(BH18=0,"",BI18/BH18-1) | BJ107: =if(BI18=0,"",BJ18/BI18-1) -> 0.6744848 | BK107: =if(BJ18=0,"",BK18/BJ18-1) -> 0.38611754 | BM107: =if(BL18=0,"",BM18/BL18-1) | BN107: =if(BM18=0,"",BN18/BM18-1) -> 0.10187186 | BO107: =if(BN18=0,"",BO18/BN18-1) -> 0.40871649 | BQ107: =if(BP18=0,"",BQ18/BP18-1) | BR107: =if(BQ18=0,"",BR18/BQ18-1) -> 0.35808421 | BT107: =if(BS18=0,"",BT18/BS18-1) | BU107: =if(BT18=0,"",BU18/BT18-1) -> 2.0082333 | BV107: =if(BU18=0,"",BV18/BU18-1) -> -0.68073058
A108: Pasivo No Corriente | E108: =if(D19=0,"",E19/D19-1) -> 0.58441714 | F108: =if(E19=0,"",F19/E19-1) -> -0.37694967 | G108: =if(F19=0,"",G19/F19-1) -> 1.220076 | H108: =if(G19=0,"",H19/G19-1) -> -0.025754816 | K108: =if(J19=0,"",K19/J19-1) -> -0.17298199 | L108: =if(K19=0,"",L19/K19-1) -> 0.36661437 | M108: =if(L19=0,"",M19/L19-1) -> 0.17102554 | N108: =if(M19=0,"",N19/M19-1) -> -0.23440538 | Q108: =if(P19=0,"",Q19/P19-1) -> 0.28314461 | R108: =if(Q19=0,"",R19/Q19-1) -> -0.1729816 | S108: =if(R19=0,"",S19/R19-1) -> 0.10579011 | T108: =if(S19=0,"",T19/S19-1) -> 0.026430121 | V108: =if(U19=0,"",V19/U19-1) | W108: =if(V19=0,"",W19/V19-1) -> 3.284431 | X108: =if(W19=0,"",X19/W19-1) -> -0.40107603 | Y108: =if(X19=0,"",Y19/X19-1) -> 78.22288 | AB108: =if(AA19=0,"",AB19/AA19-1) | AC108: =if(AB19=0,"",AC19/AB19-1) -> -0.017074157 | AD108: =if(AC19=0,"",AD19/AC19-1) -> 0.23271819 | AF108: =if(AE19=0,"",AF19/AE19-1) | AH108: =if(AG19=0,"",AH19/AG19-1) | AJ108: =if(AI19=0,"",AJ19/AI19-1) | AM108: =if(AL19=0,"",AM19/AL19-1) | AN108: =if(AM19=0,"",AN19/AM19-1) -> 0.94028397 | AO108: =if(AN19=0,"",AO19/AN19-1) -> -0.28191093 | AQ108: =if(AP19=0,"",AQ19/AP19-1) | AR108: =if(AQ19=0,"",AR19/AQ19-1) -> 0.73900245 | AS108: =if(AR19=0,"",AS19/AR19-1) -> -0.0043796866 | AU108: =if(AT19=0,"",AU19/AT19-1) | AV108: =if(AU19=0,"",AV19/AU19-1) -> -0.046202848 | AW108: =if(AV19=0,"",AW19/AV19-1) -> -0.031483483 | AY108: =if(AX19=0,"",AY19/AX19-1) | AZ108: =if(AY19=0,"",AZ19/AY19-1) -> 1.435054 | BA108: =if(AZ19=0,"",BA19/AZ19-1) -> 0.079362771 | BB108: =if(BA19=0,"",BB19/BA19-1) -> -0.016265559 | BD108: =if(BC19=0,"",BD19/BC19-1) | BE108: =if(BD19=0,"",BE19/BD19-1) -> -0.0090422995 | BF108: =if(BE19=0,"",BF19/BE19-1) -> 0.012164626 | BG108: =if(BF19=0,"",BG19/BF19-1) -> 0.0139148 | BI108: =if(BH19=0,"",BI19/BH19-1) | BJ108: =if(BI19=0,"",BJ19/BI19-1) -> -0.90925834 | BK108: =if(BJ19=0,"",BK19/BJ19-1) -> 0 | BM108: =if(BL19=0,"",BM19/BL19-1) | BN108: =if(BM19=0,"",BN19/BM19-1) -> -0.39201662 | BO108: =if(BN19=0,"",BO19/BN19-1) -> 3.3658414 | BQ108: =if(BP19=0,"",BQ19/BP19-1) | BR108: =if(BQ19=0,"",BR19/BQ19-1) | BT108: =if(BS19=0,"",BT19/BS19-1) | BU108: =if(BT19=0,"",BU19/BT19-1) | BV108: =if(BU19=0,"",BV19/BU19-1) -> 86.546011
A109: Total Pasivo | E109: =if(D20=0,"",E20/D20-1) -> -0.088939793 | F109: =if(E20=0,"",F20/E20-1) -> 0.036227769 | G109: =if(F20=0,"",G20/F20-1) -> 0.098131442 | H109: =if(G20=0,"",H20/G20-1) -> 0.19671155 | K109: =if(J20=0,"",K20/J20-1) -> 0.1103748 | L109: =if(K20=0,"",L20/K20-1) -> 0.11533487 | M109: =if(L20=0,"",M20/L20-1) -> 0.17515295 | N109: =if(M20=0,"",N20/M20-1) -> 0.099912535 | Q109: =if(P20=0,"",Q20/P20-1) -> 0.25443151 | R109: =if(Q20=0,"",R20/Q20-1) -> 0.0079677301 | S109: =if(R20=0,"",S20/R20-1) -> 0.1317628 | T109: =if(S20=0,"",T20/S20-1) -> 0.22043985 | V109: =if(U20=0,"",V20/U20-1) | W109: =if(V20=0,"",W20/V20-1) -> -0.84196322 | X109: =if(W20=0,"",X20/W20-1) -> 2.9672165 | Y109: =if(X20=0,"",Y20/X20-1) -> 0.47901546 | AB109: =if(AA20=0,"",AB20/AA20-1) | AC109: =if(AB20=0,"",AC20/AB20-1) -> -0.037758936 | AD109: =if(AC20=0,"",AD20/AC20-1) -> -0.037367659 | AF109: =if(AE20=0,"",AF20/AE20-1) | AH109: =if(AG20=0,"",AH20/AG20-1) | AJ109: =if(AI20=0,"",AJ20/AI20-1) | AM109: =if(AL20=0,"",AM20/AL20-1) | AN109: =if(AM20=0,"",AN20/AM20-1) -> 0.21576371 | AO109: =if(AN20=0,"",AO20/AN20-1) -> -0.072571519 | AQ109: =if(AP20=0,"",AQ20/AP20-1) | AR109: =if(AQ20=0,"",AR20/AQ20-1) -> 0.48292314 | AS109: =if(AR20=0,"",AS20/AR20-1) -> -0.089223455 | AU109: =if(AT20=0,"",AU20/AT20-1) | AV109: =if(AU20=0,"",AV20/AU20-1) -> 0.035038807 | AW109: =if(AV20=0,"",AW20/AV20-1) -> -0.036629026 | AY109: =if(AX20=0,"",AY20/AX20-1) | AZ109: =if(AY20=0,"",AZ20/AY20-1) -> 1.7561051 | BA109: =if(AZ20=0,"",BA20/AZ20-1) -> 0.4778573 | BB109: =if(BA20=0,"",BB20/BA20-1) -> 0.079413627 | BD109: =if(BC20=0,"",BD20/BC20-1) | BE109: =if(BD20=0,"",BE20/BD20-1) -> 0.004688984 | BF109: =if(BE20=0,"",BF20/BE20-1) -> 0.033164398 | BG109: =if(BF20=0,"",BG20/BF20-1) -> 0.19490566 | BI109: =if(BH20=0,"",BI20/BH20-1) | BJ109: =if(BI20=0,"",BJ20/BI20-1) -> 0.65395196 | BK109: =if(BJ20=0,"",BK20/BJ20-1) -> 0.38584289 | BM109: =if(BL20=0,"",BM20/BL20-1) | BN109: =if(BM20=0,"",BN20/BM20-1) -> -0.20077855 | BO109: =if(BN20=0,"",BO20/BN20-1) -> 1.787216 | BQ109: =if(BP20=0,"",BQ20/BP20-1) | BR109: =if(BQ20=0,"",BR20/BQ20-1) -> 5.5087814 | BT109: =if(BS20=0,"",BT20/BS20-1) | BU109: =if(BT20=0,"",BU20/BT20-1) -> 2.0431104 | BV109: =if(BU20=0,"",BV20/BU20-1) -> 0.31897525
E110: =if(D21=0,"",E21/D21-1) | F110: =if(E21=0,"",F21/E21-1) | G110: =if(F21=0,"",G21/F21-1) | H110: =if(G21=0,"",H21/G21-1) | K110: =if(J21=0,"",K21/J21-1) | L110: =if(K21=0,"",L21/K21-1) | M110: =if(L21=0,"",M21/L21-1) | N110: =if(M21=0,"",N21/M21-1) | Q110: =if(P21=0,"",Q21/P21-1) | R110: =if(Q21=0,"",R21/Q21-1) | S110: =if(R21=0,"",S21/R21-1) | T110: =if(S21=0,"",T21/S21-1) | V110: =if(U21=0,"",V21/U21-1) | W110: =if(V21=0,"",W21/V21-1) | X110: =if(W21=0,"",X21/W21-1) | Y110: =if(X21=0,"",Y21/X21-1) | AB110: =if(AA21=0,"",AB21/AA21-1) | AC110: =if(AB21=0,"",AC21/AB21-1) | AD110: =if(AC21=0,"",AD21/AC21-1) | AF110: =if(AE21=0,"",AF21/AE21-1) | AH110: =if(AG21=0,"",AH21/AG21-1) | AJ110: =if(AI21=0,"",AJ21/AI21-1) | AM110: =if(AL21=0,"",AM21/AL21-1) | AN110: =if(AM21=0,"",AN21/AM21-1) | AO110: =if(AN21=0,"",AO21/AN21-1) | AQ110: =if(AP21=0,"",AQ21/AP21-1) | AR110: =if(AQ21=0,"",AR21/AQ21-1) | AS110: =if(AR21=0,"",AS21/AR21-1) | AU110: =if(AT21=0,"",AU21/AT21-1) | AV110: =if(AU21=0,"",AV21/AU21-1) | AW110: =if(AV21=0,"",AW21/AV21-1) | AY110: =if(AX21=0,"",AY21/AX21-1) | AZ110: =if(AY21=0,"",AZ21/AY21-1) | BA110: =if(AZ21=0,"",BA21/AZ21-1) | BB110: =if(BA21=0,"",BB21/BA21-1) | BD110: =if(BC21=0,"",BD21/BC21-1) | BE110: =if(BD21=0,"",BE21/BD21-1) | BF110: =if(BE21=0,"",BF21/BE21-1) | BG110: =if(BF21=0,"",BG21/BF21-1) | BI110: =if(BH21=0,"",BI21/BH21-1) | BJ110: =if(BI21=0,"",BJ21/BI21-1) | BK110: =if(BJ21=0,"",BK21/BJ21-1) | BM110: =if(BL21=0,"",BM21/BL21-1) | BN110: =if(BM21=0,"",BN21/BM21-1) | BO110: =if(BN21=0,"",BO21/BN21-1) | BQ110: =if(BP21=0,"",BQ21/BP21-1) | BR110: =if(BQ21=0,"",BR21/BQ21-1) | BT110: =if(BS21=0,"",BT21/BS21-1) | BU110: =if(BT21=0,"",BU21/BT21-1) | BV110: =if(BU21=0,"",BV21/BU21-1)
A111: Capital | E111: =if(D22=0,"",E22/D22-1) | F111: =if(E22=0,"",F22/E22-1) | G111: =if(F22=0,"",G22/F22-1) | H111: =if(G22=0,"",H22/G22-1) | K111: =if(J22=0,"",K22/J22-1) -> 0.00017395086 | L111: =if(K22=0,"",L22/K22-1) -> 0 | M111: =if(L22=0,"",M22/L22-1) -> 0 | N111: =if(M22=0,"",N22/M22-1) -> 0 | Q111: =if(P22=0,"",Q22/P22-1) -> 0.00017898993 | R111: =if(Q22=0,"",R22/Q22-1) -> 0.00020995401 | S111: =if(R22=0,"",S22/R22-1) -> 0 | T111: =if(S22=0,"",T22/S22-1) -> 0.00012523567 | V111: =if(U22=0,"",V22/U22-1) | W111: =if(V22=0,"",W22/V22-1) -> 0 | X111: =if(W22=0,"",X22/W22-1) -> 0 | Y111: =if(X22=0,"",Y22/X22-1) -> 0 | AB111: =if(AA22=0,"",AB22/AA22-1) | AC111: =if(AB22=0,"",AC22/AB22-1) -> 0 | AD111: =if(AC22=0,"",AD22/AC22-1) -> 0 | AF111: =if(AE22=0,"",AF22/AE22-1) | AH111: =if(AG22=0,"",AH22/AG22-1) -> 0 | AJ111: =if(AI22=0,"",AJ22/AI22-1) | AM111: =if(AL22=0,"",AM22/AL22-1) | AN111: =if(AM22=0,"",AN22/AM22-1) -> 0 | AO111: =if(AN22=0,"",AO22/AN22-1) -> 0 | AQ111: =if(AP22=0,"",AQ22/AP22-1) | AR111: =if(AQ22=0,"",AR22/AQ22-1) -> 0 | AS111: =if(AR22=0,"",AS22/AR22-1) -> 0 | AU111: =if(AT22=0,"",AU22/AT22-1) | AV111: =if(AU22=0,"",AV22/AU22-1) -> 0 | AW111: =if(AV22=0,"",AW22/AV22-1) -> 0 | AY111: =if(AX22=0,"",AY22/AX22-1) | AZ111: =if(AY22=0,"",AZ22/AY22-1) -> 0 | BA111: =if(AZ22=0,"",BA22/AZ22-1) -> 0 | BB111: =if(BA22=0,"",BB22/BA22-1) -> 1.126938 | BD111: =if(BC22=0,"",BD22/BC22-1) | BE111: =if(BD22=0,"",BE22/BD22-1) -> 0 | BF111: =if(BE22=0,"",BF22/BE22-1) -> 0 | BG111: =if(BF22=0,"",BG22/BF22-1) -> 0 | BI111: =if(BH22=0,"",BI22/BH22-1) | BJ111: =if(BI22=0,"",BJ22/BI22-1) -> 0 | BK111: =if(BJ22=0,"",BK22/BJ22-1) -> -0.8 | BM111: =if(BL22=0,"",BM22/BL22-1) | BN111: =if(BM22=0,"",BN22/BM22-1) -> 0 | BO111: =if(BN22=0,"",BO22/BN22-1) -> 0 | BQ111: =if(BP22=0,"",BQ22/BP22-1) | BR111: =if(BQ22=0,"",BR22/BQ22-1) -> 0 | BT111: =if(BS22=0,"",BT22/BS22-1) | BU111: =if(BT22=0,"",BU22/BT22-1) -> 0 | BV111: =if(BU22=0,"",BV22/BU22-1) -> 0
A112: Otros | E112: =if(D23=0,"",E23/D23-1) | F112: =if(E23=0,"",F23/E23-1) | G112: =if(F23=0,"",G23/F23-1) | H112: =if(G23=0,"",H23/G23-1) | K112: =if(J23=0,"",K23/J23-1) | L112: =if(K23=0,"",L23/K23-1) | M112: =if(L23=0,"",M23/L23-1) -> -4.3042341 | N112: =if(M23=0,"",N23/M23-1) -> -1 | Q112: =if(P23=0,"",Q23/P23-1) -> 0.076118414 | R112: =if(Q23=0,"",R23/Q23-1) -> -0.8330688 | S112: =if(R23=0,"",S23/R23-1) -> -0.243191 | T112: =if(S23=0,"",T23/S23-1) -> 2.259131 | V112: =if(U23=0,"",V23/U23-1) | W112: =if(V23=0,"",W23/V23-1) | X112: =if(W23=0,"",X23/W23-1) | Y112: =if(X23=0,"",Y23/X23-1) | AB112: =if(AA23=0,"",AB23/AA23-1) | AC112: =if(AB23=0,"",AC23/AB23-1) | AD112: =if(AC23=0,"",AD23/AC23-1) | AF112: =if(AE23=0,"",AF23/AE23-1) | AH112: =if(AG23=0,"",AH23/AG23-1) -> -1.8882747e-05 | AJ112: =if(AI23=0,"",AJ23/AI23-1) | AM112: =if(AL23=0,"",AM23/AL23-1) | AN112: =if(AM23=0,"",AN23/AM23-1) | AO112: =if(AN23=0,"",AO23/AN23-1) | AQ112: =if(AP23=0,"",AQ23/AP23-1) | AR112: =if(AQ23=0,"",AR23/AQ23-1) -> 0 | AS112: =if(AR23=0,"",AS23/AR23-1) -> 0 | AU112: =if(AT23=0,"",AU23/AT23-1) | AV112: =if(AU23=0,"",AV23/AU23-1) -> 0 | AW112: =if(AV23=0,"",AW23/AV23-1) -> 0.56100082 | AY112: =if(AX23=0,"",AY23/AX23-1) | AZ112: =if(AY23=0,"",AZ23/AY23-1) -> -0.48881343 | BA112: =if(AZ23=0,"",BA23/AZ23-1) -> 1.9142641 | BB112: =if(BA23=0,"",BB23/BA23-1) -> -0.6316305 | BD112: =if(BC23=0,"",BD23/BC23-1) | BE112: =if(BD23=0,"",BE23/BD23-1) -> -0.077175338 | BF112: =if(BE23=0,"",BF23/BE23-1) -> -0.1600508 | BG112: =if(BF23=0,"",BG23/BF23-1) -> -0.36549873 | BI112: =if(BH23=0,"",BI23/BH23-1) | BJ112: =if(BI23=0,"",BJ23/BI23-1) -> -1 | BK112: =if(BJ23=0,"",BK23/BJ23-1) | BM112: =if(BL23=0,"",BM23/BL23-1) | BN112: =if(BM23=0,"",BN23/BM23-1) -> 0 | BO112: =if(BN23=0,"",BO23/BN23-1) -> 0 | BQ112: =if(BP23=0,"",BQ23/BP23-1) | BR112: =if(BQ23=0,"",BR23/BQ23-1) | BT112: =if(BS23=0,"",BT23/BS23-1) | BU112: =if(BT23=0,"",BU23/BT23-1) | BV112: =if(BU23=0,"",BV23/BU23-1)
A113: Reserva Legal | E113: =if(D24=0,"",E24/D24-1) | F113: =if(E24=0,"",F24/E24-1) | G113: =if(F24=0,"",G24/F24-1) | H113: =if(G24=0,"",H24/G24-1) | K113: =if(J24=0,"",K24/J24-1) -> 0.047440743 | L113: =if(K24=0,"",L24/K24-1) -> 0.047647275 | M113: =if(L24=0,"",M24/L24-1) -> 0.022986858 | N113: =if(M24=0,"",N24/M24-1) -> 0 | Q113: =if(P24=0,"",Q24/P24-1) -> 0.045590785 | R113: =if(Q24=0,"",R24/Q24-1) -> 0.065541883 | S113: =if(R24=0,"",S24/R24-1) -> 0.021841411 | T113: =if(S24=0,"",T24/S24-1) -> 0.087497593 | V113: =if(U24=0,"",V24/U24-1) | W113: =if(V24=0,"",W24/V24-1) -> 0 | X113: =if(W24=0,"",X24/W24-1) -> 0.67339483 | Y113: =if(X24=0,"",Y24/X24-1) -> 0 | AB113: =if(AA24=0,"",AB24/AA24-1) | AC113: =if(AB24=0,"",AC24/AB24-1) | AD113: =if(AC24=0,"",AD24/AC24-1) | AF113: =if(AE24=0,"",AF24/AE24-1) | AH113: =if(AG24=0,"",AH24/AG24-1) -> 0 | AJ113: =if(AI24=0,"",AJ24/AI24-1) | AM113: =if(AL24=0,"",AM24/AL24-1) | AN113: =if(AM24=0,"",AN24/AM24-1) -> 0.80542578 | AO113: =if(AN24=0,"",AO24/AN24-1) -> 0 | AQ113: =if(AP24=0,"",AQ24/AP24-1) | AR113: =if(AQ24=0,"",AR24/AQ24-1) -> 0.18377056 | AS113: =if(AR24=0,"",AS24/AR24-1) -> 0 | AU113: =if(AT24=0,"",AU24/AT24-1) | AV113: =if(AU24=0,"",AV24/AU24-1) -> 0.55137016 | AW113: =if(AV24=0,"",AW24/AV24-1) -> 0.52045431 | AY113: =if(AX24=0,"",AY24/AX24-1) | AZ113: =if(AY24=0,"",AZ24/AY24-1) -> 0.68944639 | BA113: =if(AZ24=0,"",BA24/AZ24-1) -> -0.40809012 | BB113: =if(BA24=0,"",BB24/BA24-1) -> 1.5755922 | BD113: =if(BC24=0,"",BD24/BC24-1) | BE113: =if(BD24=0,"",BE24/BD24-1) -> 0.045007241 | BF113: =if(BE24=0,"",BF24/BE24-1) -> 0.076816722 | BG113: =if(BF24=0,"",BG24/BF24-1) -> 0.12283592 | BI113: =if(BH24=0,"",BI24/BH24-1) | BJ113: =if(BI24=0,"",BJ24/BI24-1) | BK113: =if(BJ24=0,"",BK24/BJ24-1) | BM113: =if(BL24=0,"",BM24/BL24-1) | BN113: =if(BM24=0,"",BN24/BM24-1) -> 0.35998807 | BO113: =if(BN24=0,"",BO24/BN24-1) -> 0.19256926 | BQ113: =if(BP24=0,"",BQ24/BP24-1) | BR113: =if(BQ24=0,"",BR24/BQ24-1) | BT113: =if(BS24=0,"",BT24/BS24-1) | BU113: =if(BT24=0,"",BU24/BT24-1) -> 0.49140546 | BV113: =if(BU24=0,"",BV24/BU24-1) -> 0.24124151
A114: Utilidades Retenidas | E114: =if(D25=0,"",E25/D25-1) -> 0.20200858 | F114: =if(E25=0,"",F25/E25-1) -> 0.30400765 | G114: =if(F25=0,"",G25/F25-1) -> 0.27700455 | H114: =if(G25=0,"",H25/G25-1) -> 0.35691198 | K114: =if(J25=0,"",K25/J25-1) -> 0.065902373 | L114: =if(K25=0,"",L25/K25-1) -> 0.18364174 | M114: =if(L25=0,"",M25/L25-1) -> 0.016829767 | N114: =if(M25=0,"",N25/M25-1) -> -0.070928924 | Q114: =if(P25=0,"",Q25/P25-1) -> -0.35416215 | R114: =if(Q25=0,"",R25/Q25-1) -> -1.19625 | S114: =if(R25=0,"",S25/R25-1) -> 23.270837 | T114: =if(S25=0,"",T25/S25-1) -> -1.5189714 | V114: =if(U25=0,"",V25/U25-1) | W114: =if(V25=0,"",W25/V25-1) -> -30.615023 | X114: =if(W25=0,"",X25/W25-1) -> -0.25327523 | Y114: =if(X25=0,"",Y25/X25-1) -> -0.56821747 | AB114: =if(AA25=0,"",AB25/AA25-1) | AC114: =if(AB25=0,"",AC25/AB25-1) -> 0.055292472 | AD114: =if(AC25=0,"",AD25/AC25-1) -> -0.19280781 | AF114: =if(AE25=0,"",AF25/AE25-1) | AH114: =if(AG25=0,"",AH25/AG25-1) -> 0.001776568 | AJ114: =if(AI25=0,"",AJ25/AI25-1) | AM114: =if(AL25=0,"",AM25/AL25-1) | AN114: =if(AM25=0,"",AN25/AM25-1) -> 0.2982804 | AO114: =if(AN25=0,"",AO25/AN25-1) -> -0.029799992 | AQ114: =if(AP25=0,"",AQ25/AP25-1) | AR114: =if(AQ25=0,"",AR25/AQ25-1) -> 0.13091214 | AS114: =if(AR25=0,"",AS25/AR25-1) -> 0.094186284 | AU114: =if(AT25=0,"",AU25/AT25-1) | AV114: =if(AU25=0,"",AV25/AU25-1) -> 1.0558953 | AW114: =if(AV25=0,"",AW25/AV25-1) -> -0.25048868 | AY114: =if(AX25=0,"",AY25/AX25-1) | AZ114: =if(AY25=0,"",AZ25/AY25-1) -> 0.79450579 | BA114: =if(AZ25=0,"",BA25/AZ25-1) -> 2.0126276 | BB114: =if(BA25=0,"",BB25/BA25-1) -> 1.2099871 | BD114: =if(BC25=0,"",BD25/BC25-1) | BE114: =if(BD25=0,"",BE25/BD25-1) -> -0.31695131 | BF114: =if(BE25=0,"",BF25/BE25-1) -> -2.1170572 | BG114: =if(BF25=0,"",BG25/BF25-1) -> -0.057736871 | BI114: =if(BH25=0,"",BI25/BH25-1) | BJ114: =if(BI25=0,"",BJ25/BI25-1) -> 0.11404871 | BK114: =if(BJ25=0,"",BK25/BJ25-1) -> -1.048186 | BM114: =if(BL25=0,"",BM25/BL25-1) | BN114: =if(BM25=0,"",BN25/BM25-1) -> 0.28363399 | BO114: =if(BN25=0,"",BO25/BN25-1) -> 0.34784712 | BQ114: =if(BP25=0,"",BQ25/BP25-1) | BR114: =if(BQ25=0,"",BR25/BQ25-1) -> 4.491339 | BT114: =if(BS25=0,"",BT25/BS25-1) | BU114: =if(BT25=0,"",BU25/BT25-1) -> -0.36659843 | BV114: =if(BU25=0,"",BV25/BU25-1) -> 0.59034509
A115: Total Patrimonio | E115: =if(D26=0,"",E26/D26-1) -> 0.20200576 | F115: =if(E26=0,"",F26/E26-1) -> 0.30400411 | G115: =if(F26=0,"",G26/F26-1) -> 0.27700209 | H115: =if(G26=0,"",H26/G26-1) -> 0.35690949 | K115: =if(J26=0,"",K26/J26-1) -> 0.047925349 | L115: =if(K26=0,"",L26/K26-1) -> 0.11580403 | M115: =if(L26=0,"",M26/L26-1) -> 0.069426069 | N115: =if(M26=0,"",N26/M26-1) -> -0.089550958 | Q115: =if(P26=0,"",Q26/P26-1) -> 0.012696328 | R115: =if(Q26=0,"",R26/Q26-1) -> 0.010558992 | S115: =if(R26=0,"",S26/R26-1) -> 0.061458152 | T115: =if(S26=0,"",T26/S26-1) -> -0.016280457 | V115: =if(U26=0,"",V26/U26-1) | W115: =if(V26=0,"",W26/V26-1) -> -0.12569008 | X115: =if(W26=0,"",X26/W26-1) -> 0.037774898 | Y115: =if(X26=0,"",Y26/X26-1) -> 0.056857146 | AB115: =if(AA26=0,"",AB26/AA26-1) | AC115: =if(AB26=0,"",AC26/AB26-1) -> 0.024433213 | AD115: =if(AC26=0,"",AD26/AC26-1) -> 0.074474668 | AF115: =if(AE26=0,"",AF26/AE26-1) | AH115: =if(AG26=0,"",AH26/AG26-1) -> 9.9687322e-05 | AJ115: =if(AI26=0,"",AJ26/AI26-1) | AM115: =if(AL26=0,"",AM26/AL26-1) | AN115: =if(AM26=0,"",AN26/AM26-1) -> 0.1345944 | AO115: =if(AN26=0,"",AO26/AN26-1) -> -0.014441535 | AQ115: =if(AP26=0,"",AQ26/AP26-1) | AR115: =if(AQ26=0,"",AR26/AQ26-1) -> 0.064735748 | AS115: =if(AR26=0,"",AS26/AR26-1) -> 0.04367089 | AU115: =if(AT26=0,"",AU26/AT26-1) | AV115: =if(AU26=0,"",AV26/AU26-1) -> 0.16411124 | AW115: =if(AV26=0,"",AW26/AV26-1) -> -0.024996575 | AY115: =if(AX26=0,"",AY26/AX26-1) | AZ115: =if(AY26=0,"",AZ26/AY26-1) -> -0.1303656 | BA115: =if(AZ26=0,"",BA26/AZ26-1) -> 0.64970072 | BB115: =if(BA26=0,"",BB26/BA26-1) -> 0.47802955 | BD115: =if(BC26=0,"",BD26/BC26-1) | BE115: =if(BD26=0,"",BE26/BD26-1) -> -0.05221486 | BF115: =if(BE26=0,"",BF26/BE26-1) -> -0.064546243 | BG115: =if(BF26=0,"",BG26/BF26-1) -> -0.27999907 | BI115: =if(BH26=0,"",BI26/BH26-1) | BJ115: =if(BI26=0,"",BJ26/BI26-1) -> -0.29223743 | BK115: =if(BJ26=0,"",BK26/BJ26-1) -> 0.1221302 | BM115: =if(BL26=0,"",BM26/BL26-1) | BN115: =if(BM26=0,"",BN26/BM26-1) -> 0.21337531 | BO115: =if(BN26=0,"",BO26/BN26-1) -> 0.25970403 | BQ115: =if(BP26=0,"",BQ26/BP26-1) | BR115: =if(BQ26=0,"",BR26/BQ26-1) -> 4.1659828 | BT115: =if(BS26=0,"",BT26/BS26-1) | BU115: =if(BT26=0,"",BU26/BT26-1) -> -0.35025562 | BV115: =if(BU26=0,"",BV26/BU26-1) -> 0.57425464
E116: =if(D27=0,"",E27/D27-1) | F116: =if(E27=0,"",F27/E27-1) | G116: =if(F27=0,"",G27/F27-1) | H116: =if(G27=0,"",H27/G27-1) | K116: =if(J27=0,"",K27/J27-1) | L116: =if(K27=0,"",L27/K27-1) | M116: =if(L27=0,"",M27/L27-1) | N116: =if(M27=0,"",N27/M27-1) | Q116: =if(P27=0,"",Q27/P27-1) | R116: =if(Q27=0,"",R27/Q27-1) | S116: =if(R27=0,"",S27/R27-1) | T116: =if(S27=0,"",T27/S27-1) | V116: =if(U27=0,"",V27/U27-1) | W116: =if(V27=0,"",W27/V27-1) | X116: =if(W27=0,"",X27/W27-1) | Y116: =if(X27=0,"",Y27/X27-1) | AB116: =if(AA27=0,"",AB27/AA27-1) | AC116: =if(AB27=0,"",AC27/AB27-1) | AD116: =if(AC27=0,"",AD27/AC27-1) | AF116: =if(AE27=0,"",AF27/AE27-1) | AH116: =if(AG27=0,"",AH27/AG27-1) | AJ116: =if(AI27=0,"",AJ27/AI27-1) | AM116: =if(AL27=0,"",AM27/AL27-1) | AN116: =if(AM27=0,"",AN27/AM27-1) | AO116: =if(AN27=0,"",AO27/AN27-1) | AQ116: =if(AP27=0,"",AQ27/AP27-1) | AR116: =if(AQ27=0,"",AR27/AQ27-1) | AS116: =if(AR27=0,"",AS27/AR27-1) | AU116: =if(AT27=0,"",AU27/AT27-1) | AV116: =if(AU27=0,"",AV27/AU27-1) | AW116: =if(AV27=0,"",AW27/AV27-1) | AY116: =if(AX27=0,"",AY27/AX27-1) | AZ116: =if(AY27=0,"",AZ27/AY27-1) | BA116: =if(AZ27=0,"",BA27/AZ27-1) | BB116: =if(BA27=0,"",BB27/BA27-1) | BD116: =if(BC27=0,"",BD27/BC27-1) | BE116: =if(BD27=0,"",BE27/BD27-1) | BF116: =if(BE27=0,"",BF27/BE27-1) | BG116: =if(BF27=0,"",BG27/BF27-1) | BI116: =if(BH27=0,"",BI27/BH27-1) | BJ116: =if(BI27=0,"",BJ27/BI27-1) | BK116: =if(BJ27=0,"",BK27/BJ27-1) | BM116: =if(BL27=0,"",BM27/BL27-1) | BN116: =if(BM27=0,"",BN27/BM27-1) | BO116: =if(BN27=0,"",BO27/BN27-1) | BQ116: =if(BP27=0,"",BQ27/BP27-1) | BR116: =if(BQ27=0,"",BR27/BQ27-1) | BT116: =if(BS27=0,"",BT27/BS27-1) | BU116: =if(BT27=0,"",BU27/BT27-1) | BV116: =if(BU27=0,"",BV27/BU27-1)
A117: Liquidez | E117: =if(D28=0,"",E28/D28-1) -> 0.013485294 | F117: =if(E28=0,"",F28/E28-1) -> 0.34384257 | G117: =if(F28=0,"",G28/F28-1) -> 0.38101259 | H117: =if(G28=0,"",H28/G28-1) -> -0.29514238 | K117: =if(J28=0,"",K28/J28-1) -> -0.30842366 | L117: =if(K28=0,"",L28/K28-1) -> 0.34622759 | M117: =if(L28=0,"",M28/L28-1) -> -0.038649751 | N117: =if(M28=0,"",N28/M28-1) -> -0.38697516 | Q117: =if(P28=0,"",Q28/P28-1) -> -0.73602549 | R117: =if(Q28=0,"",R28/Q28-1) -> 0.093143239 | S117: =if(R28=0,"",S28/R28-1) -> 0.0035537508 | T117: =if(S28=0,"",T28/S28-1) -> -0.20210662 | V117: =if(U28=0,"",V28/U28-1) | W117: =if(V28=0,"",W28/V28-1) -> 7.793411 | X117: =if(W28=0,"",X28/W28-1) -> -0.55415725 | Y117: =if(X28=0,"",Y28/X28-1) -> -0.393678 | AB117: =if(AA28=0,"",AB28/AA28-1) | AC117: =if(AB28=0,"",AC28/AB28-1) -> -0.09730465 | AD117: =if(AC28=0,"",AD28/AC28-1) -> 0.60375453 | AF117: =if(AE28=0,"",AF28/AE28-1) | AH117: =if(AG28=0,"",AH28/AG28-1) | AJ117: =if(AI28=0,"",AJ28/AI28-1) | AM117: =if(AL28=0,"",AM28/AL28-1) | AN117: =if(AM28=0,"",AN28/AM28-1) -> 0.17921003 | AO117: =if(AN28=0,"",AO28/AN28-1) -> -0.10708977 | AQ117: =if(AP28=0,"",AQ28/AP28-1) | AR117: =if(AQ28=0,"",AR28/AQ28-1) -> 1.0603492 | AS117: =if(AR28=0,"",AS28/AR28-1) -> 6.5967745 | AU117: =if(AT28=0,"",AU28/AT28-1) | AV117: =if(AU28=0,"",AV28/AU28-1) -> -0.42047554 | AW117: =if(AV28=0,"",AW28/AV28-1) -> -0.0089719311 | AY117: =if(AX28=0,"",AY28/AX28-1) | AZ117: =if(AY28=0,"",AZ28/AY28-1) -> -0.58743493 | BA117: =if(AZ28=0,"",BA28/AZ28-1) -> -0.41098356 | BB117: =if(BA28=0,"",BB28/BA28-1) -> 0.0011523189 | BD117: =if(BC28=0,"",BD28/BC28-1) | BE117: =if(BD28=0,"",BE28/BD28-1) -> -0.014462231 | BF117: =if(BE28=0,"",BF28/BE28-1) -> -0.084229468 | BG117: =if(BF28=0,"",BG28/BF28-1) -> -0.39165106 | BI117: =if(BH28=0,"",BI28/BH28-1) | BJ117: =if(BI28=0,"",BJ28/BI28-1) -> -0.20374054 | BK117: =if(BJ28=0,"",BK28/BJ28-1) -> -0.046092222 | BM117: =if(BL28=0,"",BM28/BL28-1) | BN117: =if(BM28=0,"",BN28/BM28-1) -> 0.069422027 | BO117: =if(BN28=0,"",BO28/BN28-1) -> -0.030726626 | BQ117: =if(BP28=0,"",BQ28/BP28-1) | BR117: =if(BQ28=0,"",BR28/BQ28-1) -> 3.6144588 | BT117: =if(BS28=0,"",BT28/BS28-1) | BU117: =if(BT28=0,"",BU28/BT28-1) -> -0.46066684 | BV117: =if(BU28=0,"",BV28/BU28-1) -> 3.3062768
A118: Prueba Acida | E118: =if(D29=0,"",E29/D29-1) -> 0.013487595 | F118: =if(E29=0,"",F29/E29-1) -> 0.3438429 | G118: =if(F29=0,"",G29/F29-1) -> 0.38101259 | H118: =if(G29=0,"",H29/G29-1) -> -0.29514238 | K118: =if(J29=0,"",K29/J29-1) -> -0.26168943 | L118: =if(K29=0,"",L29/K29-1) -> 0.43734095 | M118: =if(L29=0,"",M29/L29-1) -> -0.043740112 | N118: =if(M29=0,"",N29/M29-1) -> -0.44368798 | Q118: =if(P29=0,"",Q29/P29-1) -> -0.79569985 | R118: =if(Q29=0,"",R29/Q29-1) -> 0.15775552 | S118: =if(R29=0,"",S29/R29-1) -> -0.073286136 | T118: =if(S29=0,"",T29/S29-1) -> -0.11766847 | V118: =if(U29=0,"",V29/U29-1) | W118: =if(V29=0,"",W29/V29-1) -> 7.4130154 | X118: =if(W29=0,"",X29/W29-1) -> -0.48791862 | Y118: =if(X29=0,"",Y29/X29-1) -> -0.47483367 | AB118: =if(AA29=0,"",AB29/AA29-1) | AC118: =if(AB29=0,"",AC29/AB29-1) -> -0.1690625 | AD118: =if(AC29=0,"",AD29/AC29-1) -> 0.68018962 | AF118: =if(AE29=0,"",AF29/AE29-1) | AH118: =if(AG29=0,"",AH29/AG29-1) | AJ118: =if(AI29=0,"",AJ29/AI29-1) | AM118: =if(AL29=0,"",AM29/AL29-1) | AN118: =if(AM29=0,"",AN29/AM29-1) -> 0.26445869 | AO118: =if(AN29=0,"",AO29/AN29-1) -> -0.17333225 | AQ118: =if(AP29=0,"",AQ29/AP29-1) | AR118: =if(AQ29=0,"",AR29/AQ29-1) -> 1.141749 | AS118: =if(AR29=0,"",AS29/AR29-1) -> 6.7314103 | AU118: =if(AT29=0,"",AU29/AT29-1) | AV118: =if(AU29=0,"",AV29/AU29-1) -> -0.42047554 | AW118: =if(AV29=0,"",AW29/AV29-1) -> -0.0089719311 | AY118: =if(AX29=0,"",AY29/AX29-1) | AZ118: =if(AY29=0,"",AZ29/AY29-1) -> -0.54898693 | BA118: =if(AZ29=0,"",BA29/AZ29-1) -> -0.40985026 | BB118: =if(BA29=0,"",BB29/BA29-1) -> -0.060246644 | BD118: =if(BC29=0,"",BD29/BC29-1) | BE118: =if(BD29=0,"",BE29/BD29-1) -> -0.03919758 | BF118: =if(BE29=0,"",BF29/BE29-1) -> -0.16749643 | BG118: =if(BF29=0,"",BG29/BF29-1) -> -0.57210025 | BI118: =if(BH29=0,"",BI29/BH29-1) | BJ118: =if(BI29=0,"",BJ29/BI29-1) -> -0.25896723 | BK118: =if(BJ29=0,"",BK29/BJ29-1) -> -0.032808498 | BM118: =if(BL29=0,"",BM29/BL29-1) | BN118: =if(BM29=0,"",BN29/BM29-1) -> 0.061712376 | BO118: =if(BN29=0,"",BO29/BN29-1) -> -0.18479089 | BQ118: =if(BP29=0,"",BQ29/BP29-1) | BR118: =if(BQ29=0,"",BR29/BQ29-1) -> 3.5039193 | BT118: =if(BS29=0,"",BT29/BS29-1) | BU118: =if(BT29=0,"",BU29/BT29-1) -> -0.71501162 | BV118: =if(BU29=0,"",BV29/BU29-1) -> 2.8131421
A119: Capital de Trabajo | E119: =if(D30=0,"",E30/D30-1) -> -0.26809928 | F119: =if(E30=0,"",F30/E30-1) -> -0.23635974 | G119: =if(F30=0,"",G30/F30-1) -> -0.96820746 | H119: =if(G30=0,"",H30/G30-1) -> 35.585019 | K119: =if(J30=0,"",K30/J30-1) -> -0.11029025 | L119: =if(K30=0,"",L30/K30-1) -> 0.45705972 | M119: =if(L30=0,"",M30/L30-1) -> 0.11036491 | N119: =if(M30=0,"",N30/M30-1) -> -0.38584092 | Q119: =if(P30=0,"",Q30/P30-1) -> -0.93633714 | R119: =if(Q30=0,"",R30/Q30-1) -> 1.0197688 | S119: =if(R30=0,"",S30/R30-1) -> 0.17355014 | T119: =if(S30=0,"",T30/S30-1) -> -0.83806516 | V119: =if(U30=0,"",V30/U30-1) | W119: =if(V30=0,"",W30/V30-1) -> -1.7039676 | X119: =if(W30=0,"",X30/W30-1) -> 0.0018579093 | Y119: =if(X30=0,"",Y30/X30-1) -> -0.99609569 | AB119: =if(AA30=0,"",AB30/AA30-1) -> 7.1519417 | AC119: =if(AB30=0,"",AC30/AB30-1) -> -0.20830378 | AD119: =if(AC30=0,"",AD30/AC30-1) -> 0.46085074 | AF119: =if(AE30=0,"",AF30/AE30-1) | AH119: =if(AG30=0,"",AH30/AG30-1) -> 0.00011165604 | AJ119: =if(AI30=0,"",AJ30/AI30-1) | AM119: =if(AL30=0,"",AM30/AL30-1) | AN119: =if(AM30=0,"",AN30/AM30-1) -> 0.80478585 | AO119: =if(AN30=0,"",AO30/AN30-1) -> -0.28424779 | AQ119: =if(AP30=0,"",AQ30/AP30-1) | AR119: =if(AQ30=0,"",AR30/AQ30-1) -> 0.39058832 | AS119: =if(AR30=0,"",AS30/AR30-1) -> 0.014963707 | AU119: =if(AT30=0,"",AU30/AT30-1) | AV119: =if(AU30=0,"",AV30/AU30-1) -> -0.058533744 | AW119: =if(AV30=0,"",AW30/AV30-1) -> -0.07117415 | AY119: =if(AX30=0,"",AY30/AX30-1) | AZ119: =if(AY30=0,"",AZ30/AY30-1) -> 0.57643315 | BA119: =if(AZ30=0,"",BA30/AZ30-1) -> 0.26634426 | BB119: =if(BA30=0,"",BB30/BA30-1) -> 0.19307539 | BD119: =if(BC30=0,"",BD30/BC30-1) | BE119: =if(BD30=0,"",BE30/BD30-1) -> 0.027067808 | BF119: =if(BE30=0,"",BF30/BE30-1) -> -0.034693616 | BG119: =if(BF30=0,"",BG30/BF30-1) -> -0.2841043 | BI119: =if(BH30=0,"",BI30/BH30-1) | BJ119: =if(BI30=0,"",BJ30/BI30-1) -> -0.35563435 | BK119: =if(BJ30=0,"",BK30/BJ30-1) -> -0.01305433 | BM119: =if(BL30=0,"",BM30/BL30-1) | BN119: =if(BM30=0,"",BN30/BM30-1) -> 0.18502258 | BO119: =if(BN30=0,"",BO30/BN30-1) -> 0.36192901 | BQ119: =if(BP30=0,"",BQ30/BP30-1) | BR119: =if(BQ30=0,"",BR30/BQ30-1) -> 30.821695 | BT119: =if(BS30=0,"",BT30/BS30-1) | BU119: =if(BT30=0,"",BU30/BT30-1) -> -0.33083857 | BV119: =if(BU30=0,"",BV30/BU30-1) -> 3.6392259
E120: =if(D31=0,"",E31/D31-1) | F120: =if(E31=0,"",F31/E31-1) | G120: =if(F31=0,"",G31/F31-1) | H120: =if(G31=0,"",H31/G31-1) | K120: =if(J31=0,"",K31/J31-1) | L120: =if(K31=0,"",L31/K31-1) | M120: =if(L31=0,"",M31/L31-1) | N120: =if(M31=0,"",N31/M31-1) | Q120: =if(P31=0,"",Q31/P31-1) | R120: =if(Q31=0,"",R31/Q31-1) | S120: =if(R31=0,"",S31/R31-1) | T120: =if(S31=0,"",T31/S31-1) | V120: =if(U31=0,"",V31/U31-1) | W120: =if(V31=0,"",W31/V31-1) | X120: =if(W31=0,"",X31/W31-1) | Y120: =if(X31=0,"",Y31/X31-1) | AB120: =if(AA31=0,"",AB31/AA31-1) | AC120: =if(AB31=0,"",AC31/AB31-1) | AD120: =if(AC31=0,"",AD31/AC31-1) | AF120: =if(AE31=0,"",AF31/AE31-1) | AH120: =if(AG31=0,"",AH31/AG31-1) | AJ120: =if(AI31=0,"",AJ31/AI31-1) | AM120: =if(AL31=0,"",AM31/AL31-1) | AN120: =if(AM31=0,"",AN31/AM31-1) | AO120: =if(AN31=0,"",AO31/AN31-1) | AQ120: =if(AP31=0,"",AQ31/AP31-1) | AR120: =if(AQ31=0,"",AR31/AQ31-1) | AS120: =if(AR31=0,"",AS31/AR31-1) | AU120: =if(AT31=0,"",AU31/AT31-1) | AV120: =if(AU31=0,"",AV31/AU31-1) | AW120: =if(AV31=0,"",AW31/AV31-1) | AY120: =if(AX31=0,"",AY31/AX31-1) | AZ120: =if(AY31=0,"",AZ31/AY31-1) | BA120: =if(AZ31=0,"",BA31/AZ31-1) | BB120: =if(BA31=0,"",BB31/BA31-1) | BD120: =if(BC31=0,"",BD31/BC31-1) | BE120: =if(BD31=0,"",BE31/BD31-1) | BF120: =if(BE31=0,"",BF31/BE31-1) | BG120: =if(BF31=0,"",BG31/BF31-1) | BI120: =if(BH31=0,"",BI31/BH31-1) | BJ120: =if(BI31=0,"",BJ31/BI31-1) | BK120: =if(BJ31=0,"",BK31/BJ31-1) | BM120: =if(BL31=0,"",BM31/BL31-1) | BN120: =if(BM31=0,"",BN31/BM31-1) | BO120: =if(BN31=0,"",BO31/BN31-1) | BQ120: =if(BP31=0,"",BQ31/BP31-1) | BR120: =if(BQ31=0,"",BR31/BQ31-1) | BT120: =if(BS31=0,"",BT31/BS31-1) | BU120: =if(BT31=0,"",BU31/BT31-1) | BV120: =if(BU31=0,"",BV31/BU31-1)
A121: Período promedio de cobro (días) | E121: =if(D32=0,"",E32/D32-1) -> -0.27138393 | F121: =if(E32=0,"",F32/E32-1) -> 0.39237381 | G121: =if(F32=0,"",G32/F32-1) -> 0.0091445105 | H121: =if(G32=0,"",H32/G32-1) -> -0.13839962 | K121: =if(J32=0,"",K32/J32-1) -> -0.06509086 | L121: =if(K32=0,"",L32/K32-1) -> 1.0380308 | M121: =if(L32=0,"",M32/L32-1) -> 0.0014540612 | N121: =if(M32=0,"",N32/M32-1) -> -0.24133311 | Q121: =if(P32=0,"",Q32/P32-1) -> -0.95437506 | R121: =if(Q32=0,"",R32/Q32-1) -> 0.0569265 | S121: =if(R32=0,"",S32/R32-1) -> 0.070877977 | T121: =if(S32=0,"",T32/S32-1) -> 0.23050024 | V121: =if(U32=0,"",V32/U32-1) | W121: =if(V32=0,"",W32/V32-1) -> -0.34370513 | X121: =if(W32=0,"",X32/W32-1) -> 0.85571733 | Y121: =if(X32=0,"",Y32/X32-1) -> -0.59328446 | AB121: =if(AA32=0,"",AB32/AA32-1) | AC121: =if(AB32=0,"",AC32/AB32-1) -> -0.27114979 | AD121: =if(AC32=0,"",AD32/AC32-1) -> 0.19731197 | AF121: =if(AE32=0,"",AF32/AE32-1) | AH121: =if(AG32=0,"",AH32/AG32-1) -> 0.039560984 | AJ121: =if(AI32=0,"",AJ32/AI32-1) | AM121: =if(AL32=0,"",AM32/AL32-1) | AN121: =if(AM32=0,"",AN32/AM32-1) -> 0.32642375 | AO121: =if(AN32=0,"",AO32/AN32-1) -> -0.18085967 | AQ121: =if(AP32=0,"",AQ32/AP32-1) | AR121: =if(AQ32=0,"",AR32/AQ32-1) -> 0.50298351 | AS121: =if(AR32=0,"",AS32/AR32-1) -> -0.16507513 | AU121: =if(AT32=0,"",AU32/AT32-1) | AV121: =if(AU32=0,"",AV32/AU32-1) -> -0.23579474 | AW121: =if(AV32=0,"",AW32/AV32-1) -> -0.13163696 | AY121: =if(AX32=0,"",AY32/AX32-1) | AZ121: =if(AY32=0,"",AZ32/AY32-1) -> 3.9058885 | BA121: =if(AZ32=0,"",BA32/AZ32-1) -> -0.68986466 | BB121: =if(BA32=0,"",BB32/BA32-1) -> -0.52941027 | BD121: =if(BC32=0,"",BD32/BC32-1) | BE121: =if(BD32=0,"",BE32/BD32-1) -> -0.045874844 | BF121: =if(BE32=0,"",BF32/BE32-1) -> 0.27922692 | BG121: =if(BF32=0,"",BG32/BF32-1) -> 0.25099037 | BI121: =if(BH32=0,"",BI32/BH32-1) | BJ121: =if(BI32=0,"",BJ32/BI32-1) -> 0.0092736013 | BK121: =if(BJ32=0,"",BK32/BJ32-1) -> 0.035271855 | BM121: =if(BL32=0,"",BM32/BL32-1) | BN121: =if(BM32=0,"",BN32/BM32-1) -> -0.14570475 | BO121: =if(BN32=0,"",BO32/BN32-1) -> -0.030877546 | BQ121: =if(BP32=0,"",BQ32/BP32-1) | BR121: =if(BQ32=0,"",BR32/BQ32-1) -> 19.50832 | BT121: =if(BS32=0,"",BT32/BS32-1) | BU121: =if(BT32=0,"",BU32/BT32-1) -> -0.55642199 | BV121: =if(BU32=0,"",BV32/BU32-1) -> 6.2047296
A122: Rotación promedio de inventario (días) | E122: =if(D33=0,"",E33/D33-1) | F122: =if(E33=0,"",F33/E33-1) | G122: =if(F33=0,"",G33/F33-1) | H122: =if(G33=0,"",H33/G33-1) | K122: =if(J33=0,"",K33/J33-1) -> -0.33553478 | L122: =if(K33=0,"",L33/K33-1) -> -0.29795456 | M122: =if(L33=0,"",M33/L33-1) -> 0.11811369 | N122: =if(M33=0,"",N33/M33-1) -> 0.57241746 | Q122: =if(P33=0,"",Q33/P33-1) -> -0.88434155 | R122: =if(Q33=0,"",R33/Q33-1) -> -0.17316823 | S122: =if(R33=0,"",S33/R33-1) -> 0.28363224 | T122: =if(S33=0,"",T33/S33-1) -> -0.064608788 | V122: =if(U33=0,"",V33/U33-1) | W122: =if(V33=0,"",W33/V33-1) -> -0.1226544 | X122: =if(W33=0,"",X33/W33-1) -> -0.078758499 | Y122: =if(X33=0,"",Y33/X33-1) -> 0.037136653 | AB122: =if(AA33=0,"",AB33/AA33-1) | AC122: =if(AB33=0,"",AC33/AB33-1) -> -0.19032941 | AD122: =if(AC33=0,"",AD33/AC33-1) -> -0.003555141 | AF122: =if(AE33=0,"",AF33/AE33-1) | AH122: =if(AG33=0,"",AH33/AG33-1) | AJ122: =if(AI33=0,"",AJ33/AI33-1) | AM122: =if(AL33=0,"",AM33/AL33-1) | AN122: =if(AM33=0,"",AN33/AM33-1) -> -0.0891731 | AO122: =if(AN33=0,"",AO33/AN33-1) -> 0.088772017 | AQ122: =if(AP33=0,"",AQ33/AP33-1) | AR122: =if(AQ33=0,"",AR33/AQ33-1) -> 0.44568649 | AS122: =if(AR33=0,"",AS33/AR33-1) -> -0.12815648 | AU122: =if(AT33=0,"",AU33/AT33-1) | AV122: =if(AU33=0,"",AV33/AU33-1) | AW122: =if(AV33=0,"",AW33/AV33-1) | AY122: =if(AX33=0,"",AY33/AX33-1) | AZ122: =if(AY33=0,"",AZ33/AY33-1) -> 0.70639954 | BA122: =if(AZ33=0,"",BA33/AZ33-1) -> -0.69521413 | BB122: =if(BA33=0,"",BB33/BA33-1) -> 0.018699193 | BD122: =if(BC33=0,"",BD33/BC33-1) | BE122: =if(BD33=0,"",BE33/BD33-1) -> -0.11480166 | BF122: =if(BE33=0,"",BF33/BE33-1) -> 0.066516783 | BG122: =if(BF33=0,"",BG33/BF33-1) -> 0.59504272 | BI122: =if(BH33=0,"",BI33/BH33-1) | BJ122: =if(BI33=0,"",BJ33/BI33-1) -> 0.13355227 | BK122: =if(BJ33=0,"",BK33/BJ33-1) -> 0.094254041 | BM122: =if(BL33=0,"",BM33/BL33-1) | BN122: =if(BM33=0,"",BN33/BM33-1) -> 0.27231708 | BO122: =if(BN33=0,"",BO33/BN33-1) -> 6.1558389 | BQ122: =if(BP33=0,"",BQ33/BP33-1) | BR122: =if(BQ33=0,"",BR33/BQ33-1) -> 3.7643145 | BT122: =if(BS33=0,"",BT33/BS33-1) | BU122: =if(BT33=0,"",BU33/BT33-1) -> 0.61271113 | BV122: =if(BU33=0,"",BV33/BU33-1) -> 0.34983979
A123: Período promedio de pago (días) | E123: =if(D34=0,"",E34/D34-1) | F123: =if(E34=0,"",F34/E34-1) | G123: =if(F34=0,"",G34/F34-1) | H123: =if(G34=0,"",H34/G34-1) | K123: =if(J34=0,"",K34/J34-1) -> 0.60731868 | L123: =if(K34=0,"",L34/K34-1) -> -0.2180524 | M123: =if(L34=0,"",M34/L34-1) -> -0.022316745 | N123: =if(M34=0,"",N34/M34-1) -> 0.22743127 | Q123: =if(P34=0,"",Q34/P34-1) -> -0.94584368 | R123: =if(Q34=0,"",R34/Q34-1) -> -0.16464469 | S123: =if(R34=0,"",S34/R34-1) -> 0.090142428 | T123: =if(S34=0,"",T34/S34-1) -> 1.0553561 | V123: =if(U34=0,"",V34/U34-1) | W123: =if(V34=0,"",W34/V34-1) | X123: =if(W34=0,"",X34/W34-1) | Y123: =if(X34=0,"",Y34/X34-1) | AB123: =if(AA34=0,"",AB34/AA34-1) | AC123: =if(AB34=0,"",AC34/AB34-1) -> -0.0057366648 | AD123: =if(AC34=0,"",AD34/AC34-1) -> 0.36652725 | AF123: =if(AE34=0,"",AF34/AE34-1) | AH123: =if(AG34=0,"",AH34/AG34-1) | AJ123: =if(AI34=0,"",AJ34/AI34-1) | AM123: =if(AL34=0,"",AM34/AL34-1) | AN123: =if(AM34=0,"",AN34/AM34-1) | AO123: =if(AN34=0,"",AO34/AN34-1) | AQ123: =if(AP34=0,"",AQ34/AP34-1) | AR123: =if(AQ34=0,"",AR34/AQ34-1) -> -0.32319748 | AS123: =if(AR34=0,"",AS34/AR34-1) -> -0.93097057 | AU123: =if(AT34=0,"",AU34/AT34-1) | AV123: =if(AU34=0,"",AV34/AU34-1) | AW123: =if(AV34=0,"",AW34/AV34-1) | AY123: =if(AX34=0,"",AY34/AX34-1) | AZ123: =if(AY34=0,"",AZ34/AY34-1) -> 12.76331 | BA123: =if(AZ34=0,"",BA34/AZ34-1) -> -0.98931608 | BB123: =if(BA34=0,"",BB34/BA34-1) -> -0.48771789 | BD123: =if(BC34=0,"",BD34/BC34-1) | BE123: =if(BD34=0,"",BE34/BD34-1) -> -0.86132816 | BF123: =if(BE34=0,"",BF34/BE34-1) -> 7.911829 | BG123: =if(BF34=0,"",BG34/BF34-1) -> -0.30413704 | BI123: =if(BH34=0,"",BI34/BH34-1) | BJ123: =if(BI34=0,"",BJ34/BI34-1) -> -0.063089306 | BK123: =if(BJ34=0,"",BK34/BJ34-1) -> 0.42045528 | BM123: =if(BL34=0,"",BM34/BL34-1) | BN123: =if(BM34=0,"",BN34/BM34-1) -> -0.19651841 | BO123: =if(BN34=0,"",BO34/BN34-1) -> 0.070011545 | BQ123: =if(BP34=0,"",BQ34/BP34-1) | BR123: =if(BQ34=0,"",BR34/BQ34-1) -> -0.79647272 | BT123: =if(BS34=0,"",BT34/BS34-1) | BU123: =if(BT34=0,"",BU34/BT34-1) | BV123: =if(BU34=0,"",BV34/BU34-1) -> -0.78127963
E124: =if(D35=0,"",E35/D35-1) | F124: =if(E35=0,"",F35/E35-1) | G124: =if(F35=0,"",G35/F35-1) | H124: =if(G35=0,"",H35/G35-1) | K124: =if(J35=0,"",K35/J35-1) | L124: =if(K35=0,"",L35/K35-1) | M124: =if(L35=0,"",M35/L35-1) | N124: =if(M35=0,"",N35/M35-1) | Q124: =if(P35=0,"",Q35/P35-1) | R124: =if(Q35=0,"",R35/Q35-1) | S124: =if(R35=0,"",S35/R35-1) | T124: =if(S35=0,"",T35/S35-1) | V124: =if(U35=0,"",V35/U35-1) | W124: =if(V35=0,"",W35/V35-1) | X124: =if(W35=0,"",X35/W35-1) | Y124: =if(X35=0,"",Y35/X35-1) | AB124: =if(AA35=0,"",AB35/AA35-1) | AC124: =if(AB35=0,"",AC35/AB35-1) | AD124: =if(AC35=0,"",AD35/AC35-1) | AF124: =if(AE35=0,"",AF35/AE35-1) | AH124: =if(AG35=0,"",AH35/AG35-1) | AJ124: =if(AI35=0,"",AJ35/AI35-1) | AM124: =if(AL35=0,"",AM35/AL35-1) | AN124: =if(AM35=0,"",AN35/AM35-1) | AO124: =if(AN35=0,"",AO35/AN35-1) | AQ124: =if(AP35=0,"",AQ35/AP35-1) | AR124: =if(AQ35=0,"",AR35/AQ35-1) | AS124: =if(AR35=0,"",AS35/AR35-1) | AU124: =if(AT35=0,"",AU35/AT35-1) | AV124: =if(AU35=0,"",AV35/AU35-1) | AW124: =if(AV35=0,"",AW35/AV35-1) | AY124: =if(AX35=0,"",AY35/AX35-1) | AZ124: =if(AY35=0,"",AZ35/AY35-1) | BA124: =if(AZ35=0,"",BA35/AZ35-1) | BB124: =if(BA35=0,"",BB35/BA35-1) | BD124: =if(BC35=0,"",BD35/BC35-1) | BE124: =if(BD35=0,"",BE35/BD35-1) | BF124: =if(BE35=0,"",BF35/BE35-1) | BG124: =if(BF35=0,"",BG35/BF35-1) | BI124: =if(BH35=0,"",BI35/BH35-1) | BJ124: =if(BI35=0,"",BJ35/BI35-1) | BK124: =if(BJ35=0,"",BK35/BJ35-1) | BM124: =if(BL35=0,"",BM35/BL35-1) | BN124: =if(BM35=0,"",BN35/BM35-1) | BO124: =if(BN35=0,"",BO35/BN35-1) | BQ124: =if(BP35=0,"",BQ35/BP35-1) | BR124: =if(BQ35=0,"",BR35/BQ35-1) | BT124: =if(BS35=0,"",BT35/BS35-1) | BU124: =if(BT35=0,"",BU35/BT35-1) | BV124: =if(BU35=0,"",BV35/BU35-1)
A125: Ciclo de Caja en Días | E125: =if(D36=0,"",E36/D36-1) -> -0.27138645 | F125: =if(E36=0,"",F36/E36-1) -> 0.39237315 | G125: =if(F36=0,"",G36/F36-1) -> 0.0091445105 | H125: =if(G36=0,"",H36/G36-1) -> -0.17090453 | K125: =if(J36=0,"",K36/J36-1) -> -0.31774901 | L125: =if(K36=0,"",L36/K36-1) -> 0.69441309 | M125: =if(L36=0,"",M36/L36-1) -> 0.03259535 | N125: =if(M36=0,"",N36/M36-1) -> -0.10152553 | Q125: =if(P36=0,"",Q36/P36-1) -> -0.90291314 | R125: =if(Q36=0,"",R36/Q36-1) -> -0.050432873 | S125: =if(R36=0,"",S36/R36-1) -> 0.25122287 | T125: =if(S36=0,"",T36/S36-1) -> -0.40790613 | V125: =if(U36=0,"",V36/U36-1) | W125: =if(V36=0,"",W36/V36-1) -> -0.29048122 | X125: =if(W36=0,"",X36/W36-1) -> 0.57749648 | Y125: =if(X36=0,"",Y36/X36-1) -> -0.56628086 | AB125: =if(AA36=0,"",AB36/AA36-1) | AC125: =if(AB36=0,"",AC36/AB36-1) -> -0.29589353 | AD125: =if(AC36=0,"",AD36/AC36-1) -> 0.035978243 | AF125: =if(AE36=0,"",AF36/AE36-1) | AH125: =if(AG36=0,"",AH36/AG36-1) | AJ125: =if(AI36=0,"",AJ36/AI36-1) | AM125: =if(AL36=0,"",AM36/AL36-1) | AN125: =if(AM36=0,"",AN36/AM36-1) -> 0.13806039 | AO125: =if(AN36=0,"",AO36/AN36-1) -> -0.083053632 | AQ125: =if(AP36=0,"",AQ36/AP36-1) | AR125: =if(AQ36=0,"",AR36/AQ36-1) -> 0.6255161 | AS125: =if(AR36=0,"",AS36/AR36-1) -> -0.084336286 | AU125: =if(AT36=0,"",AU36/AT36-1) | AV125: =if(AU36=0,"",AV36/AU36-1) -> -0.23579474 | AW125: =if(AV36=0,"",AW36/AV36-1) -> -0.13163696 | AY125: =if(AX36=0,"",AY36/AX36-1) | AZ125: =if(AY36=0,"",AZ36/AY36-1) -> 1.3668257 | BA125: =if(AZ36=0,"",BA36/AZ36-1) -> -0.38751189 | BB125: =if(BA36=0,"",BB36/BA36-1) -> -0.46899239 | BD125: =if(BC36=0,"",BD36/BC36-1) | BE125: =if(BD36=0,"",BE36/BD36-1) -> -0.095718845 | BF125: =if(BE36=0,"",BF36/BE36-1) -> 0.079885574 | BG125: =if(BF36=0,"",BG36/BF36-1) -> 0.55376316 | BI125: =if(BH36=0,"",BI36/BH36-1) | BJ125: =if(BI36=0,"",BJ36/BI36-1) -> 0.27855337 | BK125: =if(BJ36=0,"",BK36/BJ36-1) -> -0.43206921 | BM125: =if(BL36=0,"",BM36/BL36-1) | BN125: =if(BM36=0,"",BN36/BM36-1) -> -0.12327383 | BO125: =if(BN36=0,"",BO36/BN36-1) -> 0.2984795 | BQ125: =if(BP36=0,"",BQ36/BP36-1) | BR125: =if(BQ36=0,"",BR36/BQ36-1) -> -16.713741 | BT125: =if(BS36=0,"",BT36/BS36-1) | BU125: =if(BT36=0,"",BU36/BT36-1) -> 0.16167473 | BV125: =if(BU36=0,"",BV36/BU36-1) -> 0.81414899
...

Sheet Altman
B2: Tabla Resumida de Rangos de Interpretación | H2: Coeficientes
E3: Bajo Riesgo | F3: Riesgo Moderado | G3: Alto Riesgo | H3: a1 | I3: a2 | J3: a3 | K3: a4 | L3: a5
A4: 1 | B4: Altman Original (1968) – Manufactureras Públicas | C4: 1.81 | D4: 2.99 | E4: Z ≥ 2.99 | F4: 1.81 ≤ Z < 2.99 | G4: Z < 1.81 | H4: 1.2 | I4: 1.4 | J4: 3.3 | K4: 0.6 | L4: 1 | S4: Altman original (1968), empresas manufactureras públicas
A5: 2 | B5: Altman Revisado (1983) – Manufactureras Privadas | C5: 1.23 | D5: 2.9 | E5: Z ≥ 2.90 | F5: 1.23 ≤ Z < 2.90 | G5: Z < 1.23 | H5: 0.717 | I5: 0.847 | J5: 3.107 | K5: 0.42 | L5: 0.998 | S5: Altman revisado (1983), empresas manufactureras privadas
A6: 3 | B6: Z'' para No Manufactureras y Mercados Emergentes | C6: 1.23 | D6: 2.9 | E6: Z ≥ 2.90 | F6: 1.23 ≤ Z < 2.90 | G6: Z < 1.23 | H6: 6.56 | I6: 3.26 | J6: 6.72 | K6: 1.05 | L6: 0 | S6: Altman Z'' para no manufactureras y mercados emergentes (sin ventas/activos)
A7: 4 | B7: Altman Modificado (Ventas Ajustadas) | C7: 1.81 | D7: 2.99 | E7: Z ≥ 2.99 | F7: 1.81 ≤ Z < 2.99 | G7: Z < 1.81 | H7: 1.2 | I7: 1.4 | J7: 3.3 | K7: 0.6 | L7: 0.99 | S7: Altman modificado, empresas públicas (coeficiente de ventas ajustado)
A8: 5 | B8: Z’-Score Revisado para PYMES de Europa Central y Este | C8: 1.23 | D8: 2.9 | E8: Z ≥ 2.90 | F8: 1.23 ≤ Z < 2.90 | G8: Z < 1.23 | H8: 0.717 | I8: 0.847 | J8: 3.107 | K8: 0.42 | L8: 0.998 | S8: Z’-Score revisado, probado en pymes de Europa Central y del Este
A9: 6 | B9: Z''-Score Mercados Emergentes (con constante) | C9: 1.1 | D9: 2.6 | E9: Z ≥ 2.60 | F9: 1.10 ≤ Z < 2.60 | G9: Z < 1.10 | H9: 6.56 | I9: 3.26 | J9: 6.72 | K9: 1.05 | L9: 0 | S9: Z''-Score para mercados emergentes, con constante +3.25
A10: 7 | B10: Pesos Iguales (Propuesta Experimental) | C10: 1.81 | D10: 2.99 | E10: Z ≥ 2.99 | F10: 1.81 ≤ Z < 2.99 | G10: Z < 1.81 | H10: 1 | I10: 1 | J10: 1 | K10: 1 | L10: 1 | S10: Propuesta experimental: pesos iguales para análisis exploratorio
A11: 8 | B11: Ajuste para Empresas Medianas Latinoamericanas | C11: 1.23 | D11: 2.9 | E11: Z ≥ 2.90 | F11: 1.23 ≤ Z < 2.90 | G11: Z < 1.23 | H11: 1.5 | I11: 1 | J11: 2.5 | K11: 0.5 | L11: 1 | S11: Experiencia práctica: ajuste para empresas medianas latinoamericanas (literatura y consultoría)
A14: 1 | B14: 1. Altman Original (1968) – Empresas Manufactureras Públicas
B15: Z < 1.81: Zona de peligro (alto riesgo de quiebra)
B16: 1.81 ≤ Z < 2.99: Zona gris (riesgo moderado)
B17: Z ≥ 2.99: Zona segura (bajo riesgo de quiebra)
A19: 2 | B19: 2. Altman Revisado (1983) – Manufactureras Privadas
B20: Z < 1.23: Zona de peligro (alto riesgo)
B21: 1.23 ≤ Z < 2.90: Zona gris (riesgo moderado)
B22: Z ≥ 2.90: Zona segura (bajo riesgo)
A24: 3 | B24: 3. Z'' para No Manufactureras y Mercados Emergentes
B25: Z < 1.23: Zona de peligro (alto riesgo)
B26: 1.23 ≤ Z < 2.90: Zona gris (riesgo moderado)
B27: Z ≥ 2.90: Zona segura (bajo riesgo)
A29: 4 | B29: 4. Altman Modificado (Ventas Ajustadas)
B30: Z < 1.81: Alto riesgo
B31: 1.81 ≤ Z < 2.99: Riesgo moderado
B32: Z ≥ 2.99: Bajo riesgo
A34: 5 | B34: 5. Z’-Score Revisado para PYMES de Europa Central y del Este
B35: Z < 1.23: Alto riesgo
B36: 1.23 ≤ Z < 2.90: Riesgo moderado
B37: Z ≥ 2.90: Bajo riesgo
A39: 6 | B39: 6. Z''-Score para Mercados Emergentes (con constante)
B40: Z < 1.10: Zona de peligro (alto riesgo)
B41: 1.10 ≤ Z < 2.60: Zona gris (riesgo moderado)
B42: Z ≥ 2.60: Zona segura (bajo riesgo)
A44: 7 | B44: 7. Pesos Iguales (Propuesta Experimental)
B45: Coeficientes: 1.0, 1.0, 1.0, 1.0, 1.0
B46: Z < 1.81: Alto riesgo
B47: 1.81 ≤ Z < 2.99: Riesgo moderado
B48: Z ≥ 2.99: Bajo riesgo
B50: 8. Ajuste para Empresas Medianas Latinoamericanas
B51: Z < 1.23: Alto riesgo
B52: 1.23 ≤ Z < 2.90: Riesgo moderado
B53: Z ≥ 2.90: Bajo riesgo

Sheet Caratula_V2
B1: LU3-American Medical Enterprises v3.xlsx | I1: LU4-Novoswiss PFJuridica v3.xlsx | O1: LU2-Luminova PFJuridica v3.xlsx | T1: LU1-Helvetia PFJuridica v3.xlsx | Y1: ETI-Corp Etisa 2025 vf.xlsx
A2: LU3-American Medical Enterprises v3.xlsx | B2: 2020 | C2: 2021 | D2: 2022 | E2: 2023 | F2: 2024 | H2: 2020 | I2: 2021 | J2: 2022 | K2: 2023 | L2: 2024 | N2: 2020 | O2: 2021 | P2: 2022 | Q2: 2023 | R2: 2024 | T2: 2021 | U2: 2022 | V2: 2023 | W2: 2024 | Y2: 2021 | Z2: 2022 | AA2: 2023 | AB2: 2024
B3: Auditado | C3: Auditado | D3: Auditado | E3: Auditado | F3: Admin. | H3: Auditado | I3: Auditado | J3: Auditado | K3: Auditado | L3: Admin. | N3: Auditado | O3: Auditado | P3: Auditado | Q3: Admin. | R3: Admin. | T3: Auditado | U3: Auditado | V3: Auditado | W3: Admin. | Y3: Pendiente | Z3: Auditado | AA3: Auditado | AB3: Admin.
A5: NOMBRE DEL CLIENTE: American Medical Enterprises, Inc.
A6: GIRO DEL NEGOCIO:
A7: EN MILES DE: DÓLARES
A8: AUDITOR O CONTADOR ACTIVO: Axel Samuel Rosas
A10: Ventas | B10: 23930.151 | C10: 23578.78 | D10: 29792.243 | E10: 32768.103 | F10: 24145.584 | H10: 337466 | I10: 330048 | J10: 360978.12 | K10: 419772.2 | L10: 312105.95 | N10: 4317 | O10: 70441.169 | P10: 103822.19 | Q10: 109585.88 | R10: 75793.976 | T10: 20425.762 | U10: 33740.045 | V10: 42955.437 | W10: 33868.198 | Y10: 0 | Z10: 39281.699 | AA10: 52097.658 | AB10: 54416.681
A11: Utilidad Neta | B11: 14418.686 | C11: 2893.883 | D11: 5234.476 | E11: 6219.504 | F11: 3790.438 | H11: 19435 | I11: 21414 | J11: 16122.97 | K11: 7214.951 | L11: 2151.953 | N11: -2996 | O11: 1275.956 | P11: 2586.204 | Q11: 4571.311 | R11: -2835.862 | T11: -35.504 | U11: -2708.358 | V11: 711.661 | W11: 1111.626 | Y11: 0 | Z11: 1160.272 | AA11: 887.238 | AB11: 2968.52
A14: Activo Corriente | B14: 21443.876 | C14: 16147.77 | D14: 27257.998 | E14: 30188.632 | F14: 28923.839 | H14: 489171 | I14: 559173 | J14: 658388.66 | K14: 747714.18 | L14: 731542.08 | N14: 156739.98 | O14: 50343.569 | P14: 69251.927 | Q14: 80296.962 | R14: 89011.252 | T14: 17118.68 | U14: 22603.33 | V14: 41829.318 | W14: 22008.315 | Y14: 4149 | Z14: 55862.546 | AA14: 47567.44 | AB14: 53771.717
A15: Activo No Corriente | B15: 0 | C15: 0 | D15: 0 | E15: 0 | F15: 0 | H15: 117278.28 | I15: 105337 | J15: 183901.7 | K15: 221052.02 | L15: 95615.306 | N15: 25948 | O15: 26300.778 | P15: 23715.271 | Q15: 28567.047 | R15: 29221.778 | T15: 45079.636 | U15: 2661.033 | V15: 3208.322 | W15: 5083.783 | Y15: 0 | Z15: 11951.704 | AA15: 10657.175 | AB15: 10971.355
A16: Activo Diferido | B16: 43854.634 | C16: 47511.01 | D16: 43317.688 | E16: 51328.915 | F16: 73222.413 | H16: 316380 | I16: 332106 | J16: 269491.19 | K16: 282184.37 | L16: 442297.11 | N16: 34413 | O16: 162778.8 | P16: 148720.9 | Q16: 154873.23 | R16: 168630.21 | T16: 0 | U16: 0 | V16: 0 | W16: 31265.551 | Y16: 0 | Z16: 11319.385 | AA16: 20216.327 | AB16: 14995.304
A17: Total de Activo | B17: 65298.51 | C17: 63658.78 | D17: 70575.686 | E17: 81517.547 | F17: 102146.25 | H17: 922829.28 | I17: 996616 | J17: 1111781.5 | K17: 1250950.6 | L17: 1269454.5 | N17: 217100.98 | O17: 239423.14 | P17: 241688.1 | Q17: 263737.24 | R17: 286863.24 | T17: 62198.316 | U17: 25264.363 | V17: 45037.64 | W17: 58357.649 | Y17: 4149 | Z17: 79133.635 | AA17: 78440.942 | AB17: 79738.376
A19: Pasivo Corriente | B19: 40792.936 | C19: 30309.361 | D19: 38072.359 | E19: 30532.448 | F19: 41502.354 | H19: 162415 | I19: 268455 | J19: 234795.17 | K19: 277370.83 | L19: 442676.45 | N19: 35006 | O19: 42593.636 | P19: 53598.854 | Q19: 61927.296 | R19: 86036.563 | T19: 40572.929 | U19: 6092.298 | V19: 25287.61 | W19: 21943.731 | Y19: 0 | Z19: 22040.14 | AA19: 20790.369 | AB19: 14654.413
A20: Pasivo No Corriente | B20: 10181.019 | C20: 16130.981 | D20: 10050.413 | E20: 22312.681 | F20: 21738.022 | H20: 310963 | I20: 257172 | J20: 351454.95 | K20: 411562.72 | L20: 315090.21 | N20: 45937 | O20: 58943.814 | P20: 48747.619 | Q20: 53904.635 | R20: 55329.341 | T20: 77.481 | U20: 331.962 | V20: 198.82 | W20: 15751.093 | Y20: 0 | Z20: 20186.765 | AA20: 19842.093 | AB20: 24459.709
A21: Total Pasivo | B21: 50973.955 | C21: 46440.342 | D21: 48122.772 | E21: 52845.129 | F21: 63240.376 | H21: 473378 | I21: 525627 | J21: 586250.12 | K21: 688933.55 | L21: 757766.65 | N21: 80943 | O21: 101537.45 | P21: 102346.47 | Q21: 115831.93 | R21: 141365.9 | T21: 40650.41 | U21: 6424.26 | V21: 25486.43 | W21: 37694.824 | Y21: 0 | Z21: 42226.905 | AA21: 40632.462 | AB21: 39114.122
A23: Capital | B23: 0.2 | C23: 0.2 | D23: 0.2 | E23: 0.2 | F23: 0.2 | H23: 114975 | I23: 114995 | J23: 114995 | K23: 114995 | L23: 114995 | N23: 128348 | O23: 128370.97 | P23: 128397.93 | Q23: 128397.93 | R23: 128414.01 | T23: 21388 | U23: 21388 | V23: 21388 | W23: 21388 | Y23: 0 | Z23: 20598 | AA23: 20598 | AB23: 20598
A24: Otros | B24: 0 | C24: 0 | D24: 0 | E24: 0 | F24: 0 | H24: 0 | I24: 0 | J24: -6800.427 | K24: 22470.203 | L24: 0 | N24: 6984 | O24: 7515.611 | P24: 1254.59 | Q24: 949.485 | R24: 3094.496 | T24: 0 | U24: 0 | V24: 0 | W24: 0 | Y24: 0 | Z24: 0 | AA24: 0 | AB24: 5439.5
A25: Reserva Legal | H25: 28309 | I25: 29652 | J25: 31064.837 | K25: 31778.92 | L25: 31778.92 | N25: 3668 | O25: 3835.227 | P25: 4086.595 | Q25: 4175.852 | R25: 4541.229 | T25: 71.441 | U25: 71.441 | V25: 119.549 | W25: 119.549 | Y25: 0 | Z25: 0 | AA25: 0 | AB25: 694.589
A26: Utilidades Retenidas | B26: 14324.555 | C26: 17218.238 | D26: 22452.714 | E26: 28672.218 | F26: 38905.676 | H26: 306165 | I26: 326342 | J26: 386272.01 | K26: 392772.88 | L26: 364913.92 | N26: -2843 | O26: -1836.117 | P26: 360.338 | Q26: 8745.705 | R26: -4538.771 | T26: 88.465 | U26: -2619.893 | V26: -1956.339 | W26: -844.713 | Y26: 0 | Z26: 16308.73 | AA26: 17210.48 | AB26: 13892.165
A27: Total Patrimonio | B27: 14324.755 | C27: 17218.438 | D27: 22452.914 | E27: 28672.418 | F27: 38905.876 | H27: 449449 | I27: 470989 | J27: 525531.42 | K27: 562017 | L27: 511687.84 | N27: 136157 | O27: 137885.69 | P27: 139341.63 | Q27: 147905.31 | R27: 145497.34 | T27: 21547.906 | U27: 18839.548 | V27: 19551.21 | W27: 20662.836 | Y27: 0 | Z27: 36906.73 | AA27: 37808.48 | AB27: 40624.254
A30: Liquidez | B30: 0.52567621 | C30: 0.53276511 | D30: 0.71595243 | E30: 0.98873932 | F30: 0.69692044 | H30: 3.0118585 | I30: 2.0829301 | J30: 2.804098 | K30: 2.6957203 | L30: 1.6525435 | N30: 4.4775176 | O30: 1.1819505 | P30: 1.2920412 | Q30: 1.2966328 | R30: 1.0345747 | T30: 0.42192369 | U30: 3.7101485 | V30: 1.6541428 | W30: 1.0029432 | Y30: 0 | Z30: 2.5345822 | AA30: 2.2879555 | AB30: 3.6693191
A31: Prueba Acida | B31: 0.52567489 | C31: 0.53276498 | D31: 0.71595243 | E31: 0.98873932 | F31: 0.69692044 | H31: 2.3167996 | I31: 1.7105176 | J31: 2.458597 | K31: 2.3510577 | L31: 1.3079216 | N31: 4.1072668 | O31: 0.83911521 | P31: 0.97149027 | Q31: 0.9002935 | R31: 0.79435734 | T31: 0.33612345 | U31: 2.8278118 | V31: 1.4480697 | W31: 0.76047747 | Y31: 0 | Z31: 1.9549913 | AA31: 1.6244756 | AB31: 2.729427
A32: Capital de Trabajo | B32: -19349.06 | C32: -14161.591 | D32: -10814.361 | E32: -343.816 | F32: -12578.515 | H32: 326756 | I32: 290718 | J32: 423593.49 | K32: 470343.34 | L32: 288865.64 | N32: 121733.98 | O32: 7749.933 | P32: 15653.073 | Q32: 18369.666 | R32: 2974.689 | T32: -23454.249 | U32: 16511.032 | V32: 16541.708 | W32: 64.584 | Y32: 4149 | Z32: 33822.406 | AA32: 26777.071 | AB32: 39117.304
A35: Período promedio de cobro (días) | B35: 319.0952 | C35: 232.49789 | D35: 323.72398 | E35: 326.68427 | F35: 281.4713 | H35: 256.00126 | I35: 239.33791 | J35: 487.77804 | K35: 488.48729 | L35: 370.59914 | N35: 2608.4781 | O35: 119.01166 | P35: 125.78658 | Q35: 134.70208 | R35: 165.75094 | T35: 215.46244 | U35: 141.40689 | V35: 262.41122 | W35: 106.72672 | Y35: 0 | Z35: 281.77593 | AA35: 205.37245 | AB35: 245.89489
A36: Rotación promedio de inventario (días) | B36: 0.0012572104 | C36: 0.00011149442 | D36: 0 | E36: 0 | F36: 0 | H36: 268.7454 | I36: 178.57197 | J36: 125.36564 | K36: 140.17304 | L36: 220.41053 | N36: 1903.6965 | O36: 220.17859 | P36: 182.05065 | Q36: 233.68608 | R36: 218.58791 | T36: 68.330869 | U36: 59.949788 | V36: 55.228232 | W36: 57.279224 | Y36: 0 | Z36: 166.4898 | AA36: 134.80189 | AB36: 134.32265
A37: Período promedio de pago (días) | B37: 0 | C37: 0 | D37: 0 | E37: 0 | F37: 10.618845 | H37: 64.753056 | I37: 104.0788 | J37: 81.384164 | K37: 79.567935 | L37: 97.664171 | N37: 2303.3161 | O37: 124.73911 | P37: 104.20148 | Q37: 113.59445 | R37: 233.47706 | T37: 0 | U37: 0 | V37: 0 | W37: 26.239633 | Y37: 0 | Z37: 84.600927 | AA37: 84.1156 | AB37: 114.94626
A40: Ciclo de Caja en Días | B40: 319.09646 | C40: 232.498 | D40: 323.72398 | E40: 326.68427 | F40: 270.85245 | H40: 459.9936 | I40: 313.83109 | J40: 531.75951 | K40: 549.0924 | L40: 493.3455 | N40: 2208.8585 | O40: 214.45114 | P40: 203.63575 | Q40: 254.79371 | R40: 150.86179 | T40: 283.79331 | U40: 201.35668 | V40: 317.63946 | W40: 137.76631 | Y40: 0 | Z40: 363.6648 | AA40: 256.05874 | AB40: 265.27128
A42: Apalancamiento | B42: 3.5584521 | C42: 2.6971286 | D42: 2.1432751 | E42: 1.843065 | F42: 1.6254711 | H42: 1.0532407 | I42: 1.116007 | J42: 1.1155377 | K42: 1.2258233 | L42: 1.4809159 | N42: 0.59448284 | O42: 0.73638858 | P42: 0.73450034 | Q42: 0.78314926 | R42: 0.97160473 | T42: 1.8865132 | U42: 0.34099863 | V42: 1.303573 | W42: 1.8242812 | Y42: 0 | Z42: 1.1441519 | AA42: 1.0746918 | AB42: 0.96282684
A43: Apalancamiento Bancario | B43: 0 | C43: 0 | D43: 0 | E43: 0 | F43: 0 | H43: 0.84349059 | I43: 0.7977405 | J43: 0.47713848 | K43: 0.51855977 | L43: 0.72933114 | N43: 0.30031508 | O43: 0.29135624 | P43: 0.21246742 | Q43: 0.25251266 | R43: 0.41340849 | T43: 0 | U43: 0 | V43: 0 | W43: 0 | Y43: 0 | Z43: 0.72252822 | AA43: 0.48523395 | AB43: 0.26793166
A44: Apalancamiento Comercial | B44: 3.5502475 | C44: 2.670022 | D44: 1.9462502 | E44: 1.5135245 | F44: 1.325428 | H44: 0.058175677 | I44: 0.065799838 | J44: 0.10266551 | K44: 0.12294651 | L44: 0.13944219 | N44: 0.051756428 | O44: 0.053049173 | P44: 0.068203244 | Q44: 0.052009655 | R44: 0.061848395 | T44: 1.8690515 | U44: 0.30945095 | V44: 1.246281 | W44: 1.4969901 | Y44: 0 | Z44: 0.022176606 | AA44: 0.057237927 | AB44: 0
A45: Crecimiento Anual en Ventas
A46: ROE | B46: 1.0065572 | C46: 0.16806885 | D46: 0.23313125 | E46: 0.21691592 | F46: 0.12990113 | H46: 0.043241836 | I46: 0.04546603 | J46: 0.030679364 | K46: 0.012837603 | L46: 0.005607463 | N46: -0.02200401 | O46: 0.0092537229 | P46: 0.018560168 | Q46: 0.030907011 | R46: -0.025987756 | T46: -0.0016476775 | U46: -0.14375918 | V46: 0.036399844 | W46: 0.071731102 | Y46: 0 | Z46: 0.031437952 | AA46: 0.02346664 | AB46: 0.073072603
A47: ROA | B47: 0.22081187 | C47: 0.045459291 | D47: 0.074168262 | E47: 0.076296506 | F47: 0.049477267 | H47: 0.021060233 | I47: 0.021486711 | J47: 0.014501923 | K47: 0.0057675749 | L47: 0.0022602391 | N47: -0.01380003 | O47: 0.0053292926 | P47: 0.010700585 | Q47: 0.017332824 | R47: -0.013181017 | T47: -0.00057081931 | U47: -0.10720072 | V47: 0.015801472 | W47: 0.025398007 | Y47: 0 | Z47: 0.014662185 | AA47: 0.011310904 | AB47: 0.037228248
A48: EBITDA | B48: 14418.686 | C48: 2893.883 | D48: 5234.476 | E48: 6219.504 | F48: 3790.438 | H48: 55422 | I48: 49227 | J48: 39552.463 | K48: 32077.02 | L48: 43794.466 | N48: -2481 | O48: 6022.187 | P48: 5992.457 | Q48: 8775.025 | R48: 6049.452 | T48: -35.504 | U48: -2708.358 | V48: 962.143 | W48: 1111.626 | Y48: 0 | Z48: 4038.452 | AA48: 5892.766 | AB48: 8517.153

Sheet Balance
K1: LU4-Novoswiss PFJuridica v3 | S1: LU2-Luminova PFJuridica v3 | Z1: LU1-Helvetia PFJuridica v3.xlsx | AG1: ETI-Corp Etisa 2025 vf.xlsx | AO1: Bahía Colorada | AU1: Soluciones Carnicas.xlsm | AZ1: Servicios y Percederos.xlsm | BF1: Quimica Total.xlsm | BL1: Logistica Nave.xlsm | BR1: Inv_Iginla | BY1: Ing_Palo_Gordo | CF1: Distrib_Me_Llega | CL1: Corinco | CR1: Inversiones Mapakhan, S.A. | CW1: CorpMogori
A2: LU3-American Medical Enterprises v3.xlsx | C2: 2020 | D2: 2021 | E2: 2022 | F2: 2023 | G2: 2024 | I2: LU4-Novoswiss PFJuridica v3.xlsx | K2: 2020 | L2: 2021 | M2: 2022 | N2: 2023 | O2: 2024 | Q2: LU2-Luminova PFJuridica v3.xlsx | S2: 2020 | T2: 2021 | U2: 2022 | V2: 2023 | W2: 2024 | Y2: LU1-Helvetia PFJuridica v3.xlsx | AA2: 2021 | AB2: 2022 | AC2: 2023 | AD2: 2024 | AF2: ETI-Corp Etisa 2025 vf.xlsx | AH2: 2021 | AI2: 2022 | AJ2: 2023 | AK2: 2024 | AM2: Bahía Colorada.xlsx | AO2: 2021 | AP2: 2022 | AQ2: 2023 | AS2: Soluciones Carnicas.xlsm | AU2: 2022 | AV2: 2023 | AX2: Servicios y Percederos.xlsm | AZ2: 2021 | BA2: 2022 | BB2: 2023 | BD2: Quimica Total.xlsm | BF2: 2022 | BG2: 2023 | BH2: 2024 | BJ2: Logistica Nave.xlsm | BL2: 2022 | BM2: 2023 | BN2: 2024 | BP2: Inv_Iginla.xlsm | BR2: 2020 | BS2: 2021 | BT2: 2022 | BU2: 2023 | BW2: Ing_Palo_Gordo.xlsx | BY2: 2021 | BZ2: 2022 | CA2: 2023 | CB2: 2024 | CD2: Distrib_Me_Llega.xlsx | CF2: 2022 | CG2: 2023 | CH2: 2024 | CJ2: Corinco.xlsx | CL2: 2021 | CM2: 2022 | CN2: 2023 | CP2: InvM.xlsx | CR2: 2021 | CS2: 2022 | CU2: CorpMogori.xlsx | CW2: 2021 | CX2: 2022 | CY2: 2023 | CZ2: 2024
A4: Meses considerados | C4: 12 | D4: 12 | E4: 12 | F4: 12 | G4: 9 | K4: 12 | L4: 12 | M4: 12 | N4: 12 | O4: 9 | S4: 12 | T4: 12 | U4: 12 | V4: 12 | W4: 9 | AA4: 12 | AB4: 12 | AC4: 12 | AD4: 9 | AH4: 12 | AI4: 12 | AJ4: 12 | AK4: 12 | AO4: 12 | AP4: 12 | AQ4: 6 | AU4: 12 | AV4: 8 | AZ4: 12 | BA4: 12 | BB4: 6 | BF4: 12 | BG4: 12 | BH4: 3 | BL4: 12 | BM4: 12 | BN4: 12 | BR4: 12 | BS4: 12 | BT4: 12 | BU4: 12 | BY4: 12 | BZ4: 12 | CA4: 12 | CB4: 12 | CF4: 12 | CG4: 12 | CH4: 12 | CL4: 12 | CM4: 12 | CN4: 12 | CR4: 12 | CS4: 12 | CW4: 12 | CX4: 12 | CY4: 12 | CZ4: 5
C5: Auditado | D5: Auditado | E5: Auditado | F5: Auditado | G5: Admin. | K5: Auditado | L5: Auditado | M5: Auditado | N5: Auditado | O5: Admin. | S5: Auditado | T5: Auditado | U5: Auditado | V5: Admin. | W5: Admin. | AA5: Auditado | AB5: Auditado | AC5: Auditado | AD5: Admin. | AH5: Pendiente | AI5: Auditado | AJ5: Auditado | AK5: Admin. | AO5: Auditado | AP5: Auditado | AQ5: Administrativo | AU5: Administrativo | AV5: Administrativo | AZ5: Auditado | BA5: Auditado | BB5: Administrativo | BF5: Administrativo | BG5: Administrativo | BH5: Administrativo | BL5: Auditado | BM5: Auditado | BN5: Administrativo | BR5: Auditado | BS5: Auditado | BT5: Auditado | BU5: Auditado | BY5: Auditado | BZ5: Auditado | CA5: Auditado | CB5: Administrativo | CF5: Auditado | CG5: Auditado | CH5: Administrativo | CL5: Administrativo | CM5: Administrativo | CN5: Administrativo | CR5: Administrativo | CS5: Administrativo | CW5: Administrativo | CX5: Administrativo | CY5: Administrativo | CZ5: Administrativo
C6: Deloitte | D6: Deloitte | E6: Deloitte | F6: Deloitte | G6: Axel Samuel Rosas | K6: Miguel Angel Imul Gracia | L6: Miguel Angel Imul Gracia | M6: Deloitte | N6: Deloitte | O6: Axel Rosas y Edgar Locón S. | S6: PWR | T6: Deloitte | U6: Deloitte | V6: Deloitte | W6: Axel Rosas (cpa) y Michael Erichsen R (rep) | AB6: Deloitte | AC6: Deloitte | AD6: Axel S. Rosas S. (cpa) y Humberto Gonzalez (rep) | AI6: Nuñez Bubón y Asociados | AJ6: Nuñez Bubón y Asociados | AK6: Mynor Armando Alacan Morales | AO6: Lic. Edwin R. Hernandez B. | AP6: Lic. Edwin R. Hernandez B. | AQ6: Maria Eliza Rodas Morales | AU6: Hugo Waldermar Sutuj Chamale | AV6: Hugo Waldermar Sutuj Chamale | AZ6: Jorge Eduardo Granillo Díaz | BA6: Jorge Eduardo Granillo Díaz | BB6: Lesly Mariela de León Ruiz | BF6: Jorge Eduardo Motta Morales | BG6: Jorge Eduardo Motta Morales | BH6: Jorge Eduardo Motta Morales | BL6: Nexia | BM6: Nexia | BN6: Edgar Culajay | BR6: Lic. Oscar Saul Rodríguez Lemus | BS6: Lic. Oscar Saul Rodríguez Lemus | BT6: Lic. Oscar Saul Rodríguez Lemus | BU6: Lic. Oscar Saul Rodríguez Lemus | BY6: PKF | BZ6: PKF | CA6: PKF | CB6: MARVIN ROBERTO CANO TEPEU | CF6: Nexia | CG6: Nexia | CH6: Edgar Estuardo Culajay Pirir | CL6: Miguel Miculax Olcot | CM6: Miguel Miculax Olcot | CN6: Miguel Miculax Olcot | CR6: Sergio Armando Mancilla López | CS6: Sergio Armando Mancilla López | CW6: Sergio Armando Mancilla López | CX6: Sergio Armando Mancilla López | CY6: Sergio Armando Mancilla López | CZ6: Sergio Armando Mancilla López
C7: NIA | D7: NIA | E7: NIIF | F7: NIA, NIIF | K7: ISR | L7: ISR | M7: NIA | N7: NIIF | O7: NIIF | S7: NIIF | T7: NIA | U7: NIIF | V7: NIIF | W7: NIIF | AA7: ISR | AB7: ISR | AC7: NIA | AI7: NIIF | AJ7: NIIF | AK7: NIIF | AN7: INTEGRACIONES | AO7: NIIF | AP7: NIIF | AQ7: NIIF | AT7: INTEGRACIONES | AU7: NIIF | AV7: NIIF | AY7: INTEGRACIONES | AZ7: NIIF | BA7: NIIF | BB7: NIIF | BE7: INTEGRACIONES | BF7: NIIF PARA PYMES | BG7: NIIF PARA PYMES | BH7: NIIF PARA PYMES | BK7: INTEGRACIONES | BL7: NIIF | BM7: NIIF | BN7: NIIF | BQ7: INTEGRACIONES | BR7: NIIF PARA PYMES | BS7: NIIF PARA PYMES | BT7: NIIF PARA PYMES | BU7: NIIF PARA PYMES | BX7: INTEGRACIONES | BY7: NIIF para PYMES | BZ7: NIIF para PYMES | CA7: NIIF para PYMES | CB7: NIIF para PYMES | CE7: INTEGRACIONES | CF7: NIA | CG7: NIA | CH7: ISR | CK7: INTEGRACIONES | CL7: ISR | CM7: ISR | CN7: ISR | CQ7: INTEGRACIONES | CR7: Internos | CS7: Internos | CV7: INTEGRACIONES | CW7: ISR | CX7: ISR | CY7: ISR | CZ7: ISR
A9: ACTIVO CORRIENTE | I9: ACTIVO CORRIENTE | Q9: ACTIVO CORRIENTE | Y9: ACTIVO CORRIENTE | AF9: ACTIVO CORRIENTE | AN9: Caja y Bancos | AO9: 10.30216 | AP9: 10.38613 | AQ9: 0.17525 | AT9: Caja y Bancos | AU9: 5 | AV9: 436.04914 | AY9: Caja y Bancos | AZ9: 1508.7996 | BA9: 1898.9899 | BB9: 225.14835 | BE9: Caja y Bancos | BF9: 1596.595 | BG9: 4454.011 | BH9: 4093.314 | BK9: Caja y Bancos | BL9: 2.445 | BM9: 21.376 | BN9: 117.504 | BQ9: Caja y Bancos | BR9: 45.59096 | BS9: 870.80132 | BT9: 427.34899 | BU9: 633.43317 | BX9: Caja y Bancos | BY9: 1303.768 | BZ9: 2309.795 | CA9: 20734.921 | CB9: 2337.766 | CE9: Caja y Bancos | CF9: 9195.344 | CG9: 8076.154 | CH9: 1070.0925 | CK9: Caja y Bancos | CL9: 27.097799 | CM9: 748.67315 | CN9: 671.82429 | CQ9: Caja y Bancos | CR9: 117.925 | CS9: 236.32888 | CU9: 1 | CV9: Caja y Bancos | CW9: 1783.163 | CX9: 829.43458 | CY9: 294.17044 | CZ9: 59.15145
A10: 1 | B10: Caja y Bancos | C10: 219.281 | D10: 303.998 | E10: 467.822 | F10: 0.068 | G10: 388.108 | I10: 1 | J10: Caja y Bancos | K10: 14166 | L10: 26772 | M10: 38682.088 | N10: 13331.938 | O10: 10752.389 | Q10: 1 | R10: Caja y Bancos | S10: 3585 | T10: 6100.646 | U10: 8336.164 | V10: 5940.302 | W10: 6421.995 | Y10: 1 | Z10: Caja y Bancos | AA10: 197.63 | AB10: 364.578 | AC10: 46.361 | AD10: 50.182 | AG10: Caja y Bancos | AH10: 0 | AI10: 765.951 | AJ10: 1011.194 | AK10: 101.049 | AN10: Inversiones (Certificados/ Títulos/Pagarés/Instrumentos) | AO10: 15200 | AP10: 15200 | AQ10: 15200 | AT10: Cuentas por Cobrar Clientes | AU10: 0 | AV10: 8075.5647 | AY10: Inversiones (Certificados/ Títulos/Pagarés/Instrumentos) | AZ10: 7239.1992 | BA10: 6368.213 | BB10: 6368.213 | BE10: Inversiones (Certificados/ Títulos/Pagarés/Instrumentos) | BF10: 613.2 | BG10: 613.2 | BH10: 613.2 | BK10: Inversiones (Certificados/ Títulos/Pagarés/Instrumentos) | BL10: 459828.2 | BM10: 459828.2 | BN10: 416681.37 | BQ10: Inversiones (Certificados/ Títulos/Pagarés/Instrumentos) | BR10: 0 | BS10: 8587.6104 | BT10: 11894.141 | BU10: 15523.503 | BX10: Inversiones (Certificados/ Títulos/Pagarés/Instrumentos) | BY10: 509219.65 | BZ10: 499513.15 | CA10: 399411.11 | CB10: 205352.35 | CE10: Inversiones (Certificados/ Títulos/Pagarés/Instrumentos) | CF10: 23841.436 | CG10: 3333.333 | CH10: 45770.973 | CK10: Cuentas por Cobrar Clientes | CL10: 5460.2337 | CM10: 3657.3079 | CN10: 3609.5855 | CQ10: Inversiones (Certificados/ Títulos/Pagarés/Instrumentos) | CR10: 0 | CS10: 0 | CU10: 4 | CV10: Cuentas por Cobrar Relacionadas | CW10: 0 | CX10: 0 | CY10: 892.9099 | CZ10: 892.9099
A11: 3 | B11: Cuentas por Cobrar Clientes | C11: 0 | D11: 0 | E11: 387.652 | F11: 0 | G11: 0 | I11: 2 | J11: Inversiones (Certificados/Títulos/Pagarés/Instrumentos) | K11: 45970 | L11: 126269 | M11: 0 | N11: 0 | O11: 0 | Q11: 2 | R11: Inversiones (Certificados/Títulos/Pagarés/Instrumentos) | S11: 278.98 | T11: 278.84 | U11: 278.84 | V11: 278.84 | W11: 4679.839 | Y11: 2 | Z11: Inversiones (Certificados/Títulos/Pagarés/Instrumentos) | AA11: 0 | AB11: 0 | AC11: 0 | AD11: 0 | AG11: Inversiones (Certificados/Títulos/Pagarés/Instrumentos) | AH11: 4149 | AI11: 5.914 | AJ11: 0 | AK11: 5.941 | AN11: Cuentas por Cobrar Clientes | AO11: 941.09612 | AP11: 920.00069 | AQ11: 932.01341 | AT11: Otras Cuentas por Cobrar | AU11: 0 | AV11: 991.25011 | AY11: Cuentas por Cobrar Clientes | AZ11: 19070.07 | BA11: 24998.007 | BB11: 17518.266 | BE11: Cuentas por Cobrar Clientes | BF11: 21057.765 | BG11: 26519.139 | BH11: 25176.069 | BK11: Cuentas por Cobrar Clientes | BL11: 4896.367 | BM11: 8658.035 | BN11: 7948.988 | BQ11: Cuentas por Cobrar Clientes | BR11: 12452.901 | BS11: 5655.5022 | BT11: 15975.129 | BU11: 23033.634 | BX11: Cuentas por Cobrar Clientes | BY11: 55000.387 | BZ11: 52219.487 | CA11: 60044.077 | CB11: 80798.438 | CE11: Cuentas por Cobrar Clientes | CF11: 170896.82 | CG11: 248400.58 | CH11: 326310.61 | CK11: Otras Cuentas por Cobrar | CL11: 4098.2996 | CM11: 6768.7392 | CN11: 8492.9404 | CQ11: Cuentas por Cobrar Clientes | CR11: 0 | CS11: 525.90912 | CU11: 5 | CV11: Otras Cuentas por Cobrar | CW11: 179.2345 | CX11: 123.90426 | CY11: 147.52546 | CZ11: 671.33073
A12: 4 | B12: Cuentas por Cobrar Relacionadas | C12: 21211.101 | D12: 15227.824 | E12: 23900.83 | F12: 28045.861 | G12: 25171.44 | I12: 3 | J12: Cuentas por Cobrar Clientes | K12: 15066 | L12: 14499 | M12: 13337.418 | N12: 13468.897 | O12: 19104.821 | Q12: 3 | R12: Cuentas por Cobrar Clientes | S12: 14682 | T12: 17314.2 | U12: 25084.24 | V12: 28476.013 | W12: 25199.921 | Y12: 3 | Z12: Cuentas por Cobrar Clientes | AA12: 0 | AB12: 0 | AC12: 0 | AD12: 0 | AG12: Cuentas por Cobrar Clientes | AH12: 0 | AI12: 9294.08 | AJ12: 5900.932 | AK12: 32253.842 | AN12: Impuestos | AO12: 2.02953 | AP12: 2.02953 | AQ12: 2.02953 | AT12: Impuestos | AU12: 0 | AV12: 7086.6092 | AY12: Otras Cuentas por Cobrar | AZ12: 6392.8361 | BA12: 12491.402 | BB12: 13617.278 | BE12: Otras Cuentas por Cobrar | BF12: 7380.778 | BG12: 9260.485 | BH12: 8975.67 | BK12: Cuentas por Cobrar Relacionadas | BL12: 13483.195 | BM12: 13448.041 | BN12: 13279.567 | BQ12: Cuentas por Cobrar Relacionadas | BR12: 0 | BS12: 18615.149 | BT12: 23072.723 | BU12: 17543.464 | BX12: Otras Cuentas por Cobrar | BY12: 37490.535 | BZ12: 55736.681 | CA12: 83561.713 | CB12: 76602.89 | CE12: Otras Cuentas por Cobrar | CF12: 45008.598 | CG12: 50203.721 | CH12: 55970.855 | CK12: Impuestos | CL12: 386.10319 | CM12: 490.92243 | CN12: 622.45642 | CQ12: Cuentas por Cobrar Relacionadas | CR12: 0 | CS12: 0 | CU12: 7 | CV12: IVA Crédito Fiscal | CW12: 253.033 | CX12: 945.97525 | CY12: 977.6565 | CZ12: 481.26655
A13: 5 | B13: Otras Cuentas por Cobrar | C13: 0 | D13: 0 | E13: 2501.694 | F13: 1689.761 | G13: 0 | I13: 4 | J13: Cuentas por Cobrar Relacionadas | K13: 224911 | L13: 204926 | M13: 475765.91 | N13: 556123.84 | O13: 409288.5 | Q13: 4 | R13: Cuentas por Cobrar Relacionadas | S13: 12099 | T13: 5972.802 | U13: 11191.979 | V13: 12528.005 | W13: 13489.001 | Y13: 4 | Z13: Cuentas por Cobrar Relacionadas | AA13: 12224.957 | AB13: 13252.986 | AC13: 31311.08 | AD13: 13387.562 | AG13: Cuentas por Cobrar Relacionadas | AH13: 0 | AI13: 19267.42 | AJ13: 20016.31 | AK13: 0 | AN13: Activos Biológicos de CP | AO13: 5 | AP13: 5 | AQ13: 5 | AY13: Impuestos | AZ13: 553.3086 | BA13: 1373.6288 | BB13: 1330.027 | BE13: Impuestos | BF13: 5485.768 | BG13: 7753.662 | BH13: 8638.738 | BK13: Otras Cuentas por Cobrar | BL13: 2230.989 | BM13: 4196.481 | BN13: 8261.426 | BQ13: Otras Cuentas por Cobrar | BR13: 145.51567 | BS13: 0 | BT13: 34.30854 | BU13: 346.59269 | BX13: Impuestos | BY13: 91009.488 | BZ13: 89361.003 | CA13: 74420.367 | CB13: 98694.956 | CE13: Impuestos | CF13: 48308.574 | CG13: 58829.271 | CH13: 65363.634 | CQ13: Otras Cuentas por Cobrar | CR13: 17.55 | CS13: 45 | CU13: 9 | CV13: Inventarios | CW13: 4641.469 | CX13: 9225.5937 | CY13: 12982.956 | CZ13: 12645.701
I14: 7 | J14: IVA Crédito Fiscal | K14: 29830 | L14: 32500 | M14: 0 | N14: 0 | O14: 0 | Q14: 5 | R14: Otras Cuentas por Cobrar | S14: 4499 | T14: 0 | U14: 0 | V14: 0 | W14: 7840.422 | Y14: 5 | Z14: Otras Cuentas por Cobrar | AA14: 0 | AB14: 0 | AC14: 0 | AD14: 0 | AG14: Otras Cuentas por Cobrar | AH14: 0 | AI14: 2184.715 | AJ14: 3803.379 | AK14: 4915.002 | AN14: ACTIVO CORRIENTE | AO14: 16158.428 | AP14: 16137.416 | AQ14: 16139.218 | BK14: Impuestos | BL14: 8816.64 | BM14: 9132.948 | BN14: 14491.366 | BQ14: Impuestos | BR14: 1071.5326 | BS14: 1412.5233 | BT14: 2424.7249 | BU14: 3167.1286 | CQ14: Gobierno de Guatemala | CU14: 15 | CV14: ACTIVO CORRIENTE | CW14: 6856.8995 | CX14: 11124.908 | CY14: 15295.218 | CZ14: 14750.36
I15: 8 | J15: Impuestos por cobrar | K15: 42202 | L15: 42760 | M15: 39072.231 | N15: 44778.312 | O15: 110252.67 | Q15: 7 | R15: IVA Crédito Fiscal | S15: 108635 | T15: 6074.48 | U15: 7179.542 | V15: 8529.582 | W15: 10283.608 | Y15: 6 | Z15: Gobierno de Guatemala | AG15: IVA Crédito Fiscal | AH15: 0 | AI15: 11570.202 | AJ15: 3041.632 | AK15: 2722.317 | BK15: ACTIVO CORRIENTE | BL15: 489257.84 | BM15: 495285.08 | BN15: 460780.22 | CQ15: IVA Crédito Fiscal | CU15: 20 | CV15: Maquinaria, Equipo y Herramienta | CW15: 14.285 | CX15: 14.28571
Y16: 7 | Z16: IVA Crédito Fiscal | AA16: 0 | AB16: 0 | AC16: 0 | AD16: 0 | CQ16: Impuestos | CR16: 30.217 | CS16: 206.25054 | CU16: 22 | CV16: Vehículos | CW16: 10.705 | CX16: 10.70535 | CY16: 10.70535 | CZ16: 10.70535
Y17: 8 | Z17: Impuestos por cobrar | AD17: 3178.024 | CQ17: Inventarios | CR17: 241.976 | CS17: 1541.2949 | CU17: 23 | CV17: Mobiliario y Equipo | CW17: 142.841 | CX17: 142.84113 | CY17: 286.19145 | CZ17: 286.19145
A18: 9 | B18: Inventarios | C18: 0.054 | D18: 0.004 | E18: 0 | F18: 0 | G18: 0 | I18: 9 | J18: Inventarios | K18: 82040 | L18: 69549 | M18: 58821.594 | N18: 60654.179 | O18: 152555.97 | Q18: 9 | R18: Inventarios | S18: 5924 | T18: 9027.959 | U18: 9936.311 | V18: 11853.918 | W18: 20667.477 | Y18: 9 | Z18: Inventarios | AA18: 3481.167 | AB18: 2275.958 | AC18: 2412.788 | AD18: 5320.602 | AG18: Inventarios | AH18: 0 | AI18: 3179.649 | AJ18: 4199.378 | AK18: 2754.552 | AT18: Inventarios | AU18: 0 | AV18: 1436.0616 | AY18: Inventarios | AZ18: 14964.555 | BA18: 15742.367 | BB18: 17221.702 | BE18: Inventarios | BF18: 23678.823 | BG18: 28790.548 | BH18: 26819.743 | BQ18: Inventarios | BR18: 3017.9806 | BS18: 2449.5644 | BT18: 3641.5624 | BU18: 8278.4365 | BX18: Inventarios | BY18: 149388.94 | BZ18: 135129.34 | CA18: 140786.46 | CB18: 274342.42 | CE18: Inventarios | CF18: 106027.18 | CG18: 168857.25 | CH18: 216476.4 | CK18: Inventarios | CL18: 225.88182 | CM18: 350.88182 | CN18: 3010.9329 | CQ18: Activos Biológicos de CP | CR18: 0 | CS18: 0 | CU18: 24 | CV18: Equipo de Cómputo | CW18: 67.251 | CX18: 123.53296 | CY18: 186.9362 | CZ18: 186.9362
I19: 11 | J19: Inventario de Materias Primas y Repuestos | K19: 30848 | L19: 30427 | M19: 22300.368 | N19: 34945.174 | O19: 0 | Q19: 10 | R19: Otros activos financieros a costo amortizado | S19: 0 | T19: 3140.73 | U19: 4404.015 | V19: 8225.29 | W19: 0 | Y19: 10 | Z19: Activos Biológicos de CP | AA19: 0 | AB19: 0 | AC19: 0 | AD19: 0 | AG19: Inventario de Materias Primas y Repuestos | AH19: 0 | AI19: 9594.615 | AJ19: 9594.615 | AK19: 11019.014 | AN19: Terrenos y Edificios | AO19: 1937.5 | AP19: 1937.5 | AQ19: 1937.5 | AT19: ACTIVO CORRIENTE | AU19: 5 | AV19: 18025.535 | AY19: ACTIVO CORRIENTE | AZ19: 49728.769 | BA19: 62872.607 | BB19: 56280.634 | BE19: ACTIVO CORRIENTE | BF19: 59812.929 | BG19: 77391.045 | BH19: 74316.734 | BK19: Terrenos y Edificios | BL19: 40927.962 | BM19: 40927.962 | BN19: 46483.492 | BQ19: Activo Diferido | BR19: 4100.779 | BT19: 0 | BX19: Activos Biológicos de CP | BY19: 152416.8 | BZ19: 166259.58 | CA19: 198951.18 | CB19: 228310.44 | CE19: ACTIVO CORRIENTE | CF19: 403277.95 | CG19: 537700.31 | CH19: 710962.57 | CK19: ACTIVO CORRIENTE | CL19: 10197.616 | CM19: 12016.524 | CN19: 16407.74 | CQ19: Inventario de Materias Primas y Repuestos | CR19: 0 | CS19: 0 | CU19: 25 | CV19: Otros Activos Fijos | CW19: 24.927 | CX19: 24.92798
A20: 12 | B20: Gastos Anticipados | C20: 0 | D20: 0 | E20: 0 | F20: 452.942 | G20: 0 | I20: 12 | J20: Gastos Anticipados | K20: 4138 | L20: 11471 | M20: 0 | N20: 0 | O20: 0 | Q20: 11 | R20: Inventario de Materias Primas y Repuestos | S20: 7037 | T20: 2433.912 | U20: 2840.836 | V20: 4465.012 | W20: 0 | Y20: 11 | Z20: Inventario de Materias Primas y Repuestos | AA20: 0 | AB20: 3099.5 | AC20: 2798.307 | AD20: 0 | AG20: TOTAL ACTIVO CORRIENTE | AH20: 4149 | AI20: 55862.546 | AJ20: 47567.44 | AK20: 53771.717 | AN20: Propiedad, Planta y Equipo | AO20: 1937.5 | AP20: 1937.5 | AQ20: 1937.5 | AT20: Otros Activos Fijos | AV20: 129.08187 | AY20: Terrenos y Edificios | AZ20: 5512.9789 | BA20: 5990.7122 | BB20: 5990.7122 | BE20: Terrenos y Edificios | BF20: 1430.8 | BG20: 1430.8 | BH20: 1430.8 | BK20: Instalaciones y obras civiles | BL20: 12436.298 | BM20: 12759.469 | BN20: 17613.393 | BQ20: ACTIVO CORRIENTE | BR20: 20834.299 | BS20: 37591.151 | BT20: 57469.938 | BU20: 68526.191 | BX20: Gastos precosecha | BY20: 211503.85 | BZ20: 247016.04 | CA20: 274742.23 | CB20: 327820.12 | CE20: Construcciones en Proceso | CF20: 1347.453 | CG20: 5300.249 | CH20: 18388.685 | CK20: Mejoras a Instalaciones | CL20: 65.29882 | CM20: 203.7483 | CN20: 203.74838 | CQ20: Funcionarios y Empleados | CU20: 26 | CV20: Propiedad, Planta y Equipo | CW20: 260.009 | CX20: 316.29313 | CY20: 483.833 | CZ20: 483.833
A21: 15 | B21: Otros activos corrientes | C21: 13.44 | D21: 615.944 | E21: 0 | F21: 0 | G21: 3364.291 | I21: 14 | J21: Otros activos corrientes | K21: 0 | L21: 0 | M21: 10409.053 | N21: 24411.839 | O21: 29587.734 | Q21: 13 | R21: Gastos Anticipados | S21: 0 | T21: 0 | U21: 0 | V21: 0 | W21: 428.989 | Y21: 12 | Z21: Gastos Anticipados | AA21: 267.691 | AB21: 1287.722 | AC21: 1566.337 | AD21: 0 | AF21: ACTIVOS FIJOS: PROPIEDAD, PLANTA Y EQUIPO | AN21: PROPIEDAD, PLANTA Y EQUIPO (neto) | AO21: 1937.5 | AP21: 1937.5 | AQ21: 1937.5 | AT21: Propiedad, Planta y Equipo | AU21: 0 | AV21: 129.08187 | AY21: Maquinaria, Equipo y Herramienta | AZ21: 5117.2233 | BA21: 8323.5691 | BB21: 10603.106 | BE21: Construcciones en Proceso | BF21: 97.751 | BG21: 100.576 | BH21: 100.576 | BK21: Construcciones en Proceso | BL21: 96.008 | BM21: 398.182 | BN21: 14183.671 | BQ21: Terrenos y Edificios | BU21: 2660 | BX21: ACTIVO CORRIENTE | BY21: 1207333.4 | BZ21: 1247545.1 | CA21: 1252652.1 | CB21: 1294259.4 | CE21: Maquinaria, Equipo y Herramienta | CG21: 21.428 | CH21: 21.429 | CK21: Maquinaria, Equipo y Herramienta | CL21: 6604.8758 | CM21: 6604.8758 | CN21: 7758.8055 | CQ21: Gastos Anticipados | CU21: 27 | CV21: Depreciación Acumulada (-) | CW21: -215.901 | CX21: -269.05 | CY21: -362.12911 | CZ21: -412.92128
A22: 16 | B22: TOTAL ACTIVO CORRIENTE | C22: 21443.876 | D22: 16147.77 | E22: 27257.998 | F22: 30188.632 | G22: 28923.839 | I22: 15 | J22: TOTAL ACTIVO CORRIENTE | K22: 489171 | L22: 559173 | M22: 658388.66 | N22: 747714.18 | O22: 731542.08 | Q22: 15 | R22: TOTAL ACTIVO CORRIENTE | S22: 156739.98 | T22: 50343.569 | U22: 69251.927 | V22: 80296.962 | W22: 89011.252 | Y22: 13 | Z22: Anticipo a Proveedores | AG22: Maquinaria, Equipo y Herramienta | AH22: 0 | AI22: 28392.108 | AJ22: 28763.889 | AK22: 33008.888 | AN22: TOTAL OTROS ACTIVOS | AO22: 0 | AP22: 0 | AQ22: 0 | AT22: Depreciación Acumulada (-) | AU22: 0 | AV22: 0 | AY22: Vehículos | AZ22: 2190.8746 | BA22: 2568.5039 | BB22: 2568.5039 | BE22: Maquinaria, Equipo y Herramienta | BF22: 245.042 | BG22: 247.985 | BH22: 247.985 | BK22: Maquinaria, Equipo y Herramienta | BL22: 7010.1 | BM22: 7023.492 | BN22: 7023.493 | BQ22: Maquinaria, Equipo y Herramienta | BR22: 2.63103 | BS22: 0.37575 | BT22: 14.41729 | BU22: 7.48575 | BX22: Terrenos y Edificios | BY22: 0 | BZ22: 114564.07 | CA22: 119305.23 | CB22: 122267.73 | CE22: Vehículos | CF22: 1061.769 | CG22: 1061.769 | CH22: 1061.769 | CK22: Vehículos | CL22: 129.11785 | CM22: 142.01071 | CN22: 703.47946 | CQ22: Anticipo a Proveedores | CU22: 28 | CV22: PROPIEDAD, PLANTA Y EQUIPO (neto) | CW22: 44.108 | CX22: 47.24313 | CY22: 121.70389 | CZ22: 70.91172
Y23: 14 | Z23: Créditos Fiscales | AA23: 947.235 | AB23: 2322.586 | AC23: 3694.445 | AD23: 0 | AG23: Activo Diferido | AH23: 0 | AI23: 0 | AJ23: 0 | AK23: 165.382 | AN23: TOTAL ACTIVO | AO23: 18095.928 | AP23: 18074.916 | AQ23: 18076.718 | AT23: PROPIEDAD, PLANTA Y EQUIPO (neto) | AU23: 0 | AV23: 129.08187 | AY23: Mobiliario y Equipo | AZ23: 1324.9412 | BA23: 200.33234 | BB23: 200.33234 | BE23: Vehículos | BF23: 769.454 | BG23: 789.37 | BH23: 928.791 | BK23: Vehículos | BL23: 41213.109 | BM23: 62895.831 | BN23: 46525.352 | BQ23: Vehículos | BR23: 284.40045 | BS23: 480.94971 | BT23: 1922.9298 | BU23: 530.81506 | BX23: Instalaciones y obras civiles | BY23: 0 | BZ23: 852918.21 | CA23: 885930.72 | CB23: 880164.07 | CE23: Mobiliario y Equipo | CF23: 2785.983 | CG23: 3461.277 | CH23: 3998.361 | CK23: Mobiliario y Equipo | CL23: 305.49762 | CM23: 404.32849 | CN23: 659.75551 | CQ23: ACTIVO CORRIENTE | CR23: 407.668 | CS23: 2554.7835 | CU23: 34 | CV23: TOTAL OTROS ACTIVOS | CW23: 0 | CX23: 0 | CY23: 0 | CZ23: 0
Y24: 15 | Z24: Otros activos corrientes | AA24: 0 | AB24: 0 | AC24: 0 | AD24: 71.945 | AG24: Subtotal Activos Fijos: Propiedad, Planta y Equipo | AH24: 0 | AI24: 30400.785 | AJ24: 30955.847 | AK24: 33174.27 | AT24: Gastos de Organización | AU24: 7.5 | AV24: 7.5 | AY24: Equipo de Cómputo | AZ24: 872.30448 | BA24: 272.25507 | BB24: 272.25507 | BE24: Mobiliario y Equipo | BF24: 245.74 | BG24: 306.351 | BH24: 309.985 | BK24: Mobiliario y Equipo | BL24: 10867.467 | BM24: 12936.183 | BN24: 16235.297 | BQ24: Mobiliario y Equipo | BR24: 24.91852 | BS24: 14.41624 | BT24: 29.7336 | BU24: 5.39205 | BX24: Maquinaria, Equipo y Herramienta | BY24: 0 | BZ24: 405529.23 | CA24: 412164.03 | CB24: 454824.45 | CE24: Equipo de Cómputo | CF24: 1560.74 | CG24: 2483.927 | CH24: 3840.796 | CK24: Equipo de Cómputo | CL24: 133.69395 | CM24: 133.69395 | CN24: 133.69395 | CQ24: Terrenos y Edificios | CU24: 35 | CV24: TOTAL ACTIVO | CW24: 6901.0075 | CX24: 11172.151 | CY24: 15416.922 | CZ24: 14821.271
Y25: 16 | Z25: TOTAL ACTIVO CORRIENTE | AA25: 17118.68 | AB25: 22603.33 | AC25: 41829.318 | AD25: 22008.315 | AG25: Depreciación Acumulada (-) | AH25: 0 | AI25: -18449.081 | AJ25: -20298.672 | AK25: -22202.915 | AN25: PASIVO CORRIENTE | AO25: 0 | AP25: 0 | AQ25: 0 | AT25: TOTAL OTROS ACTIVOS | AU25: 7.5 | AV25: 7.5 | AY25: Otros Activos Fijos | AZ25: 1329.3856 | BA25: 1145.7195 | BB25: 1145.7195 | BE25: Equipo de Cómputo | BF25: 222.241 | BG25: 320.451 | BH25: 323.932 | BK25: Equipo de Cómputo | BL25: 1350.093 | BM25: 2740.582 | BN25: 3387.618 | BQ25: Equipo de Cómputo | BR25: 77.12312 | BS25: 55.06513 | BT25: 40.8125 | BU25: 56.13315 | BX25: Vehículos | BY25: 0 | BZ25: 69950.308 | CA25: 75555.917 | CB25: 85517.599 | CE25: Propiedad, Planta y Equipo | CF25: 6755.945 | CG25: 12328.65 | CH25: 27311.04 | CK25: Propiedad, Planta y Equipo | CL25: 7238.484 | CM25: 7488.6572 | CN25: 9459.4828 | CQ25: Instalaciones y obras civiles
A26: ACTIVOS FIJOS: PROPIEDAD, PLANTA Y EQUIPO | I26: ACTIVOS FIJOS: PROPIEDAD, PLANTA Y EQUIPO | Q26: ACTIVOS FIJOS: PROPIEDAD, PLANTA Y EQUIPO | Y26: ACTIVOS FIJOS: PROPIEDAD, PLANTA Y EQUIPO | AG26: PROPIEDAD, PLANTA Y EQUIPO (neto) | AH26: 0 | AI26: 11951.704 | AJ26: 10657.175 | AK26: 10971.355 | AN26: Cuentas por Pagar LP | AO26: 5.89476 | AQ26: 0 | AT26: TOTAL ACTIVO | AU26: 12.5 | AV26: 18162.117 | AY26: Propiedad, Planta y Equipo | AZ26: 16347.708 | BA26: 18501.092 | BB26: 20780.629 | BE26: Propiedad, Planta y Equipo | BF26: 3011.028 | BG26: 3195.533 | BH26: 3342.069 | BK26: Otros Activos Fijos | BL26: 1953.602 | BM26: 16092.191 | BN26: 26296.914 | BQ26: Otros Activos Fijos | BR26: 429.75155 | BS26: 24.02801 | BT26: 10.41581 | BU26: 2.86137 | BX26: Mobiliario y Equipo | BY26: 0 | BZ26: 363355.95 | CA26: 363959.8 | CB26: 326068.13 | CE26: Depreciación Acumulada (-) | CF26: -4598.095 | CG26: -6259.373 | CH26: -8178.749 | CK26: Depreciación Acumulada (-) | CL26: -3647.0224 | CM26: -3647.0224 | CN26: -3316.7604 | CQ26: Construcciones en Proceso
I27: 16 | J27: Terrenos y Edificios | K27: 58054 | L27: 51873 | M27: 0 | N27: 0 | O27: 0 | Q27: 16 | R27: Edificios e Instalaciones | S27: 10925 | T27: 26300.778 | U27: 23715.271 | V27: 28567.047 | W27: 29221.778 | Y27: 17 | Z27: Terrenos y Edificios | AG27: Cuentas por Cobrar a Relacionadas de L.P. | AH27: 0 | AI27: 11319.385 | AJ27: 20216.327 | AK27: 14995.304 | AN27: PASIVO NO CORRIENTE | AO27: 5.89476 | AP27: 0 | AQ27: 0 | AV27: 0 | AY27: Depreciación Acumulada (-) | BB27: 0 | BE27: Depreciación Acumulada (-) | BF27: -1203.923 | BG27: -1452.702 | BH27: -1529.055 | BK27: Propiedad, Planta y Equipo | BL27: 115854.64 | BM27: 155773.89 | BN27: 177749.23 | BQ27: Propiedad, Planta y Equipo | BR27: 818.82467 | BS27: 574.83484 | BT27: 2018.309 | BU27: 3263.6498 | BX27: Equipo de Cómputo | BY27: 0 | BZ27: 12203.466 | CA27: 12805.699 | CB27: 12902.94 | CE27: PROPIEDAD, PLANTA Y EQUIPO (neto) | CF27: 2157.85 | CG27: 6069.277 | CH27: 19132.291 | CK27: PROPIEDAD, PLANTA Y EQUIPO (neto) | CL27: 3591.4617 | CM27: 3841.6349 | CN27: 6142.7224 | CQ27: Plantaciones de Caña
I28: 17 | J28: Instalaciones y obras civiles | K28: 42183 | L28: 43456 | M28: 0 | N28: 0 | O28: 0 | Q28: 27 | R28: Subtotal Activos Fijos: Propiedad, Planta y Equipo | S28: 25948 | T28: 26300.778 | U28: 23715.271 | V28: 28567.047 | W28: 29221.778 | Y28: 18 | Z28: Instalaciones y obras civiles | AG28: TOTAL OTROS ACTIVOS | AH28: 0 | AI28: 11319.385 | AJ28: 20216.327 | AK28: 14995.304 | AN28: TOTAL PASIVO | AO28: 5.89476 | AP28: 0 | AQ28: 0 | AT28: Porción Corriente No Bancarias | AV28: 1517.881 | AY28: PROPIEDAD, PLANTA Y EQUIPO (neto) | AZ28: 16347.708 | BA28: 18501.092 | BB28: 20780.629 | BE28: PROPIEDAD, PLANTA Y EQUIPO (neto) | BF28: 1807.105 | BG28: 1742.831 | BH28: 1813.014 | BK28: Depreciación Acumulada (-) | BL28: -44364.334 | BM28: -53133.562 | BN28: -61649.073 | BQ28: Depreciación Acumulada (-) | BR28: -323.2547 | BS28: -379.52225 | BT28: -549.19017 | BU28: -282.16308 | BX28: Otros Activos Fijos | BY28: 1074320.7 | BZ28: -4031.162 | CA28: -6234.923 | CB28: 95995.851 | CE28: Marcas y Patentes | CF28: 5951.627 | CG28: 5951.627 | CH28: 5951.627 | CK28: TOTAL OTROS ACTIVOS | CL28: 0 | CM28: 0 | CN28: 0 | CQ28: Maquinaria, Equipo y Herramienta | CR28: 0 | CS28: 0
I29: 18 | J29: Construcciones en Proceso | K29: 7791 | L29: 5995 | M29: 0 | N29: 0 | O29: 0 | Q29: 28 | R29: Depreciación Acumulada (-) | S29: 0 | T29: 0 | U29: 0 | V29: 0 | W29: 0 | Y29: 19 | Z29: Construcciones en Proceso | AB29: 1689.486 | AC29: 2505.577 | AG29: TOTAL ACTIVO | AH29: 4149 | AI29: 79133.635 | AJ29: 78440.942 | AK29: 79738.376 | AN29: Capital Pagado | AO29: 2000 | AP29: 2000 | AQ29: 2000 | AT29: Impuestos por Pagar | AU29: 0 | AV29: 777.17908 | AY29: Cuentas por Cobrar a Relacionadas de Largo Plazo | AZ29: 4372.5589 | BA29: 2125.3835 | BB29: 2125.3849 | BE29: Marcas y Patentes | BF29: 12.811 | BG29: 250.039 | BH29: 235.915 | BK29: PROPIEDAD, PLANTA Y EQUIPO (neto) | BL29: 71490.305 | BM29: 102640.33 | BN29: 116100.16 | BQ29: PROPIEDAD, PLANTA Y EQUIPO (neto) | BR29: 495.56997 | BS29: 195.31259 | BT29: 1469.1188 | BU29: 2981.4867 | BX29: Propiedad, Planta y Equipo | BY29: 1074320.7 | BZ29: 1814490.1 | CA29: 1863486.5 | CB29: 1977740.8 | CE29: TOTAL OTROS ACTIVOS | CF29: 5951.627 | CG29: 5951.627 | CH29: 5951.627 | CK29: TOTAL ACTIVO | CL29: 13789.078 | CM29: 15858.159 | CN29: 22550.462 | CQ29: Materiales y repuestos
I30: 20 | J30: Maquinaria, Equipo y Herramienta | K30: 142121 | L30: 124902 | M30: 183901.7 | N30: 221052.02 | O30: 95615.306 | Q30: 29 | R30: PROPIEDAD, PLANTA Y EQUIPO (neto) | S30: 25948 | T30: 26300.778 | U30: 23715.271 | V30: 28567.047 | W30: 29221.778 | Y30: 20 | Z30: Plantaciones de Caña | AN30: Aportaciones por Capitalizar | AO30: 14879.185 | AP30: 14858.537 | AQ30: 14858.257 | AT30: Otras cuentas por pagar | AU30: 7.5 | AV30: 12035.121 | AY30: TOTAL OTROS ACTIVOS | AZ30: 4372.5589 | BA30: 2125.3835 | BB30: 2125.3849 | BE30: TOTAL OTROS ACTIVOS | BF30: 12.811 | BG30: 250.039 | BH30: 235.915 | BK30: Marcas y Patentes | BL30: 3297.461 | BM30: 4455.227 | BN30: 5384.058 | BQ30: Marcas y Patentes | BR30: 1479.4846 | BS30: 1392.3783 | BT30: 1305.272 | BU30: 1218.1657 | BX30: Depreciación Acumulada (-) | BY30: 0 | BZ30: -825733.24 | CA30: -871961.98 | CB30: -942492 | CE30: TOTAL ACTIVO | CF30: 411387.43 | CG30: 549721.22 | CH30: 736046.49 | CQ30: Vehículos | CR30: 0 | CS30: 0
I31: 22 | J31: Vehículos | K31: 4450 | L31: 4298 | M31: 0 | N31: 0 | O31: 0 | Q31: 30 | R31: Activos intangibles | S31: 30351 | T31: 30351.24 | U31: 30351.24 | V31: 30351.24 | W31: 30351.24 | Y31: 21 | Z31: Maquinaria, Equipo y Herramienta | AB31: 945.096 | AC31: 683.986 | AF31: PASIVO CORRIENTE | AN31: Reservas | AO31: 44.22588 | AP31: 44.22588 | AQ31: 44.22588 | AT31: PASIVO CORRIENTE | AU31: 7.5 | AV31: 14330.181 | AY31: TOTAL ACTIVO | AZ31: 70449.036 | BA31: 83499.083 | BB31: 79186.648 | BE31: TOTAL ACTIVO | BF31: 61632.845 | BG31: 79383.915 | BH31: 76365.663 | BK31: TOTAL OTROS ACTIVOS | BL31: 3297.461 | BM31: 4455.227 | BN31: 5384.058 | BQ31: Gastos de Organización | BR31: 661.75697 | BS31: 563.71766 | BT31: 465.67838 | BU31: 367.6391 | BX31: PROPIEDAD, PLANTA Y EQUIPO (neto) | BY31: 1074320.7 | BZ31: 988756.83 | CA31: 991524.48 | CB31: 1035248.8 | CK31: Proveedores | CL31: 765.0985 | CM31: 757.72108 | CN31: 1126.4137 | CQ31: Mobiliario y Equipo | CR31: 0 | CS31: 0 | CU31: 36 | CV31: Préstamos no Bancarios | CW31: 274.136 | CX31: 2087.9733 | CY31: 143.73359 | CZ31: 885.31976
I32: 23 | J32: Mobiliario y Equipo | K32: 15355 | L32: 15000 | M32: 0 | N32: 0 | O32: 0 | Q32: 31 | R32: Cuentas por Cobrar a Relacionadas de L.P. | S32: 0 | T32: 7753.363 | U32: 2320.992 | V32: 6389.589 | W32: 19758.36 | Y32: 22 | Z32: Materiales y repuestos | AG32: Proveedores | AH32: 0 | AI32: 9493.161 | AJ32: 8845.636 | AK32: 11780.171 | AN32: Utilidades Acumuladas | AO32: 1166.902 | AP32: 1166.622 | AQ32: 1172.4339 | AT32: PASIVO NO CORRIENTE | AU32: 0 | AV32: 0 | BF32: 0 | BK32: TOTAL ACTIVO | BL32: 564045.6 | BM32: 602380.64 | BN32: 582264.43 | BQ32: TOTAL OTROS ACTIVOS | BR32: 2141.2416 | BS32: 1956.096 | BT32: 1770.9504 | BU32: 1585.8048 | BX32: Cuentas por Cobrar a Relacionadas de Largo Plazo | BY32: 8968.307 | BZ32: 19772.419 | CA32: 12101.736 | CE32: Proveedores | CF32: 181356.57 | CG32: 249616.46 | CH32: 409004.96 | CK32: Impuestos por Pagar | CL32: 51.2604 | CM32: 141.80182 | CN32: 140.75902 | CQ32: Equipo de Cómputo | CR32: 3.749 | CS32: 32.09395 | CU32: 39 | CV32: Proveedores | CW32: 0 | CX32: 3557.5964 | CY32: 758.8798 | CZ32: 2051.1672
I33: 24 | J33: Equipo de Cómputo | K33: 39919 | L33: 40033 | M33: 0 | N33: 0 | O33: 0 | Q33: 32 | R33: Activos de derecho de uso | S33: 4062 | T33: 15287.065 | U33: 12178.625 | V33: 11363.427 | W33: 10791.562 | Y33: 23 | Z33: Vehículos | AG33: Impuestos por Pagar | AH33: 0 | AI33: 1459.251 | AJ33: 1088.722 | AK33: 839.323 | AN33: Utilidad del Ejercicio | AO33: -0.28 | AP33: 5.53129 | AQ33: 1.80184 | AT33: TOTAL PASIVO | AU33: 7.5 | AV33: 14330.181 | AY33: Porción Corriente de la D.B. de L.P. | AZ33: 28381.898 | BA33: 33918.558 | BB33: 33918.558 | BE33: Proveedores | BF33: 7412.341 | BG33: 4610.936 | BH33: 269.496 | BQ33: TOTAL ACTIVO | BR33: 23471.111 | BS33: 39742.559 | BT33: 60710.007 | BU33: 73093.482 | BX33: activo biologico a largo plazo | BY33: 123234.41 | BZ33: 115619.68 | CA33: 107032.77 | CB33: 98694.956 | CE33: Impuestos por Pagar | CF33: 2146.514 | CG33: 2956.72 | CH33: 2211.581 | CK33: PASIVO CORRIENTE | CL33: 816.3589 | CM33: 899.5229 | CN33: 1267.1727 | CQ33: Otros Activos Fijos | CR33: 0 | CS33: 0 | CU33: 45 | CV33: Impuestos por Pagar | CW33: 53.745 | CX33: 169.45457 | CY33: 773.61848 | CZ33: 26.601615
I34: 26 | J34: Otros Activos Fijos | K34: 6462 | L34: 9819 | M34: 0 | N34: 0 | O34: 0 | Q34: 33 | R34: Impuesto sobre la renta diferido, L.P. | S34: 0 | T34: 6188.536 | U34: 1095.01 | V34: 2592.901 | W34: 2145.317 | Y34: 24 | Z34: Mobiliario y Equipo | AB34: 20.875 | AC34: 15.342 | AG34: Otras cuentas por pagar | AH34: 0 | AI34: 3379.814 | AJ34: 3392.147 | AK34: 2034.919 | AN34: TOTAL PATRIMONIO | AO34: 18090.033 | AP34: 18074.916 | AQ34: 18076.718 | AT34: Capital Pagado | AU34: 5 | AV34: 490 | AY34: Cuentas por Pagar | AZ34: 7742.7185 | BA34: 4908.5143 | BB34: 4697.9563 | BE34: Impuestos por Pagar | BF34: 172.436 | BG34: 152.251 | BH34: 332.598 | BK34: Porción Corriente de la D.B. de L.P. | BL34: 3503.891 | BM34: 2341.886 | BT34: 0 | BX34: TOTAL OTROS ACTIVOS | BY34: 132202.72 | BZ34: 135392.1 | CA34: 119134.51 | CB34: 98694.956 | CE34: Otras cuentas por pagar | CF34: 86215.093 | CG34: 199065.8 | CH34: 214808.17 | CK34: Deuda Bancaria Largo Plazo | CL34: 1291.9569 | CM34: 785.48835 | CN34: 3429.3175 | CQ34: Propiedad, Planta y Equipo | CR34: 3.749 | CS34: 32.09395 | CU34: 46 | CV34: Otras cuentas por pagar | CW34: 2466.6185 | CX34: 2591.4821 | CY34: 1007.7085 | CZ34: 186.74568
I35: 27 | J35: Subtotal Activos Fijos: Propiedad, Planta y Equipo | K35: 316335 | L35: 295376 | M35: 183901.7 | N35: 221052.02 | O35: 95615.306 | Q35: 34 | R35: Impuestos por cobrar, L.P. | S35: 0 | T35: 5595.623 | U35: 5139.42 | V35: 6574.83 | W35: 7982.494 | Y35: 25 | Z35: Equipo de Cómputo | AB35: 5.576 | AC35: 3.417 | AG35: TOTAL PASIVO CORRIENTE | AH35: 0 | AI35: 22040.14 | AJ35: 20790.369 | AK35: 14654.413 | AN35: TOTAL PASIVO + PATRIMONIO | AO35: 18095.928 | AP35: 18074.916 | AQ35: 18076.718 | AT35: Aportaciones por Capitalizar | AU35: 0 | AV35: 3000 | AY35: Impuestos por Pagar | AZ35: 156.75977 | BA35: 94.66515 | BB35: 99.25771 | BE35: PASIVO CORRIENTE | BF35: 7584.777 | BG35: 4763.187 | BH35: 602.094 | BK35: Proveedores | BL35: 16496.579 | BM35: 30961.074 | BN35: 15660.375 | BQ35: Prestamos a corto plazo | BR35: 0 | BS35: 0 | BT35: 18601.971 | BU35: 22123.917 | BX35: TOTAL ACTIVO | BY35: 2413856.8 | BZ35: 2371694 | CA35: 2363311 | CB35: 2428203.1 | CE35: PASIVO CORRIENTE | CF35: 269718.17 | CG35: 451638.98 | CH35: 626024.71 | CK35: PASIVO NO CORRIENTE | CL35: 1291.9569 | CM35: 785.48835 | CN35: 3429.3175 | CQ35: Depreciación Acumulada (-) | CR35: -0.41652 | CS35: -4.44762 | CU35: 49 | CV35: PASIVO CORRIENTE | CW35: 2794.4995 | CX35: 8406.5064 | CY35: 2683.9404 | CZ35: 3149.8343
I36: 28 | J36: Depreciación Acumulada (-) | K36: -199056.72 | L36: -190039 | M36: 0 | N36: 0 | O36: 0 | Q36: 35 | R36: Otros Activos LP: activos financieros, inversiones | S36: 0 | T36: 1.728 | U36: 34.374 | V36: 0 | W36: 0 | Y36: 26 | Z36: Activo Diferido | AA36: 0 | AB36: 0 | AC36: 0 | AD36: 0 | AF36: PASIVO NO CORRIENTE | AT36: Utilidad del Ejercicio | AU36: 0 | AV36: 341.9356 | AY36: Otras cuentas por pagar | AZ36: 405.07512 | BA36: 412.27961 | BB36: 717.06405 | BE36: Deuda Bancaria Largo Plazo | BF36: 25245.176 | BG36: 43906.206 | BH36: 43685.168 | BK36: Impuestos por Pagar | BL36: 13192.852 | BM36: 16982.156 | BN36: 22915.269 | BQ36: Proveedores | BR36: 1691.6603 | BS36: 7421.15 | BT36: 658.96935 | BU36: 822.87784 | BY36: 0 | CA36: 0 | CB36: 0 | CE36: Cuentas por Pagar a Relacionadas | CF36: 3542.761 | CG36: 321.476 | CH36: 321.476 | CK36: TOTAL PASIVO | CL36: 2108.3158 | CM36: 1685.0113 | CN36: 4696.4903 | CQ36: PROPIEDAD, PLANTA Y EQUIPO (neto) | CR36: 3.33248 | CS36: 27.64633 | CU36: 50 | CV36: Deuda Bancaria Largo Plazo | CW36: 0 | CX36: 97.46402 | CY36: 8532.5861 | CZ36: 7195.3633
